<?xml version="1.0" encoding="UTF-8"?>
<writ><QW nameCN="全文" value="甘肃省西和县人民法院 刑事判决书 （2015）西刑初字第19号 公诉机关：西和县人民检察院。 被告人常某某，男，生于1994年8月25日，汉族。2015年1月10日因涉嫌交通肇事罪被西和县公安局刑事拘留，同年2月12日被西和县人民检察院批准逮捕，现羁押于西和县看守所。 辩护人刘某某，西和县法律援助中心律师。 西和县人民检察院以西检刑诉（2015）第14号起诉书指控被告人常某某犯交通肇事罪，于2015年4月2日向本院提起公诉。本院依法组成合议庭于2015年4月16日公开开庭进行了审理。西和县人民检察院指派代理检察员张建新出庭支持公诉，被告人常某某及其辩护人刘某某到庭参加了诉讼。现已审理终结。 公诉机关指控：2015年1月4日12时许，被告人常某某驾驶“南方”牌二轮弯梁摩托车（车上乘坐赵某某）由西和县城驶往西和县十里乡张集村，当摩托车行驶至西和县十里乡段集村路段时将正在该路段行走回家的柳某某（女，75岁）撞倒，致柳某某受伤，2015年1月18日经西和县公安司法鉴定中心法医学人体损伤程度鉴定：柳某某损伤程度属重伤一级。事故发生后被告人常某某驾驶摩托车逃逸。后柳某某被家人送往西和县人民医院救治，因伤情严重同日又转送天水市第一人民医院救治，2015年2月14日出院回家。同年2月28日上午柳某某又因伤情危重被送往西和县人民医院救治，2月29日上午10时柳某某经抢救无效死亡，经西和县人民医院诊断柳某某死亡原因为：脑外伤后遗症、多器官功能衰竭、电解质紊乱。经西和县公安局交通警察大队道路交通事故认定书认定：常某某承担本次事故的全部责任，柳某某无责任。2015年1月9日被告人常某某被抓获归案。其行为已触犯《中华人民共和国刑法》第一百三十三条之规定，构成交通肇事罪，要求依法判处。证据有物证、书证、证人证言、被告人供述、现场勘查笔录、鉴定意见等证据在卷相互印证。根据量刑规范化的规定，认为被告人常某某在发生交通肇事后逃逸；在审查起诉阶段认罪态度较好。建议对被告人常某某判处四年以上六年以下有期徒刑。 被告人常某某对起诉书指控的犯罪事实供认不讳，未提出辩解意见。辩护人的辩护意见是：一是起诉书指控被告人交通肇事致人死亡与事实不符，事故发生后被害人的伤情鉴定为重伤一级，事故发生后近两个月死亡，其死亡原因并不是本起交通事故直接造成的，与被害人年老体弱、身体本身多病等因素有关，起诉书认定经西和县人民医院诊断柳某某死亡原因为：脑外伤后遗症、多器官功能衰竭、电解质紊乱，本案交通事故对被害人造成的伤害后果是重伤。二是被告人具有认罪态度好、积极赔偿被害人家属损失，本案属过失犯罪的酌定从轻处罚情节。 经审理查明：2015年1月4日12时许，被告人常某某驾驶“南方”牌二轮弯梁摩托车（车上乘坐赵某某）由西和县城驶往西和县十里乡张集村，当摩托车行驶至西和县十里乡段集村路段时将正在该路段行走回家的柳某某（女，75岁）撞倒，致柳某某受伤，2015年1月18日经西和县公安司法鉴定中心法医学人体损伤程度鉴定：柳某某损伤程度属重伤一级。事故发生后被告人常某某驾驶摩托车逃逸。后柳某某被家人送往西和县人民医院救治，因伤情严重同日又转送天水市第一人民医院救治，2015年2月14日出院回家。同年2月28日上午柳某某又因伤情危重被送往西和县人民医院救治，2月29日上午10时柳某某经抢救无效死亡，经西和县人民医院诊断柳某某死亡原因为：脑外伤后遗症、多器官功能衰竭、电解质紊乱。经西和县公安局交通警察大队道路交通事故认定书认定：常某某承担本次事故的全部责任，柳某某无责任。2015年1月9日被告人常某某被抓获归案。 事故发生后被告人常某某家属与被害人家属达成了由常某某一次性支付被害人医疗费135000元，被害人家属放弃要求被告人赔偿被害人的死亡赔偿金、丧葬费等其他费用的协议，并已履行。被害人家属对被告人的行为予以谅解并请求从轻处罚。 上述事实有公诉机关出示的书证西和县公安局受案登记表、立案决定书、拘留证、逮捕证、扣押物品清单，道路交通事故认定书，户籍证明，天水市第一人民医院住院证、病历、CT检查报告单、诊断证明、出院证明书，西和县人民医院诊断证明、出院证明、死亡通知书，被害人柳某某家属自愿要求对被害人尸体不再做进一步尸体解剖的申请；证人王某、卢某某、赵某某的证言；被告人供述；现场勘查笔录、事故现场图及现场照片；西和县公安司法鉴定中心法医学人体损伤程度鉴定意见书。被告人的辩护人出示的书证事故调解协议书、收条、谅解书、西和县十里乡张集村委会证明等证据在卷相互印证。 以上证据在庭审中经举证、质证，证据来源合法，反映内容客观真实，能够相互印证，合议庭当庭予以确认和采信。 本院认为，被告人常某某目无国法，违反交通运输管理法规，无证驾驶机动车，发生交通事故致被害人柳某某受重伤，被害人当日被家人送往西和县人民医院救治，因伤情严重同日又转送天水市第一人民医院救治，2015年2月14日出院回家。同年2月28日上午柳某某又因伤情危重被送往西和县人民医院救治，2月29日上午10时柳某某经抢救无效死亡，经西和县人民医院诊断柳某某死亡原因为：脑外伤后遗症、多器官功能衰竭、电解质紊乱。被告人常某某交通肇事的行为是造成被害人柳某某死亡的原因之一，其交通肇事的行为与被害人柳某某的死亡具有因果关系，肇事后逃逸，且承担事故的全部责任，其行为已构成交通肇事罪。西和县人民检察院指控被告人常某某犯交通肇事罪的事实清楚，证据确实充分，罪名成立。被告人无证驾驶无号牌机动车，酌定从重处罚；被告人当庭自愿认罪，积极赔偿被害人大部分损失并取得谅解的，且被告人交通肇事的行为不是造成被害人死亡的唯一原因，被害人的死亡是多种原因共同作用的结果，酌定从轻处罚。辩护人关于起诉书指控被告人交通肇事致人死亡与事实不符，被害人死亡并不是本起交通事故直接造成的，本案交通事故对被害人造成的伤害后果是重伤的辩护意见，与审理查明的事实不符，不予采纳。辩护人关于被告人具有认罪态度好、积极赔偿被害人家属损失，本案属过失犯罪的酌定从轻处罚情节的辩护意见，与审理查明的事实相符且符合法律规定，予以采纳。看守所关于被告人常某某羁押期间遵守监规、服从监管、表现好，建议从轻处罚的意见符合法律规定，予以采纳。本案属过失犯罪，被告人认罪态度好，放归社会不致发生危险，依法适用缓刑。本案经合议庭根据量刑规范化的规定评议并经本院审判委员会讨论决定，依据《中华人民共和国刑法》第一百三十三条、第七十二条之规定，判决如下： 被告人常某某犯交通肇事罪，判处有期徒刑三年，缓刑四年。 （缓刑考验期限，从判决确定之日起计算。） 如不服本判决，可在接到判决书的第二日起十日内，通过本院或者直接向甘肃省陇南市中级人民法院提起上诉，书面上诉的，应当提交上诉状正本一份，副本二份。 审判长黄海林 代理审判员成鹏 代理审判员王昱 二〇一五年六月十日 书记员胡勤福 "><WS nameCN="文首" value="甘肃省西和县人民法院 刑事判决书 （2015）西刑初字第19号"><WSZZDW nameCN="文书制作单位" value="法院"/><FYWSZL nameCN="法院文书种类" value="裁判文书"/><JBFY nameCN="经办法院" value="甘肃省西和县人民法院"><FYCJM nameCN="法院层级码" value="SA6"/><BZFYMC nameCN="标准法院名称" value="西和县人民法院"/><FYJB nameCN="法院级别" value="基层"/><XZQH_P nameCN="行政区划(省)" value="甘肃"/><XZQH_C nameCN="行政区划(市)" value="陇南市"/></JBFY><WSMC nameCN="文书名称" value="刑事判决书"/><AH nameCN="案号" value="（2015）西刑初字第19号"><ZH nameCN="字号" value="刑初字"/><LAND nameCN="立案年度" value="2015"/><FYJC nameCN="法院简称" value="西"/><AHSXH nameCN="案号顺序号" value="19"/></AH><AJLB nameCN="案件类别" value="刑事案件"/><WSZL nameCN="文书种类" value="判决书"/><SPCX nameCN="审判程序" value="一审案件"/><AJLX nameCN="案件类型" value="刑事一审案件"/></WS><DSR nameCN="当事人" value=" 公诉机关：西和县人民检察院。 被告人常某某，男，生于1994年8月25日，汉族。2015年1月10日因涉嫌交通肇事罪被西和县公安局刑事拘留，同年2月12日被西和县人民检察院批准逮捕，现羁押于西和县看守所。 辩护人刘某某，西和县法律援助中心律师。"><GSF nameCN="公诉方" value="公诉机关：西和县人民检察院。"><SSCYR nameCN="诉讼参与人" value="西和县人民检察院"/><SSSF nameCN="诉讼身份" value="公诉机关"/><DSRLB nameCN="当事人类别" value="公诉机关"/><BSSSDW nameCN="本审诉讼地位" value="公诉机关"/></GSF><YSF nameCN="应诉方" value="被告人常某某，男，生于1994年8月25日，汉族。2015年1月10日因涉嫌交通肇事罪被西和县公安局刑事拘留，同年2月12日被西和县人民检察院批准逮捕，现羁押于西和县看守所。"><SSCYR nameCN="诉讼参与人" value="常某某"><SFMH nameCN="是否模糊" value="是"/></SSCYR><SSSF nameCN="诉讼身份" value="被告人"/><DSRLX nameCN="当事人类型" value="自然人"/><XB nameCN="性别" value="男"/><MZ nameCN="民族" value="汉族"/><CSRQ nameCN="出生日期" value="1994年8月25日"/><GJ nameCN="国籍" value="中国"/><DSRLB nameCN="当事人类别" value="被告人"/><QZCS nameCN="强制措施"><QZCSZL nameCN="强制措施种类" value="拘留"/><QZCSZXSJ nameCN="强制措施执行时间" value="2015年1月10日"/><QZCSZXDW nameCN="强制措施执行单位" value="西和县公安局"/><QZCSYYFZ nameCN="强制措施原因组"><QZCSYY nameCN="强制措施原因" value="交通肇事罪"/></QZCSYYFZ></QZCS><QZCS nameCN="强制措施"><QZCSZL nameCN="强制措施种类" value="逮捕"/><QZCSPZSJ nameCN="强制措施批准时间" value="2015年2月12日"/><QZCSPZDW nameCN="强制措施批准单位" value="西和县人民检察院"/></QZCS><JYCS nameCN="羁押场所" value="西和县看守所"/><BDBRQ nameCN="被逮捕日期" value="2015年2月12日"/><PZDBJG nameCN="批准逮捕机关" value="检察院"/><HXKYQNFZ nameCN="缓刑考验期内犯罪" value="否"/><JSKYQNFZ nameCN="假释考验期内犯罪" value="否"/><XSZRNL nameCN="刑事责任能力" value="完全刑事责任能力"/><BSSSDW nameCN="本审诉讼地位" value="被告人"/><SFBHR nameCN="是否被害人" value="否"/><ZRRSF nameCN="自然人身份" value="其他"/></YSF><DLR nameCN="代理人" value="辩护人刘某某，西和县法律援助中心律师。"><SSCYR nameCN="诉讼参与人" value="刘某某"><SFMH nameCN="是否模糊" value="是"/></SSCYR><SSSF nameCN="诉讼身份" value="辩护人"/><DSRLX nameCN="当事人类型" value="自然人"/><DWZWFZ nameCN="单位职务分组"><ZW nameCN="职务" value="律师"/><DWMC nameCN="单位名称" value="西和县法律援助中心"/><DWXZ nameCN="单位性质" value="事业单位"/></DWZWFZ><GJ nameCN="国籍" value="中国"/><DSRLB nameCN="当事人类别" value="代理人"/><CYRSSDW nameCN="参与人诉讼地位" value="辩护人"/><BHZL nameCN="辩护种类" value="委托辩护"/><BHDX nameCN="辩护对象" value="常某某"/><DLRBHRZYLX nameCN="代理人辩护人职业类型" value="职业律师"/><BHRHSSDLRLX nameCN="辩护人或诉讼代理人类型" value="承担法律援助的律师"/><ZRRSF nameCN="自然人身份" value="职员"/></DLR><BGRQX nameCN="被告人缺席" value="无缺席"/></DSR><SSJL nameCN="诉讼记录" value=" 西和县人民检察院以西检刑诉（2015）第14号起诉书指控被告人常某某犯交通肇事罪，于2015年4月2日向本院提起公诉。本院依法组成合议庭于2015年4月16日公开开庭进行了审理。西和县人民检察院指派代理检察员张建新出庭支持公诉，被告人常某某及其辩护人刘某某到庭参加了诉讼。现已审理终结。"><KTSL nameCN="开庭审理" value="是"/><KTSLXX nameCN="开庭审理信息" value="公开审理"/><KTRQ nameCN="开庭日期" value="2015年4月16日"/><CTJCYs nameCN="出庭检察员"><JCYFZ nameCN="检察员分组"><JS nameCN="角色" value="代理检察员"/><JCY nameCN="检察员" value="张建新"/></JCYFZ></CTJCYs><SSXZ nameCN="诉讼性质" value="公诉"/><QSRQ nameCN="起诉日期" value="2015年4月2日"/><JCYJYYQSL nameCN="检察院建议延期审理" value="否"/><SNFT nameCN="少年法庭" value="否"/><ZKXX nameCN="指控信息"><ZKJL nameCN="指控记录"><ZKZM nameCN="指控罪名" value="交通肇事罪"><ZMDM nameCN="罪名代码" value="51"/><WZZM nameCN="完整罪名" value="交通肇事罪"/></ZKZM><XGR nameCN="相关人" value="常某某"/></ZKJL></ZKXX><QSZAY nameCN="起诉主案由" value="交通肇事罪"><ZMDM nameCN="罪名代码" value="51"/><WZZM nameCN="完整罪名" value="交通肇事罪"/></QSZAY><YSAJSYCX nameCN="一审案件适用程序" value="普通程序"/><JYSYJYCX nameCN="建议适用简易程序" value="无"/><DRSP nameCN="独任审判" value="否"/><YSAJLY nameCN="一审案件来源" value="新收公诉"/><GSJG nameCN="公诉机关" value="西和县人民检察院"/><GSAH nameCN="公诉案号" value="西检刑诉（2015）第14号"/><JYZPT nameCN="简易转普通" value="否"/><SPZZ nameCN="审判组织" value="合议庭"/><CTDSRXX nameCN="出庭当事人信息"><CTRXM nameCN="出庭人姓名" value="常某某"><SSDW nameCN="诉讼地位" value="被告人"/></CTRXM><CTRXM nameCN="出庭人姓名" value="刘某某"><SSDW nameCN="诉讼地位" value="辩护人"/></CTRXM></CTDSRXX></SSJL><AJJBQK nameCN="案件基本情况" value=" 公诉机关指控：2015年1月4日12时许，被告人常某某驾驶“南方”牌二轮弯梁摩托车（车上乘坐赵某某）由西和县城驶往西和县十里乡张集村，当摩托车行驶至西和县十里乡段集村路段时将正在该路段行走回家的柳某某（女，75岁）撞倒，致柳某某受伤，2015年1月18日经西和县公安司法鉴定中心法医学人体损伤程度鉴定：柳某某损伤程度属重伤一级。事故发生后被告人常某某驾驶摩托车逃逸。后柳某某被家人送往西和县人民医院救治，因伤情严重同日又转送天水市第一人民医院救治，2015年2月14日出院回家。同年2月28日上午柳某某又因伤情危重被送往西和县人民医院救治，2月29日上午10时柳某某经抢救无效死亡，经西和县人民医院诊断柳某某死亡原因为：脑外伤后遗症、多器官功能衰竭、电解质紊乱。经西和县公安局交通警察大队道路交通事故认定书认定：常某某承担本次事故的全部责任，柳某某无责任。2015年1月9日被告人常某某被抓获归案。其行为已触犯《中华人民共和国刑法》第一百三十三条之规定，构成交通肇事罪，要求依法判处。证据有物证、书证、证人证言、被告人供述、现场勘查笔录、鉴定意见等证据在卷相互印证。根据量刑规范化的规定，认为被告人常某某在发生交通肇事后逃逸；在审查起诉阶段认罪态度较好。建议对被告人常某某判处四年以上六年以下有期徒刑。 被告人常某某对起诉书指控的犯罪事实供认不讳，未提出辩解意见。辩护人的辩护意见是：一是起诉书指控被告人交通肇事致人死亡与事实不符，事故发生后被害人的伤情鉴定为重伤一级，事故发生后近两个月死亡，其死亡原因并不是本起交通事故直接造成的，与被害人年老体弱、身体本身多病等因素有关，起诉书认定经西和县人民医院诊断柳某某死亡原因为：脑外伤后遗症、多器官功能衰竭、电解质紊乱，本案交通事故对被害人造成的伤害后果是重伤。二是被告人具有认罪态度好、积极赔偿被害人家属损失，本案属过失犯罪的酌定从轻处罚情节。 经审理查明：2015年1月4日12时许，被告人常某某驾驶“南方”牌二轮弯梁摩托车（车上乘坐赵某某）由西和县城驶往西和县十里乡张集村，当摩托车行驶至西和县十里乡段集村路段时将正在该路段行走回家的柳某某（女，75岁）撞倒，致柳某某受伤，2015年1月18日经西和县公安司法鉴定中心法医学人体损伤程度鉴定：柳某某损伤程度属重伤一级。事故发生后被告人常某某驾驶摩托车逃逸。后柳某某被家人送往西和县人民医院救治，因伤情严重同日又转送天水市第一人民医院救治，2015年2月14日出院回家。同年2月28日上午柳某某又因伤情危重被送往西和县人民医院救治，2月29日上午10时柳某某经抢救无效死亡，经西和县人民医院诊断柳某某死亡原因为：脑外伤后遗症、多器官功能衰竭、电解质紊乱。经西和县公安局交通警察大队道路交通事故认定书认定：常某某承担本次事故的全部责任，柳某某无责任。2015年1月9日被告人常某某被抓获归案。 事故发生后被告人常某某家属与被害人家属达成了由常某某一次性支付被害人医疗费135000元，被害人家属放弃要求被告人赔偿被害人的死亡赔偿金、丧葬费等其他费用的协议，并已履行。被害人家属对被告人的行为予以谅解并请求从轻处罚。 上述事实有公诉机关出示的书证西和县公安局受案登记表、立案决定书、拘留证、逮捕证、扣押物品清单，道路交通事故认定书，户籍证明，天水市第一人民医院住院证、病历、CT检查报告单、诊断证明、出院证明书，西和县人民医院诊断证明、出院证明、死亡通知书，被害人柳某某家属自愿要求对被害人尸体不再做进一步尸体解剖的申请；证人王某、卢某某、赵某某的证言；被告人供述；现场勘查笔录、事故现场图及现场照片；西和县公安司法鉴定中心法医学人体损伤程度鉴定意见书。被告人的辩护人出示的书证事故调解协议书、收条、谅解书、西和县十里乡张集村委会证明等证据在卷相互印证。 以上证据在庭审中经举证、质证，证据来源合法，反映内容客观真实，能够相互印证，合议庭当庭予以确认和采信。 "><ZZQK nameCN="质证情况" value="质证"/><BHR nameCN="被害人"><BHRXM nameCN="被害人姓名" value="柳某某"/><SFSW nameCN="是否死亡" value="是"/><BHRXB nameCN="被害人性别" value="女"/></BHR><ZKDL nameCN="指控段落" value=" 公诉机关指控：2015年1月4日12时许，被告人常某某驾驶“南方”牌二轮弯梁摩托车（车上乘坐赵某某）由西和县城驶往西和县十里乡张集村，当摩托车行驶至西和县十里乡段集村路段时将正在该路段行走回家的柳某某（女，75岁）撞倒，致柳某某受伤，2015年1月18日经西和县公安司法鉴定中心法医学人体损伤程度鉴定：柳某某损伤程度属重伤一级。事故发生后被告人常某某驾驶摩托车逃逸。后柳某某被家人送往西和县人民医院救治，因伤情严重同日又转送天水市第一人民医院救治，2015年2月14日出院回家。同年2月28日上午柳某某又因伤情危重被送往西和县人民医院救治，2月29日上午10时柳某某经抢救无效死亡，经西和县人民医院诊断柳某某死亡原因为：脑外伤后遗症、多器官功能衰竭、电解质紊乱。经西和县公安局交通警察大队道路交通事故认定书认定：常某某承担本次事故的全部责任，柳某某无责任。2015年1月9日被告人常某某被抓获归案。其行为已触犯《中华人民共和国刑法》第一百三十三条之规定，构成交通肇事罪，要求依法判处。证据有物证、书证、证人证言、被告人供述、现场勘查笔录、鉴定意见等证据在卷相互印证。根据量刑规范化的规定，认为被告人常某某在发生交通肇事后逃逸；在审查起诉阶段认罪态度较好。建议对被告人常某某判处四年以上六年以下有期徒刑。 "><ZKSS nameCN="指控事实" value="公诉机关指控：2015年1月4日12时许，被告人常某某驾驶“南方”牌二轮弯梁摩托车（车上乘坐赵某某）由西和县城驶往西和县十里乡张集村，当摩托车行驶至西和县十里乡段集村路段时将正在该路段行走回家的柳某某（女，75岁）撞倒，致柳某某受伤，2015年1月18日经西和县公安司法鉴定中心法医学人体损伤程度鉴定：柳某某损伤程度属重伤一级。事故发生后被告人常某某驾驶摩托车逃逸。后柳某某被家人送往西和县人民医院救治，因伤情严重同日又转送天水市第一人民医院救治，2015年2月14日出院回家。同年2月28日上午柳某某又因伤情危重被送往西和县人民医院救治，2月29日上午10时柳某某经抢救无效死亡，经西和县人民医院诊断柳某某死亡原因为：脑外伤后遗症、多器官功能衰竭、电解质紊乱。经西和县公安局交通警察大队道路交通事故认定书认定：常某某承担本次事故的全部责任，柳某某无责任。2015年1月9日被告人常某某被抓获归案。"/><ZKZJ nameCN="指控证据" value="证据有物证、书证、证人证言、被告人供述、现场勘查笔录、鉴定意见等证据在卷相互印证。根据量刑规范化的规定，认为被告人常某某在发生交通肇事后逃逸；在审查起诉阶段认罪态度较好。建议对被告人常某某判处四年以上六年以下有期徒刑。"><ZJXX nameCN="证据信息"><ZJFZ nameCN="证据分组"><ZJJL nameCN="证据记录" value="在卷相互印证。根据量刑规范化的规定，认为被告人常某某在发生交通肇事后逃逸；在审查起诉阶段认罪态度较好。建议对被告人常某某判处四年以上六年以下有期徒刑。"><ZJMX nameCN="证据明细"><MC nameCN="名称" value="在卷相互印证"/><ZL nameCN="种类" value="其他"/></ZJMX></ZJJL></ZJFZ></ZJXX></ZKZJ><ZKYJ nameCN="指控意见" value="其行为已触犯《中华人民共和国刑法》第一百三十三条之规定，构成交通肇事罪，要求依法判处。"/></ZKDL><BHDL nameCN="辩护段落" value="被告人常某某对起诉书指控的犯罪事实供认不讳，未提出辩解意见。辩护人的辩护意见是：一是起诉书指控被告人交通肇事致人死亡与事实不符，事故发生后被害人的伤情鉴定为重伤一级，事故发生后近两个月死亡，其死亡原因并不是本起交通事故直接造成的，与被害人年老体弱、身体本身多病等因素有关，起诉书认定经西和县人民医院诊断柳某某死亡原因为：脑外伤后遗症、多器官功能衰竭、电解质紊乱，本案交通事故对被害人造成的伤害后果是重伤。二是被告人具有认罪态度好、积极赔偿被害人家属损失，本案属过失犯罪的酌定从轻处罚情节。 "><BGRBC nameCN="被告人辩称" value="被告人常某某对起诉书指控的犯罪事实供认不讳，未提出辩解意见。"/><BHRBH nameCN="辩护人辩护" value="辩护人的辩护意见是：一是起诉书指控被告人交通肇事致人死亡与事实不符，事故发生后被害人的伤情鉴定为重伤一级，事故发生后近两个月死亡，其死亡原因并不是本起交通事故直接造成的，与被害人年老体弱、身体本身多病等因素有关，起诉书认定经西和县人民医院诊断柳某某死亡原因为：脑外伤后遗症、多器官功能衰竭、电解质紊乱，本案交通事故对被害人造成的伤害后果是重伤。二是被告人具有认罪态度好、积极赔偿被害人家属损失，本案属过失犯罪的酌定从轻处罚情节。"><BHYJ nameCN="辩护意见"><BGRXM nameCN="被告人姓名" value="常某某"/><BHYJZL nameCN="辩护意见种类" value="罪轻辩护"/></BHYJ></BHRBH></BHDL><BSSLD nameCN="本审审理段" value="经审理查明：2015年1月4日12时许，被告人常某某驾驶“南方”牌二轮弯梁摩托车（车上乘坐赵某某）由西和县城驶往西和县十里乡张集村，当摩托车行驶至西和县十里乡段集村路段时将正在该路段行走回家的柳某某（女，75岁）撞倒，致柳某某受伤，2015年1月18日经西和县公安司法鉴定中心法医学人体损伤程度鉴定：柳某某损伤程度属重伤一级。事故发生后被告人常某某驾驶摩托车逃逸。后柳某某被家人送往西和县人民医院救治，因伤情严重同日又转送天水市第一人民医院救治，2015年2月14日出院回家。同年2月28日上午柳某某又因伤情危重被送往西和县人民医院救治，2月29日上午10时柳某某经抢救无效死亡，经西和县人民医院诊断柳某某死亡原因为：脑外伤后遗症、多器官功能衰竭、电解质紊乱。经西和县公安局交通警察大队道路交通事故认定书认定：常某某承担本次事故的全部责任，柳某某无责任。2015年1月9日被告人常某某被抓获归案。 事故发生后被告人常某某家属与被害人家属达成了由常某某一次性支付被害人医疗费135000元，被害人家属放弃要求被告人赔偿被害人的死亡赔偿金、丧葬费等其他费用的协议，并已履行。被害人家属对被告人的行为予以谅解并请求从轻处罚。 上述事实有公诉机关出示的书证西和县公安局受案登记表、立案决定书、拘留证、逮捕证、扣押物品清单，道路交通事故认定书，户籍证明，天水市第一人民医院住院证、病历、CT检查报告单、诊断证明、出院证明书，西和县人民医院诊断证明、出院证明、死亡通知书，被害人柳某某家属自愿要求对被害人尸体不再做进一步尸体解剖的申请；证人王某、卢某某、赵某某的证言；被告人供述；现场勘查笔录、事故现场图及现场照片；西和县公安司法鉴定中心法医学人体损伤程度鉴定意见书。被告人的辩护人出示的书证事故调解协议书、收条、谅解书、西和县十里乡张集村委会证明等证据在卷相互印证。 以上证据在庭审中经举证、质证，证据来源合法，反映内容客观真实，能够相互印证，合议庭当庭予以确认和采信。 "><ZRXX nameCN="证人信息"><ZR nameCN="证人" value="王某"/><ZR nameCN="证人" value="卢某某"/><ZR nameCN="证人" value="赵某某"/></ZRXX></BSSLD></AJJBQK><CPFXGC nameCN="裁判分析过程" value="本院认为，被告人常某某目无国法，违反交通运输管理法规，无证驾驶机动车，发生交通事故致被害人柳某某受重伤，被害人当日被家人送往西和县人民医院救治，因伤情严重同日又转送天水市第一人民医院救治，2015年2月14日出院回家。同年2月28日上午柳某某又因伤情危重被送往西和县人民医院救治，2月29日上午10时柳某某经抢救无效死亡，经西和县人民医院诊断柳某某死亡原因为：脑外伤后遗症、多器官功能衰竭、电解质紊乱。被告人常某某交通肇事的行为是造成被害人柳某某死亡的原因之一，其交通肇事的行为与被害人柳某某的死亡具有因果关系，肇事后逃逸，且承担事故的全部责任，其行为已构成交通肇事罪。西和县人民检察院指控被告人常某某犯交通肇事罪的事实清楚，证据确实充分，罪名成立。被告人无证驾驶无号牌机动车，酌定从重处罚；被告人当庭自愿认罪，积极赔偿被害人大部分损失并取得谅解的，且被告人交通肇事的行为不是造成被害人死亡的唯一原因，被害人的死亡是多种原因共同作用的结果，酌定从轻处罚。辩护人关于起诉书指控被告人交通肇事致人死亡与事实不符，被害人死亡并不是本起交通事故直接造成的，本案交通事故对被害人造成的伤害后果是重伤的辩护意见，与审理查明的事实不符，不予采纳。辩护人关于被告人具有认罪态度好、积极赔偿被害人家属损失，本案属过失犯罪的酌定从轻处罚情节的辩护意见，与审理查明的事实相符且符合法律规定，予以采纳。看守所关于被告人常某某羁押期间遵守监规、服从监管、表现好，建议从轻处罚的意见符合法律规定，予以采纳。本案属过失犯罪，被告人认罪态度好，放归社会不致发生危险，依法适用缓刑。本案经合议庭根据量刑规范化的规定评议并经本院审判委员会讨论决定，依据《中华人民共和国刑法》第一百三十三条、第七十二条之规定，判决如下："><LXQJ nameCN="量刑情节"><ZDLXQJ nameCN="酌定量刑情节"><XGR nameCN="相关人" value="常某某"/><QJ nameCN="情节" value="认罪态度好"/><LXQJLB nameCN="量刑情节类别" value="酌定从轻情节"/></ZDLXQJ><ZDLXQJ nameCN="酌定量刑情节"><XGR nameCN="相关人" value="常某某"/><QJ nameCN="情节" value="主动取得被害人谅解"/><LXQJLB nameCN="量刑情节类别" value="酌定从轻情节"/></ZDLXQJ><ZDLXQJ nameCN="酌定量刑情节"><XGR nameCN="相关人" value="常某某"/><QJ nameCN="情节" value="犯罪后采取补救措施降低损失"/><LXQJLB nameCN="量刑情节类别" value="酌定从轻情节"/></ZDLXQJ><ZDLXQJ nameCN="酌定量刑情节"><XGR nameCN="相关人" value="常某某"/><QJ nameCN="情节" value="其他"/><LXQJLB nameCN="量刑情节类别" value="酌定从重情节"/></ZDLXQJ></LXQJ><BGRTYRZCX nameCN="被告人同意认罪程序" value="是"/><FLFTYY nameCN="法律法条引用"><FLFTFZ nameCN="法律法条分组"><MC nameCN="名称" value="《中华人民共和国刑法》"/><T nameCN="条" value="第一百三十三条"/><T nameCN="条" value="第七十二条"/></FLFTFZ></FLFTYY><CUS_FLFT_FZ_RY nameCN="法律法条分组冗余"><CUS_FLFT_RY nameCN="法律法条" value="《中华人民共和国刑法》第一百三十三条"/><CUS_FLFT_RY nameCN="法律法条" value="《中华人民共和国刑法》第七十二条"/></CUS_FLFT_FZ_RY></CPFXGC><PJJG nameCN="判决结果" value=" 被告人常某某犯交通肇事罪，判处有期徒刑三年，缓刑四年。 （缓刑考验期限，从判决确定之日起计算。） 如不服本判决，可在接到判决书的第二日起十日内，通过本院或者直接向甘肃省陇南市中级人民法院提起上诉，书面上诉的，应当提交上诉状正本一份，副本二份。"><GXQYY nameCN="提出管辖权异议" value="否"/><YSJAFS nameCN="一审结案方式" value="判决"/><YSXSBFCPJG nameCN="一审刑事部分裁判结果" value="判决"/><XSPJJGFZ nameCN="刑事判决结果分组"><SSCYR nameCN="诉讼参与人" value="常某某"/><BSPJJG nameCN="本审判决结果"><DZPF nameCN="单罪判罚" value="犯交通肇事罪，判处有期徒刑三年，缓刑四年。"><ZM nameCN="罪名" value="交通肇事罪"><ZMDM nameCN="罪名代码" value="51"/><WZZM nameCN="完整罪名" value="交通肇事罪"/></ZM><HX nameCN="缓刑"><HXLB nameCN="缓刑类别" value="普通缓刑"/><HXXQ nameCN="缓刑刑期" value="四年"/></HX><ZX nameCN="主刑"><ZXLB nameCN="主刑类别" value="有期徒刑"/><ZXXQ nameCN="主刑刑期" value="三年"/></ZX><PJJGLX nameCN="判决结果类型" value="给予刑事处罚"/></DZPF><ZXPF nameCN="执行判罚" value="犯交通肇事罪，判处有期徒刑三年，缓刑四年。"><HX nameCN="缓刑"><HXLB nameCN="缓刑类别" value="普通缓刑"/><HXXQ nameCN="缓刑刑期" value="四年"/></HX><ZX nameCN="主刑"><ZXLB nameCN="主刑类别" value="有期徒刑"/><ZXXQ nameCN="主刑刑期" value="三年"/></ZX><PJJGLX nameCN="判决结果类型" value="给予刑事处罚"/></ZXPF><PJZZM nameCN="判决主罪名" value="交通肇事罪"><ZMDM nameCN="罪名代码" value="51"/><WZZM nameCN="完整罪名" value="交通肇事罪"/></PJZZM></BSPJJG><MXHWZSF nameCN="免刑或无罪释放" value="否"/><SZBF nameCN="数罪并罚" value="否"/><HBLX nameCN="合并量刑" value="否"/></XSPJJGFZ><KSSZ nameCN="可上诉至" value="甘肃省陇南市中级人民法院"/><SSTJCL nameCN="上诉提交材料" value="上诉状正本一份，副本二份"/><SSQX nameCN="上诉期限" value="十日"/></PJJG><WW nameCN="文尾" value=" 审判长黄海林 代理审判员成鹏 代理审判员王昱 二〇一五年六月十日 书记员胡勤福 "><CPSJ nameCN="裁判时间" value="2015年6月10日"><JAND nameCN="结案年度" value="2015"/><CUS_JANYR nameCN="结案年月日" value="2015年6月10日"/><CUS_JANY nameCN="结案年月" value="2015-6"/><CUS_JAYF nameCN="结案月份" value="6"/></CPSJ><SPZZCY nameCN="审判组织成员"><SPRYXM nameCN="审判人员姓名" value="黄海林"/><SPRYJS nameCN="审判人员角色" value="审判长"/></SPZZCY><SPZZCY nameCN="审判组织成员"><SPRYXM nameCN="审判人员姓名" value="成鹏"/><SPRYJS nameCN="审判人员角色" value="代理审判员"/></SPZZCY><SPZZCY nameCN="审判组织成员"><SPRYXM nameCN="审判人员姓名" value="王昱"/><SPRYJS nameCN="审判人员角色" value="代理审判员"/></SPZZCY><SPZZCY nameCN="审判组织成员"><SPRYXM nameCN="审判人员姓名" value="胡勤福"/><SPRYJS nameCN="审判人员角色" value="书记员"/></SPZZCY></WW><WSSFMH nameCN="文书是否模糊" value="是"/><CUS_SJ nameCN="时间"><CUS_YW nameCN="原文" value="西和县人民检察院以西检刑诉（2015）第14号起诉书指控被告人常某某犯交通肇事罪，于2015年4月2日向本院提起公诉"/><CUS_SJYW nameCN="时间原文" value="西和县人民检察院以西检刑诉（2015）第14号起诉书指控被告人常某某犯交通肇事罪，于2015年4月2日向本院提起公诉"/><CUS_JTSJ nameCN="具体时间" value="2015年4月2日"/></CUS_SJ><CUS_SJ nameCN="时间"><CUS_YW nameCN="原文" value="本院依法组成合议庭于2015年4月16日公开开庭进行了审理"/><CUS_SJYW nameCN="时间原文" value="本院依法组成合议庭于2015年4月16日公开开庭进行了审理"/><CUS_JTSJ nameCN="具体时间" value="2015年4月16日"/></CUS_SJ><CUS_SJ nameCN="时间"><CUS_YW nameCN="原文" value="公诉机关指控：2015年1月4日12时许，被告人常某某驾驶“南方”牌二轮弯梁摩托车（车上乘坐赵某某）由西和县城驶往西和县十里乡张集村，当摩托车行驶至西和县十里乡段集村路段时将正在该路段行走回家的柳某某（女，75岁）撞倒，致柳某某受伤，2015年1月18日经西和县公安司法鉴定中心法医学人体损伤程度鉴定：柳某某损伤程度属重伤一级"/><CUS_SJYW nameCN="时间原文" value="公诉机关指控：2015年1月4日12时许，被告人常某某驾驶“南方”牌二轮弯梁摩托车（车上乘坐赵某某）由西和县城驶往西和县十里乡张集村，当摩托车行驶至西和县十里乡段集村路段时将正在该路段行走回家的柳某某（女，75岁）撞倒，致柳某某受伤，2015年1月18日经西和县公安司法鉴定中心法医学人体损伤程度鉴定：柳某某损伤程度属重伤一级"/><CUS_JTSJ nameCN="具体时间" value="2015年1月4日"/></CUS_SJ><CUS_SJ nameCN="时间"><CUS_YW nameCN="原文" value="后柳某某被家人送往西和县人民医院救治，因伤情严重同日又转送天水市第一人民医院救治，2015年2月14日出院回家"/><CUS_SJYW nameCN="时间原文" value="后柳某某被家人送往西和县人民医院救治，因伤情严重2015年1月18日又转送天水市第一人民医院救治，2015年2月14日出院回家"/><CUS_JTSJ nameCN="具体时间" value="2015年1月18日"/></CUS_SJ><CUS_SJ nameCN="时间"><CUS_YW nameCN="原文" value="同年2月28日上午柳某某又因伤情危重被送往西和县人民医院救治，2月29日上午10时柳某某经抢救无效死亡，经西和县人民医院诊断柳某某死亡原因为：脑外伤后遗症、多器官功能衰竭、电解质紊乱"/><CUS_SJYW nameCN="时间原文" value="2015年2月28日上午柳某某又因伤情危重被送往西和县人民医院救治，2015年3月1日上午10时柳某某经抢救无效死亡，经西和县人民医院诊断柳某某死亡原因为：脑外伤后遗症、多器官功能衰竭、电解质紊乱"/><CUS_JTSJ nameCN="具体时间" value="2015年2月28日"/></CUS_SJ><CUS_SJ nameCN="时间"><CUS_YW nameCN="原文" value="2015年1月9日被告人常某某被抓获归案"/><CUS_SJYW nameCN="时间原文" value="2015年1月9日被告人常某某被抓获归案"/><CUS_JTSJ nameCN="具体时间" value="2015年1月9日"/></CUS_SJ><CUS_SJ nameCN="时间"><CUS_YW nameCN="原文" value="经审理查明：2015年1月4日12时许，被告人常某某驾驶“南方”牌二轮弯梁摩托车（车上乘坐赵某某）由西和县城驶往西和县十里乡张集村，当摩托车行驶至西和县十里乡段集村路段时将正在该路段行走回家的柳某某（女，75岁）撞倒，致柳某某受伤，2015年1月18日经西和县公安司法鉴定中心法医学人体损伤程度鉴定：柳某某损伤程度属重伤一级"/><CUS_SJYW nameCN="时间原文" value="经审理查明：2015年1月4日12时许，被告人常某某驾驶“南方”牌二轮弯梁摩托车（车上乘坐赵某某）由西和县城驶往西和县十里乡张集村，当摩托车行驶至西和县十里乡段集村路段时将正在该路段行走回家的柳某某（女，75岁）撞倒，致柳某某受伤，2015年1月18日经西和县公安司法鉴定中心法医学人体损伤程度鉴定：柳某某损伤程度属重伤一级"/><CUS_JTSJ nameCN="具体时间" value="2015年1月4日"/></CUS_SJ><CUS_SJ nameCN="时间"><CUS_YW nameCN="原文" value="后柳某某被家人送往西和县人民医院救治，因伤情严重同日又转送天水市第一人民医院救治，2015年2月14日出院回家"/><CUS_SJYW nameCN="时间原文" value="后柳某某被家人送往西和县人民医院救治，因伤情严重2015年1月18日又转送天水市第一人民医院救治，2015年2月14日出院回家"/><CUS_JTSJ nameCN="具体时间" value="2015年1月18日"/></CUS_SJ><CUS_SJ nameCN="时间"><CUS_YW nameCN="原文" value="同年2月28日上午柳某某又因伤情危重被送往西和县人民医院救治，2月29日上午10时柳某某经抢救无效死亡，经西和县人民医院诊断柳某某死亡原因为：脑外伤后遗症、多器官功能衰竭、电解质紊乱"/><CUS_SJYW nameCN="时间原文" value="2015年2月28日上午柳某某又因伤情危重被送往西和县人民医院救治，2015年3月1日上午10时柳某某经抢救无效死亡，经西和县人民医院诊断柳某某死亡原因为：脑外伤后遗症、多器官功能衰竭、电解质紊乱"/><CUS_JTSJ nameCN="具体时间" value="2015年2月28日"/></CUS_SJ><CUS_SJ nameCN="时间"><CUS_YW nameCN="原文" value="2015年1月9日被告人常某某被抓获归案"/><CUS_SJYW nameCN="时间原文" value="2015年1月9日被告人常某某被抓获归案"/><CUS_JTSJ nameCN="具体时间" value="2015年1月9日"/></CUS_SJ><CUS_SJ nameCN="时间"><CUS_YW nameCN="原文" value="本院认为，被告人常某某目无国法，违反交通运输管理法规，无证驾驶机动车，发生交通事故致被害人柳某某受重伤，被害人当日被家人送往西和县人民医院救治，因伤情严重同日又转送天水市第一人民医院救治，2015年2月14日出院回家"/><CUS_SJYW nameCN="时间原文" value="本院认为，被告人常某某目无国法，违反交通运输管理法规，无证驾驶机动车，发生交通事故致被害人柳某某受重伤，被害人2015年1月9日被家人送往西和县人民医院救治，因伤情严重2015年1月9日又转送天水市第一人民医院救治，2015年2月14日出院回家"/><CUS_JTSJ nameCN="具体时间" value="2015年1月9日"/></CUS_SJ><CUS_SJ nameCN="时间"><CUS_YW nameCN="原文" value="同年2月28日上午柳某某又因伤情危重被送往西和县人民医院救治，2月29日上午10时柳某某经抢救无效死亡，经西和县人民医院诊断柳某某死亡原因为：脑外伤后遗症、多器官功能衰竭、电解质紊乱"/><CUS_SJYW nameCN="时间原文" value="2015年2月28日上午柳某某又因伤情危重被送往西和县人民医院救治，2015年3月1日上午10时柳某某经抢救无效死亡，经西和县人民医院诊断柳某某死亡原因为：脑外伤后遗症、多器官功能衰竭、电解质紊乱"/><CUS_JTSJ nameCN="具体时间" value="2015年2月28日"/></CUS_SJ><title value="常某某犯交通肇事罪"/><subTitle value="刑事一审判决书"/><slzq value="69"/></QW></writ>