<?xml version="1.0" encoding="UTF-8"?>
<writ><QW nameCN="全文" value=" 河南省淮阳县人民法院 刑事判决书 （2014）淮刑初字第28号 公诉机关淮阳县人民检察院。 被告人王东廷，男，1958年10月13日，汉族，小学文化，无业，住淮阳县城关镇南关村银张庄30号。因涉嫌交通肇事，于2013年8月30日拘留，同年9月7日被执行逮捕。现押于淮阳县看守所。 辩护人蔡静，女，系河南众望律师事务所律师。 淮阳县人民检察院以淮检刑诉（2014）21号起诉书指控被告人王东廷犯交通肇事罪，于2014年2月20日向本院提起公诉，本院审查后，依法组成合议庭，公开开庭审理了本案。淮阳县人民检察院代理检察员朱晓峰出庭支持公诉，被告人王东廷及其辩护人蔡静到庭参加了诉讼，本案现已审理终结。 淮阳县人民检察院指控：2013年8月29日7时许，被告人王东廷驾驶一辆电动三轮车由东向西行驶至淮阳县大同街商城北门路段时，与由北向南步行的叶孝珍发生相撞，致叶孝珍受伤入院经抢救无效死亡及电动车受损的交通事故，被告人王东廷肇事后逃逸。经认定，王东廷负此事故的全部责任。当日18时许，被告人王东廷到淮阳县公安局投案自首。 被告人辩称：我构不成交通肇事逃逸。 辩护人辩称：被告人王东廷构不成交通肇事逃逸，其主观上没有逃逸的故意。被告人有投案自首情节，且已经赔偿了受害人的经济损失，应当减轻处罚。 经审理查明：2013年8月29日7时许，被告人王东廷驾驶一辆电动三轮车由东向西行驶至淮阳县大同街商城北门路段时，与由北向南步行的叶孝珍发生相撞，致叶某某受伤入院经抢救无效死亡及电动车受损的交通事故，被告人王东廷肇事后逃逸。经认定，王东廷负此事故的全部责任。当日18时许，被告人王东廷到淮阳县公安局投案自首。2013年8月31日被告人赔偿受害人17000元丧葬费。2014年3月10日经本院调解，被告人方赔偿受害人150000元。 上述事实，经公诉机关提交，并经法庭举证、质证、认证的有下列证据予以证实： 户籍证明、前科证明。2、叶孝珍火化证。3、交通事故认定。4、交通事故车辆技术检验报告。5、雷东、马旭东人民医院医生书写的证言2013年8月29日7时许在城关镇大同街商城北门出诊及跟车的老头否认自己是肇事司机的事实。6、发破案报告书。7、现场勘查笔录。8、鉴定意见书。9、证人叶某某证言，我不知道事情经过，在2013年8月29日8时，我给我父亲打电话，没有打通，然后就回家找他没有找着，我在家等他，等到10时多时间，我又回到城内店里面，又给我父亲打了一个电话，还是关机，我又骑着电动车回家看看，还是没有回家，等到12点多，又回到城里店内，在12时35分有一个人给我打电话，是用俺爸的手机给我打的，他说我爸被人撞着拉医院去了，我就骑摩托车去找，找到老人民医院找，人家说：确实有一个老头，没有抢救过来，拉太平间里去了。到医院太平间，一看就是俺爸叶某某。10、证人董某某证言，2013年8月29日7时许，我开机动三轮前往西关公交车上送货，当行驶到商城东路口时，看到商城北门对面，大同路的北侧，倒一辆红色的电动三轮车，头朝商城，是往西翻的，我走到跟前，有几个人将电动三轮车扶起来，从红色三轮车下来一个人有60多岁，平头，头高170多，身材较胖，没有看见穿的啥衣服，他拿着手机报的120，他说在商城北门我碰着人啦，赶紧过来将他拉走。也看一个老头朝东北扒着，面朝东面，鼻子出血，当时旁边围很多人。在现场西侧有10米远，在路中间，捡个手机没有电了，我回去后充了电，给手机的家人打电话，他们说手机是他爸的手机。11、证人贺某某证言，当时我骑着电车从由西往东在路南走着，开始没有注意拉人的电三轮和其他人，我听见路北边一声响，我顺着声音看，在路北一辆红色电动三轮车翻车，碰伤一步行的老年人，三轮车压步行人身上了，过路的人都帮着将三轮车抬开以后，看见受伤者流好多血，开电动三轮车也是年纪大的人，说快打120，然后到车里找他的手机，我看见开三轮车的人找到手机以后，我有事走了。不知开三轮车的打没有打120。12、证人马某某证言，2013年8月30日早起7时左右，我院120车去大同路商城北门去接诊，到现场看见一辆红色的拉客的电动三轮车，撞着一个老头，我们将伤者抬到120车上，要求伤者的家属去一个人，没有家属在场。开三轮车的司机是一个50多岁，大高个子，身材一般胖瘦，是他跟着120车一块去的医院，由于伤情严重，我们一块将伤者送到北关人民医院，我就回来了。我们问那老头是不是伤者的家属，他说不是哩，我又问他是不是司机，他说：他不是司机，司机走罢了。13、证人王某某证言，2013年8月29日具体几点我记不住了，是上午，我叔用他的手机给我打电话说：他碰着人了，他和碰伤的人都在北关人民医院，我到北关人民医院，见到我叔王东延，并询问伤者病情，医生说：人伤的不轻。我就让我叔王东延报警。然后我从医院回家了，中午我到交警问情况，见到办案警官，办案警官说：人不行了，该投案投案。当天下午（几点记不清了）。我回到家，见到我叔王东延说了说情况。然后我就和我叔王东延一块来交警队投案。14、被告人王东廷供述，我来交通大队投案自首。2013年8月29日7时许，我驾驶电动三轮在大同路从东向西行驶，准备去西关车站，行驶到商城北门路段时，从路北的美食广场由北向南过来一个男的，我看见后刹车，没有刹住，往南打方向，我车的右侧后部撞着那个人了，我的车也刹车刹翻了，车头朝南，我赶紧出来，车压着那个人的腿哩，其他帮忙把车掀起来，我叫人打120，我也打了120，我的手机号15896755051，120车去了后，我也跟着去医院，给伤者拍CT，打上针，我有200元钱，给他交上，当时写的是无名者，后来医生说还交钱。我从医院回来找钱，没有回家又到现场把我的车开回家了。就去找钱，家里没有，又到周口找着俺闺女了，找了几千元钱。又到医院听说人死了，我就回家了。这个时间下午约三点的时间，到了下午6时左右，我就到交警队投案了。我是9点左右13673555676报的110，报警之后我的电话打不通是因为我的手机摔的接触不良。我是下午2点接的民警电话，我说叫王东廷，心里害怕，没有说家庭住址。 辩护人提交的证据：1、照片。2、周口市开发区陈营行 政村蔡扎卫生室证明。3、医院收费条。辩护人提交的该组证据的目的证明被告人王东廷没有逃逸的动机。 本院认为，被告人王东廷违反道路运输管理法规，致一人死亡，且肇事后逃逸，其行为已构成了交通肇事罪，淮阳县人民检察院指控的罪名成立，本院予以支持。被告人及其辩护人的辩解理由及提交的证据与庭审查明事实不符本院不予采纳。案发后被告人王东廷主动投案自首如实供述自己的罪行，属自首，且赔偿了受害人的经济损失，判处缓刑不至于再危害社会，为达到法律效果和社会效果相统一的原则，可以对其适用缓刑故依照《中华人民共和国刑法》第一百三十三条、第六十七条第一款、第七十二条第一款、第七十三条第二款、第三款之规定，判决如下： 被告人王东廷犯交通肇事罪，判处有期徒刑三年缓刑三年。 （缓刑考验期从判决确定之日起计算）。 如不服本判决，可在接到判决书的第二日起十日内，通过本院或者直接向河南省周口市中级人民法院提出上诉，书面上诉的，应当提交上诉状正本一份，副本二份。 审判长：方若飞 审判员：马骏 人民陪审员：牛洪彬 二〇一四年三月十七日 书记员：王磊 "><WS nameCN="文首" value=" 河南省淮阳县人民法院 刑事判决书 （2014）淮刑初字第28号 "><WSZZDW nameCN="文书制作单位" value="法院"/><FYWSZL nameCN="法院文书种类" value="裁判文书"/><JBFY nameCN="经办法院" value="河南省淮阳县人民法院"><FYCJM nameCN="法院层级码" value="GE8"/><BZFYMC nameCN="标准法院名称" value="淮阳县人民法院"/><FYJB nameCN="法院级别" value="基层"/><XZQH_P nameCN="行政区划(省)" value="河南"/><XZQH_C nameCN="行政区划(市)" value="周口市"/></JBFY><WSMC nameCN="文书名称" value="刑事判决书"/><AH nameCN="案号" value="（2014）淮刑初字第28号"><ZH nameCN="字号" value="刑初字"/><LAND nameCN="立案年度" value="2014"/><FYJC nameCN="法院简称" value="淮"/><AHSXH nameCN="案号顺序号" value="28"/></AH><AJLB nameCN="案件类别" value="刑事案件"/><WSZL nameCN="文书种类" value="判决书"/><SPCX nameCN="审判程序" value="一审案件"/><AJLX nameCN="案件类型" value="刑事一审案件"/></WS><DSR nameCN="当事人" value="公诉机关淮阳县人民检察院。 被告人王东廷，男，1958年10月13日，汉族，小学文化，无业，住淮阳县城关镇南关村银张庄30号。因涉嫌交通肇事，于2013年8月30日拘留，同年9月7日被执行逮捕。现押于淮阳县看守所。 辩护人蔡静，女，系河南众望律师事务所律师。"><GSF nameCN="公诉方" value="公诉机关淮阳县人民检察院。"><SSCYR nameCN="诉讼参与人" value="淮阳县人民检察院"/><SSSF nameCN="诉讼身份" value="公诉机关"/><DSRLB nameCN="当事人类别" value="公诉机关"/><BSSSDW nameCN="本审诉讼地位" value="公诉机关"/></GSF><YSF nameCN="应诉方" value="被告人王东廷，男，1958年10月13日，汉族，小学文化，无业，住淮阳县城关镇南关村银张庄30号。因涉嫌交通肇事，于2013年8月30日拘留，同年9月7日被执行逮捕。现押于淮阳县看守所。"><SSCYR nameCN="诉讼参与人" value="王东廷"/><SSSF nameCN="诉讼身份" value="被告人"/><DSRLX nameCN="当事人类型" value="自然人"/><XB nameCN="性别" value="男"/><MZ nameCN="民族" value="汉族"/><WHCD nameCN="文化程度" value="小学毕业"/><XW nameCN="学位" value="其他"/><DSRDZ nameCN="当事人地址" value="淮阳县城关镇南关村银张庄30号"/><GJ nameCN="国籍" value="中国"/><DSRLB nameCN="当事人类别" value="被告人"/><QZCS nameCN="强制措施"><QZCSZL nameCN="强制措施种类" value="拘留"/><QZCSZXSJ nameCN="强制措施执行时间" value="2013年8月30日"/><QZCSYYFZ nameCN="强制措施原因组"><QZCSYY nameCN="强制措施原因" value="交通肇事"/></QZCSYYFZ></QZCS><QZCS nameCN="强制措施"><QZCSZL nameCN="强制措施种类" value="逮捕"/><QZCSZXSJ nameCN="强制措施执行时间" value="2013年9月7日"/></QZCS><JYCS nameCN="羁押场所" value="淮阳县看守所"/><BDBRQ nameCN="被逮捕日期" value="2013年9月7日"/><HXKYQNFZ nameCN="缓刑考验期内犯罪" value="否"/><JSKYQNFZ nameCN="假释考验期内犯罪" value="否"/><XSZRNL nameCN="刑事责任能力" value="完全刑事责任能力"/><BSSSDW nameCN="本审诉讼地位" value="被告人"/><SFBHR nameCN="是否被害人" value="否"/><ZRRSF nameCN="自然人身份" value="无业人员"/></YSF><DLR nameCN="代理人" value="辩护人蔡静，女，系河南众望律师事务所律师。"><SSCYR nameCN="诉讼参与人" value="蔡静"/><SSSF nameCN="诉讼身份" value="辩护人"/><DSRLX nameCN="当事人类型" value="自然人"/><XB nameCN="性别" value="女"/><DWZWFZ nameCN="单位职务分组"><ZW nameCN="职务" value="律师"/><DWMC nameCN="单位名称" value="河南众望律师事务所"/><DWXZ nameCN="单位性质" value="事业单位"/></DWZWFZ><GJ nameCN="国籍" value="中国"/><DSRLB nameCN="当事人类别" value="代理人"/><CYRSSDW nameCN="参与人诉讼地位" value="辩护人"/><BHZL nameCN="辩护种类" value="委托辩护"/><BHDX nameCN="辩护对象" value="王东廷"/><DLRBHRZYLX nameCN="代理人辩护人职业类型" value="职业律师"/><BHRHSSDLRLX nameCN="辩护人或诉讼代理人类型" value="律师"/><ZRRSF nameCN="自然人身份" value="职员"/></DLR><BGRQX nameCN="被告人缺席" value="无缺席"/></DSR><SSJL nameCN="诉讼记录" value=" 淮阳县人民检察院以淮检刑诉（2014）21号起诉书指控被告人王东廷犯交通肇事罪，于2014年2月20日向本院提起公诉，本院审查后，依法组成合议庭，公开开庭审理了本案。淮阳县人民检察院代理检察员朱晓峰出庭支持公诉，被告人王东廷及其辩护人蔡静到庭参加了诉讼，本案现已审理终结。"><KTSL nameCN="开庭审理" value="是"/><KTSLXX nameCN="开庭审理信息" value="公开审理"/><CTJCYs nameCN="出庭检察员"><JCYFZ nameCN="检察员分组"><JS nameCN="角色" value="代理检察员"/><JCY nameCN="检察员" value="朱晓峰"/></JCYFZ></CTJCYs><SSXZ nameCN="诉讼性质" value="公诉"/><QSRQ nameCN="起诉日期" value="2014年2月20日"/><JCYJYYQSL nameCN="检察院建议延期审理" value="否"/><SNFT nameCN="少年法庭" value="否"/><ZKXX nameCN="指控信息"><ZKJL nameCN="指控记录"><ZKZM nameCN="指控罪名" value="交通肇事罪"><ZMDM nameCN="罪名代码" value="51"/><WZZM nameCN="完整罪名" value="交通肇事罪"/></ZKZM><XGR nameCN="相关人" value="王东廷"/></ZKJL></ZKXX><QSZAY nameCN="起诉主案由" value="交通肇事罪"><ZMDM nameCN="罪名代码" value="51"/><WZZM nameCN="完整罪名" value="交通肇事罪"/></QSZAY><YSAJSYCX nameCN="一审案件适用程序" value="普通程序"/><JYSYJYCX nameCN="建议适用简易程序" value="无"/><DRSP nameCN="独任审判" value="否"/><YSAJLY nameCN="一审案件来源" value="新收公诉"/><GSJG nameCN="公诉机关" value="淮阳县人民检察院"/><GSAH nameCN="公诉案号" value="淮检刑诉（2014）21号"/><JYZPT nameCN="简易转普通" value="否"/><SPZZ nameCN="审判组织" value="合议庭"/><CTDSRXX nameCN="出庭当事人信息"><CTRXM nameCN="出庭人姓名" value="王东廷"><SSDW nameCN="诉讼地位" value="被告人"/></CTRXM><CTRXM nameCN="出庭人姓名" value="蔡静"><SSDW nameCN="诉讼地位" value="辩护人"/></CTRXM></CTDSRXX></SSJL><AJJBQK nameCN="案件基本情况" value=" 淮阳县人民检察院指控：2013年8月29日7时许，被告人王东廷驾驶一辆电动三轮车由东向西行驶至淮阳县大同街商城北门路段时，与由北向南步行的叶孝珍发生相撞，致叶孝珍受伤入院经抢救无效死亡及电动车受损的交通事故，被告人王东廷肇事后逃逸。经认定，王东廷负此事故的全部责任。当日18时许，被告人王东廷到淮阳县公安局投案自首。 被告人辩称：我构不成交通肇事逃逸。 辩护人辩称：被告人王东廷构不成交通肇事逃逸，其主观上没有逃逸的故意。被告人有投案自首情节，且已经赔偿了受害人的经济损失，应当减轻处罚。 经审理查明：2013年8月29日7时许，被告人王东廷驾驶一辆电动三轮车由东向西行驶至淮阳县大同街商城北门路段时，与由北向南步行的叶孝珍发生相撞，致叶某某受伤入院经抢救无效死亡及电动车受损的交通事故，被告人王东廷肇事后逃逸。经认定，王东廷负此事故的全部责任。当日18时许，被告人王东廷到淮阳县公安局投案自首。2013年8月31日被告人赔偿受害人17000元丧葬费。2014年3月10日经本院调解，被告人方赔偿受害人150000元。 上述事实，经公诉机关提交，并经法庭举证、质证、认证的有下列证据予以证实： 户籍证明、前科证明。2、叶孝珍火化证。3、交通事故认定。4、交通事故车辆技术检验报告。5、雷东、马旭东人民医院医生书写的证言2013年8月29日7时许在城关镇大同街商城北门出诊及跟车的老头否认自己是肇事司机的事实。6、发破案报告书。7、现场勘查笔录。8、鉴定意见书。9、证人叶某某证言，我不知道事情经过，在2013年8月29日8时，我给我父亲打电话，没有打通，然后就回家找他没有找着，我在家等他，等到10时多时间，我又回到城内店里面，又给我父亲打了一个电话，还是关机，我又骑着电动车回家看看，还是没有回家，等到12点多，又回到城里店内，在12时35分有一个人给我打电话，是用俺爸的手机给我打的，他说我爸被人撞着拉医院去了，我就骑摩托车去找，找到老人民医院找，人家说：确实有一个老头，没有抢救过来，拉太平间里去了。到医院太平间，一看就是俺爸叶某某。10、证人董某某证言，2013年8月29日7时许，我开机动三轮前往西关公交车上送货，当行驶到商城东路口时，看到商城北门对面，大同路的北侧，倒一辆红色的电动三轮车，头朝商城，是往西翻的，我走到跟前，有几个人将电动三轮车扶起来，从红色三轮车下来一个人有60多岁，平头，头高170多，身材较胖，没有看见穿的啥衣服，他拿着手机报的120，他说在商城北门我碰着人啦，赶紧过来将他拉走。也看一个老头朝东北扒着，面朝东面，鼻子出血，当时旁边围很多人。在现场西侧有10米远，在路中间，捡个手机没有电了，我回去后充了电，给手机的家人打电话，他们说手机是他爸的手机。11、证人贺某某证言，当时我骑着电车从由西往东在路南走着，开始没有注意拉人的电三轮和其他人，我听见路北边一声响，我顺着声音看，在路北一辆红色电动三轮车翻车，碰伤一步行的老年人，三轮车压步行人身上了，过路的人都帮着将三轮车抬开以后，看见受伤者流好多血，开电动三轮车也是年纪大的人，说快打120，然后到车里找他的手机，我看见开三轮车的人找到手机以后，我有事走了。不知开三轮车的打没有打120。12、证人马某某证言，2013年8月30日早起7时左右，我院120车去大同路商城北门去接诊，到现场看见一辆红色的拉客的电动三轮车，撞着一个老头，我们将伤者抬到120车上，要求伤者的家属去一个人，没有家属在场。开三轮车的司机是一个50多岁，大高个子，身材一般胖瘦，是他跟着120车一块去的医院，由于伤情严重，我们一块将伤者送到北关人民医院，我就回来了。我们问那老头是不是伤者的家属，他说不是哩，我又问他是不是司机，他说：他不是司机，司机走罢了。13、证人王某某证言，2013年8月29日具体几点我记不住了，是上午，我叔用他的手机给我打电话说：他碰着人了，他和碰伤的人都在北关人民医院，我到北关人民医院，见到我叔王东延，并询问伤者病情，医生说：人伤的不轻。我就让我叔王东延报警。然后我从医院回家了，中午我到交警问情况，见到办案警官，办案警官说：人不行了，该投案投案。当天下午（几点记不清了）。我回到家，见到我叔王东延说了说情况。然后我就和我叔王东延一块来交警队投案。14、被告人王东廷供述，我来交通大队投案自首。2013年8月29日7时许，我驾驶电动三轮在大同路从东向西行驶，准备去西关车站，行驶到商城北门路段时，从路北的美食广场由北向南过来一个男的，我看见后刹车，没有刹住，往南打方向，我车的右侧后部撞着那个人了，我的车也刹车刹翻了，车头朝南，我赶紧出来，车压着那个人的腿哩，其他帮忙把车掀起来，我叫人打120，我也打了120，我的手机号15896755051，120车去了后，我也跟着去医院，给伤者拍CT，打上针，我有200元钱，给他交上，当时写的是无名者，后来医生说还交钱。我从医院回来找钱，没有回家又到现场把我的车开回家了。就去找钱，家里没有，又到周口找着俺闺女了，找了几千元钱。又到医院听说人死了，我就回家了。这个时间下午约三点的时间，到了下午6时左右，我就到交警队投案了。我是9点左右13673555676报的110，报警之后我的电话打不通是因为我的手机摔的接触不良。我是下午2点接的民警电话，我说叫王东廷，心里害怕，没有说家庭住址。 辩护人提交的证据：1、照片。2、周口市开发区陈营行 政村蔡扎卫生室证明。3、医院收费条。辩护人提交的该组证据的目的证明被告人王东廷没有逃逸的动机。 "><ZZQK nameCN="质证情况" value="质证"/><ZKDL nameCN="指控段落" value=" 淮阳县人民检察院指控：2013年8月29日7时许，被告人王东廷驾驶一辆电动三轮车由东向西行驶至淮阳县大同街商城北门路段时，与由北向南步行的叶孝珍发生相撞，致叶孝珍受伤入院经抢救无效死亡及电动车受损的交通事故，被告人王东廷肇事后逃逸。经认定，王东廷负此事故的全部责任。当日18时许，被告人王东廷到淮阳县公安局投案自首。 "><ZKSS nameCN="指控事实" value="淮阳县人民检察院指控：2013年8月29日7时许，被告人王东廷驾驶一辆电动三轮车由东向西行驶至淮阳县大同街商城北门路段时，与由北向南步行的叶孝珍发生相撞，致叶孝珍受伤入院经抢救无效死亡及电动车受损的交通事故，被告人王东廷肇事后逃逸。经认定，王东廷负此事故的全部责任。当日18时许，被告人王东廷到淮阳县公安局投案自首。"/></ZKDL><BHDL nameCN="辩护段落" value="被告人辩称：我构不成交通肇事逃逸。 辩护人辩称：被告人王东廷构不成交通肇事逃逸，其主观上没有逃逸的故意。被告人有投案自首情节，且已经赔偿了受害人的经济损失，应当减轻处罚。 "><BHRBH nameCN="辩护人辩护" value="辩护人辩称：被告人王东廷构不成交通肇事逃逸，其主观上没有逃逸的故意。被告人有投案自首情节，且已经赔偿了受害人的经济损失，应当减轻处罚。"><BHYJ nameCN="辩护意见"><BGRXM nameCN="被告人姓名" value="王东廷"/><BHYJZL nameCN="辩护意见种类" value="罪轻辩护"/></BHYJ></BHRBH></BHDL><BSSLD nameCN="本审审理段" value="经审理查明：2013年8月29日7时许，被告人王东廷驾驶一辆电动三轮车由东向西行驶至淮阳县大同街商城北门路段时，与由北向南步行的叶孝珍发生相撞，致叶某某受伤入院经抢救无效死亡及电动车受损的交通事故，被告人王东廷肇事后逃逸。经认定，王东廷负此事故的全部责任。当日18时许，被告人王东廷到淮阳县公安局投案自首。2013年8月31日被告人赔偿受害人17000元丧葬费。2014年3月10日经本院调解，被告人方赔偿受害人150000元。 上述事实，经公诉机关提交，并经法庭举证、质证、认证的有下列证据予以证实： 户籍证明、前科证明。2、叶孝珍火化证。3、交通事故认定。4、交通事故车辆技术检验报告。5、雷东、马旭东人民医院医生书写的证言2013年8月29日7时许在城关镇大同街商城北门出诊及跟车的老头否认自己是肇事司机的事实。6、发破案报告书。7、现场勘查笔录。8、鉴定意见书。9、证人叶某某证言，我不知道事情经过，在2013年8月29日8时，我给我父亲打电话，没有打通，然后就回家找他没有找着，我在家等他，等到10时多时间，我又回到城内店里面，又给我父亲打了一个电话，还是关机，我又骑着电动车回家看看，还是没有回家，等到12点多，又回到城里店内，在12时35分有一个人给我打电话，是用俺爸的手机给我打的，他说我爸被人撞着拉医院去了，我就骑摩托车去找，找到老人民医院找，人家说：确实有一个老头，没有抢救过来，拉太平间里去了。到医院太平间，一看就是俺爸叶某某。10、证人董某某证言，2013年8月29日7时许，我开机动三轮前往西关公交车上送货，当行驶到商城东路口时，看到商城北门对面，大同路的北侧，倒一辆红色的电动三轮车，头朝商城，是往西翻的，我走到跟前，有几个人将电动三轮车扶起来，从红色三轮车下来一个人有60多岁，平头，头高170多，身材较胖，没有看见穿的啥衣服，他拿着手机报的120，他说在商城北门我碰着人啦，赶紧过来将他拉走。也看一个老头朝东北扒着，面朝东面，鼻子出血，当时旁边围很多人。在现场西侧有10米远，在路中间，捡个手机没有电了，我回去后充了电，给手机的家人打电话，他们说手机是他爸的手机。11、证人贺某某证言，当时我骑着电车从由西往东在路南走着，开始没有注意拉人的电三轮和其他人，我听见路北边一声响，我顺着声音看，在路北一辆红色电动三轮车翻车，碰伤一步行的老年人，三轮车压步行人身上了，过路的人都帮着将三轮车抬开以后，看见受伤者流好多血，开电动三轮车也是年纪大的人，说快打120，然后到车里找他的手机，我看见开三轮车的人找到手机以后，我有事走了。不知开三轮车的打没有打120。12、证人马某某证言，2013年8月30日早起7时左右，我院120车去大同路商城北门去接诊，到现场看见一辆红色的拉客的电动三轮车，撞着一个老头，我们将伤者抬到120车上，要求伤者的家属去一个人，没有家属在场。开三轮车的司机是一个50多岁，大高个子，身材一般胖瘦，是他跟着120车一块去的医院，由于伤情严重，我们一块将伤者送到北关人民医院，我就回来了。我们问那老头是不是伤者的家属，他说不是哩，我又问他是不是司机，他说：他不是司机，司机走罢了。13、证人王某某证言，2013年8月29日具体几点我记不住了，是上午，我叔用他的手机给我打电话说：他碰着人了，他和碰伤的人都在北关人民医院，我到北关人民医院，见到我叔王东延，并询问伤者病情，医生说：人伤的不轻。我就让我叔王东延报警。然后我从医院回家了，中午我到交警问情况，见到办案警官，办案警官说：人不行了，该投案投案。当天下午（几点记不清了）。我回到家，见到我叔王东延说了说情况。然后我就和我叔王东延一块来交警队投案。14、被告人王东廷供述，我来交通大队投案自首。2013年8月29日7时许，我驾驶电动三轮在大同路从东向西行驶，准备去西关车站，行驶到商城北门路段时，从路北的美食广场由北向南过来一个男的，我看见后刹车，没有刹住，往南打方向，我车的右侧后部撞着那个人了，我的车也刹车刹翻了，车头朝南，我赶紧出来，车压着那个人的腿哩，其他帮忙把车掀起来，我叫人打120，我也打了120，我的手机号15896755051，120车去了后，我也跟着去医院，给伤者拍CT，打上针，我有200元钱，给他交上，当时写的是无名者，后来医生说还交钱。我从医院回来找钱，没有回家又到现场把我的车开回家了。就去找钱，家里没有，又到周口找着俺闺女了，找了几千元钱。又到医院听说人死了，我就回家了。这个时间下午约三点的时间，到了下午6时左右，我就到交警队投案了。我是9点左右13673555676报的110，报警之后我的电话打不通是因为我的手机摔的接触不良。我是下午2点接的民警电话，我说叫王东廷，心里害怕，没有说家庭住址。 辩护人提交的证据：1、照片。2、周口市开发区陈营行 政村蔡扎卫生室证明。3、医院收费条。辩护人提交的该组证据的目的证明被告人王东廷没有逃逸的动机。 "><ZJXX nameCN="证据信息"><ZJFZ nameCN="证据分组"><RDSS nameCN="认定事实" value="经审理查明：2013年8月29日7时许，被告人王东廷驾驶一辆电动三轮车由东向西行驶至淮阳县大同街商城北门路段时，与由北向南步行的叶孝珍发生相撞，致叶某某受伤入院经抢救无效死亡及电动车受损的交通事故，被告人王东廷肇事后逃逸。经认定，王东廷负此事故的全部责任。当日18时许，被告人王东廷到淮阳县公安局投案自首。2013年8月31日被告人赔偿受害人17000元丧葬费。2014年3月10日经本院调解，被告人方赔偿受害人150000元。 "/><ZJJL nameCN="证据记录" value="户籍证明、前科证明。2、叶孝珍火化证。3、交通事故认定。4、交通事故车辆技术检验报告。5、雷东、马旭东人民医院医生书写的证言2013年8月29日7时许在城关镇大同街商城北门出诊及跟车的老头否认自己是肇事司机的事实。6、发破案报告书。7、现场勘查笔录。8、鉴定意见书。9、证人叶某某证言，我不知道事情经过，在2013年8月29日8时，我给我父亲打电话，没有打通，然后就回家找他没有找着，我在家等他，等到10时多时间，我又回到城内店里面，又给我父亲打了一个电话，还是关机，我又骑着电动车回家看看，还是没有回家，等到12点多，又回到城里店内，在12时35分有一个人给我打电话，是用俺爸的手机给我打的，他说我爸被人撞着拉医院去了，我就骑摩托车去找，找到老人民医院找，人家说：确实有一个老头，没有抢救过来，拉太平间里去了。到医院太平间，一看就是俺爸叶某某。10、证人董某某证言，2013年8月29日7时许，我开机动三轮前往西关公交车上送货，当行驶到商城东路口时，看到商城北门对面，大同路的北侧，倒一辆红色的电动三轮车，头朝商城，是往西翻的，我走到跟前，有几个人将电动三轮车扶起来，从红色三轮车下来一个人有60多岁，平头，头高170多，身材较胖，没有看见穿的啥衣服，他拿着手机报的120，他说在商城北门我碰着人啦，赶紧过来将他拉走。也看一个老头朝东北扒着，面朝东面，鼻子出血，当时旁边围很多人。在现场西侧有10米远，在路中间，捡个手机没有电了，我回去后充了电，给手机的家人打电话，他们说手机是他爸的手机。11、证人贺某某证言，当时我骑着电车从由西往东在路南走着，开始没有注意拉人的电三轮和其他人，我听见路北边一声响，我顺着声音看，在路北一辆红色电动三轮车翻车，碰伤一步行的老年人，三轮车压步行人身上了，过路的人都帮着将三轮车抬开以后，看见受伤者流好多血，开电动三轮车也是年纪大的人，说快打120，然后到车里找他的手机，我看见开三轮车的人找到手机以后，我有事走了。不知开三轮车的打没有打120。12、证人马某某证言，2013年8月30日早起7时左右，我院120车去大同路商城北门去接诊，到现场看见一辆红色的拉客的电动三轮车，撞着一个老头，我们将伤者抬到120车上，要求伤者的家属去一个人，没有家属在场。开三轮车的司机是一个50多岁，大高个子，身材一般胖瘦，是他跟着120车一块去的医院，由于伤情严重，我们一块将伤者送到北关人民医院，我就回来了。我们问那老头是不是伤者的家属，他说不是哩，我又问他是不是司机，他说：他不是司机，司机走罢了。13、证人王某某证言，2013年8月29日具体几点我记不住了，是上午，我叔用他的手机给我打电话说：他碰着人了，他和碰伤的人都在北关人民医院，我到北关人民医院，见到我叔王东延，并询问伤者病情，医生说：人伤的不轻。我就让我叔王东延报警。然后我从医院回家了，中午我到交警问情况，见到办案警官，办案警官说：人不行了，该投案投案。当天下午（几点记不清了）。我回到家，见到我叔王东延说了说情况。然后我就和我叔王东延一块来交警队投案。14、被告人王东廷供述，我来交通大队投案自首。2013年8月29日7时许，我驾驶电动三轮在大同路从东向西行驶，准备去西关车站，行驶到商城北门路段时，从路北的美食广场由北向南过来一个男的，我看见后刹车，没有刹住，往南打方向，我车的右侧后部撞着那个人了，我的车也刹车刹翻了，车头朝南，我赶紧出来，车压着那个人的腿哩，其他帮忙把车掀起来，我叫人打120，我也打了120，我的手机号15896755051，120车去了后，我也跟着去医院，给伤者拍CT，打上针，我有200元钱，给他交上，当时写的是无名者，后来医生说还交钱。我从医院回来找钱，没有回家又到现场把我的车开回家了。就去找钱，家里没有，又到周口找着俺闺女了，找了几千元钱。又到医院听说人死了，我就回家了。这个时间下午约三点的时间，到了下午6时左右，我就到交警队投案了。我是9点左右13673555676报的110，报警之后我的电话打不通是因为我的手机摔的接触不良。我是下午2点接的民警电话，我说叫王东廷，心里害怕，没有说家庭住址。 "><ZJMX nameCN="证据明细"><MC nameCN="名称" value="户籍证明、前科证明"/><ZL nameCN="种类" value="书证"/></ZJMX></ZJJL><ZJJL nameCN="证据记录" value="辩护人提交的证据：1、照片。2、周口市开发区陈营行 "><ZJMX nameCN="证据明细"><MC nameCN="名称" value="辩护人证据"/><ZL nameCN="种类" value="其他"/><TJR nameCN="提交人" value="辩护人"/></ZJMX></ZJJL><ZJJL nameCN="证据记录" value="政村蔡扎卫生室证明。3、医院收费条。辩护人提交的该组证据的目的证明被告人王东廷没有逃逸的动机。"><ZJMX nameCN="证据明细"><MC nameCN="名称" value="政村蔡扎卫生室证明"/><ZL nameCN="种类" value="书证"/></ZJMX></ZJJL></ZJFZ></ZJXX><ZRXX nameCN="证人信息"><ZR nameCN="证人" value="叶某某"/><ZR nameCN="证人" value="董某某"/><ZR nameCN="证人" value="贺某某"/><ZR nameCN="证人" value="马某某"/><ZR nameCN="证人" value="王某某"/></ZRXX></BSSLD></AJJBQK><CPFXGC nameCN="裁判分析过程" value="本院认为，被告人王东廷违反道路运输管理法规，致一人死亡，且肇事后逃逸，其行为已构成了交通肇事罪，淮阳县人民检察院指控的罪名成立，本院予以支持。被告人及其辩护人的辩解理由及提交的证据与庭审查明事实不符本院不予采纳。案发后被告人王东廷主动投案自首如实供述自己的罪行，属自首，且赔偿了受害人的经济损失，判处缓刑不至于再危害社会，为达到法律效果和社会效果相统一的原则，可以对其适用缓刑故依照《中华人民共和国刑法》第一百三十三条、第六十七条第一款、第七十二条第一款、第七十三条第二款、第三款之规定，判决如下："><LXQJ nameCN="量刑情节"><ZDLXQJ nameCN="酌定量刑情节"><XGR nameCN="相关人" value="王东廷"/><QJ nameCN="情节" value="认罪态度好"/><LXQJLB nameCN="量刑情节类别" value="酌定从轻情节"/></ZDLXQJ><ZDLXQJ nameCN="酌定量刑情节"><XGR nameCN="相关人" value="王东廷"/><QJ nameCN="情节" value="犯罪后采取补救措施降低损失"/><LXQJLB nameCN="量刑情节类别" value="酌定从轻情节"/></ZDLXQJ></LXQJ><BGRTYRZCX nameCN="被告人同意认罪程序" value="是"/><FLFTYY nameCN="法律法条引用"><FLFTFZ nameCN="法律法条分组"><MC nameCN="名称" value="《中华人民共和国刑法》"/><T nameCN="条" value="第一百三十三条"/><T nameCN="条" value="第六十七条"><K nameCN="款" value="第一款"/></T><T nameCN="条" value="第七十二条"><K nameCN="款" value="第一款"/></T><T nameCN="条" value="第七十三条"><K nameCN="款" value="第二款"/><K nameCN="款" value="第三款"/></T></FLFTFZ></FLFTYY><CUS_FLFT_FZ_RY nameCN="法律法条分组冗余"><CUS_FLFT_RY nameCN="法律法条" value="《中华人民共和国刑法》第一百三十三条"/><CUS_FLFT_RY nameCN="法律法条" value="《中华人民共和国刑法》第六十七条第一款"/><CUS_FLFT_RY nameCN="法律法条" value="《中华人民共和国刑法》第七十二条第一款"/><CUS_FLFT_RY nameCN="法律法条" value="《中华人民共和国刑法》第七十三条第二款"/><CUS_FLFT_RY nameCN="法律法条" value="《中华人民共和国刑法》第七十三条第三款"/></CUS_FLFT_FZ_RY></CPFXGC><PJJG nameCN="判决结果" value=" 被告人王东廷犯交通肇事罪，判处有期徒刑三年缓刑三年。 （缓刑考验期从判决确定之日起计算）。 如不服本判决，可在接到判决书的第二日起十日内，通过本院或者直接向河南省周口市中级人民法院提出上诉，书面上诉的，应当提交上诉状正本一份，副本二份。"><GXQYY nameCN="提出管辖权异议" value="否"/><YSJAFS nameCN="一审结案方式" value="判决"/><YSXSBFCPJG nameCN="一审刑事部分裁判结果" value="判决"/><XSPJJGFZ nameCN="刑事判决结果分组"><SSCYR nameCN="诉讼参与人" value="王东廷"/><BSPJJG nameCN="本审判决结果"><DZPF nameCN="单罪判罚" value="犯交通肇事罪，判处有期徒刑三年缓刑三年。"><ZM nameCN="罪名" value="交通肇事罪"><ZMDM nameCN="罪名代码" value="51"/><WZZM nameCN="完整罪名" value="交通肇事罪"/></ZM><HX nameCN="缓刑"><HXLB nameCN="缓刑类别" value="普通缓刑"/><HXXQ nameCN="缓刑刑期" value="三年"/></HX><ZX nameCN="主刑"><ZXLB nameCN="主刑类别" value="有期徒刑"/><ZXXQ nameCN="主刑刑期" value="三年"/></ZX><PJJGLX nameCN="判决结果类型" value="给予刑事处罚"/></DZPF><ZXPF nameCN="执行判罚" value="犯交通肇事罪，判处有期徒刑三年缓刑三年。"><HX nameCN="缓刑"><HXLB nameCN="缓刑类别" value="普通缓刑"/><HXXQ nameCN="缓刑刑期" value="三年"/></HX><ZX nameCN="主刑"><ZXLB nameCN="主刑类别" value="有期徒刑"/><ZXXQ nameCN="主刑刑期" value="三年"/></ZX><PJJGLX nameCN="判决结果类型" value="给予刑事处罚"/></ZXPF><PJZZM nameCN="判决主罪名" value="交通肇事罪"><ZMDM nameCN="罪名代码" value="51"/><WZZM nameCN="完整罪名" value="交通肇事罪"/></PJZZM></BSPJJG><MXHWZSF nameCN="免刑或无罪释放" value="否"/><SZBF nameCN="数罪并罚" value="否"/><HBLX nameCN="合并量刑" value="否"/></XSPJJGFZ><KSSZ nameCN="可上诉至" value="河南省周口市中级人民法院"/><SSTJCL nameCN="上诉提交材料" value="上诉状正本一份，副本二份"/><SSQX nameCN="上诉期限" value="十日"/></PJJG><WW nameCN="文尾" value=" 审判长：方若飞 审判员：马骏 人民陪审员：牛洪彬 二〇一四年三月十七日 书记员：王磊 "><CPSJ nameCN="裁判时间" value="2014年3月17日"><JAND nameCN="结案年度" value="2014"/><CUS_JANYR nameCN="结案年月日" value="2014年3月17日"/><CUS_JANY nameCN="结案年月" value="2014-3"/><CUS_JAYF nameCN="结案月份" value="3"/></CPSJ><SPZZCY nameCN="审判组织成员"><SPRYXM nameCN="审判人员姓名" value="方若飞"/><SPRYJS nameCN="审判人员角色" value="审判长"/></SPZZCY><SPZZCY nameCN="审判组织成员"><SPRYXM nameCN="审判人员姓名" value="马骏"/><SPRYJS nameCN="审判人员角色" value="审判员"/></SPZZCY><SPZZCY nameCN="审判组织成员"><SPRYXM nameCN="审判人员姓名" value="牛洪彬"/><SPRYJS nameCN="审判人员角色" value="人民陪审员"/></SPZZCY><SPZZCY nameCN="审判组织成员"><SPRYXM nameCN="审判人员姓名" value="王磊"/><SPRYJS nameCN="审判人员角色" value="书记员"/></SPZZCY></WW><WSSFMH nameCN="文书是否模糊" value="否"/><CUS_SJ nameCN="时间"><CUS_YW nameCN="原文" value="淮阳县人民检察院以淮检刑诉（2014）21号起诉书指控被告人王东廷犯交通肇事罪，于2014年2月20日向本院提起公诉，本院审查后，依法组成合议庭，公开开庭审理了本案"/><CUS_SJYW nameCN="时间原文" value="淮阳县人民检察院以淮检刑诉（2014）21号起诉书指控被告人王东廷犯交通肇事罪，于2014年2月20日向本院提起公诉，本院审查后，依法组成合议庭，公开开庭审理了本案"/><CUS_JTSJ nameCN="具体时间" value="2014年2月20日"/></CUS_SJ><CUS_SJ nameCN="时间"><CUS_YW nameCN="原文" value="淮阳县人民检察院指控：2013年8月29日7时许，被告人王东廷驾驶一辆电动三轮车由东向西行驶至淮阳县大同街商城北门路段时，与由北向南步行的叶孝珍发生相撞，致叶孝珍受伤入院经抢救无效死亡及电动车受损的交通事故，被告人王东廷肇事后逃逸"/><CUS_SJYW nameCN="时间原文" value="淮阳县人民检察院指控：2013年8月29日7时许，被告人王东廷驾驶一辆电动三轮车由东向西行驶至淮阳县大同街商城北门路段时，与由北向南步行的叶孝珍发生相撞，致叶孝珍受伤入院经抢救无效死亡及电动车受损的交通事故，被告人王东廷肇事后逃逸"/><CUS_JTSJ nameCN="具体时间" value="2013年8月29日"/></CUS_SJ><CUS_SJ nameCN="时间"><CUS_YW nameCN="原文" value="当日18时许，被告人王东廷到淮阳县公安局投案自首"/><CUS_SJYW nameCN="时间原文" value="2013年8月29日18时许，被告人王东廷到淮阳县公安局投案自首"/><CUS_JTSJ nameCN="具体时间" value="2013年8月29日"/></CUS_SJ><CUS_SJ nameCN="时间"><CUS_YW nameCN="原文" value="经审理查明：2013年8月29日7时许，被告人王东廷驾驶一辆电动三轮车由东向西行驶至淮阳县大同街商城北门路段时，与由北向南步行的叶孝珍发生相撞，致叶某某受伤入院经抢救无效死亡及电动车受损的交通事故，被告人王东廷肇事后逃逸"/><CUS_SJYW nameCN="时间原文" value="经审理查明：2013年8月29日7时许，被告人王东廷驾驶一辆电动三轮车由东向西行驶至淮阳县大同街商城北门路段时，与由北向南步行的叶孝珍发生相撞，致叶某某受伤入院经抢救无效死亡及电动车受损的交通事故，被告人王东廷肇事后逃逸"/><CUS_JTSJ nameCN="具体时间" value="2013年8月29日"/></CUS_SJ><CUS_SJ nameCN="时间"><CUS_YW nameCN="原文" value="当日18时许，被告人王东廷到淮阳县公安局投案自首"/><CUS_SJYW nameCN="时间原文" value="2013年8月29日18时许，被告人王东廷到淮阳县公安局投案自首"/><CUS_JTSJ nameCN="具体时间" value="2013年8月29日"/></CUS_SJ><CUS_SJ nameCN="时间"><CUS_YW nameCN="原文" value="2013年8月31日被告人赔偿受害人17000元丧葬费"/><CUS_SJYW nameCN="时间原文" value="2013年8月31日被告人赔偿受害人17000元丧葬费"/><CUS_JTSJ nameCN="具体时间" value="2013年8月31日"/></CUS_SJ><CUS_SJ nameCN="时间"><CUS_YW nameCN="原文" value="2014年3月10日经本院调解，被告人方赔偿受害人150000元"/><CUS_SJYW nameCN="时间原文" value="2014年3月10日经本院调解，被告人方赔偿受害人150000元"/><CUS_JTSJ nameCN="具体时间" value="2014年3月10日"/></CUS_SJ><CUS_SJ nameCN="时间"><CUS_YW nameCN="原文" value="5、雷东、马旭东人民医院医生书写的证言2013年8月29日7时许在城关镇大同街商城北门出诊及跟车的老头否认自己是肇事司机的事实"/><CUS_SJYW nameCN="时间原文" value="5、雷东、马旭东人民医院医生书写的证言2013年8月29日7时许在城关镇大同街商城北门出诊及跟车的老头否认自己是肇事司机的事实"/><CUS_JTSJ nameCN="具体时间" value="2013年8月29日"/></CUS_SJ><CUS_SJ nameCN="时间"><CUS_YW nameCN="原文" value="9、证人叶某某证言，我不知道事情经过，在2013年8月29日8时，我给我父亲打电话，没有打通，然后就回家找他没有找着，我在家等他，等到10时多时间，我又回到城内店里面，又给我父亲打了一个电话，还是关机，我又骑着电动车回家看看，还是没有回家，等到12点多，又回到城里店内，在12时35分有一个人给我打电话，是用俺爸的手机给我打的，他说我爸被人撞着拉医院去了，我就骑摩托车去找，找到老人民医院找，人家说：确实有一个老头，没有抢救过来，拉太平间里去了"/><CUS_SJYW nameCN="时间原文" value="9、证人叶某某证言，我不知道事情经过，在2013年8月29日8时，我给我父亲打电话，没有打通，然后就回家找他没有找着，我在家等他，等到10时多时间，我又回到城内店里面，又给我父亲打了一个电话，还是关机，我又骑着电动车回家看看，还是没有回家，等到12点多，又回到城里店内，在12时35分有一个人给我打电话，是用俺爸的手机给我打的，他说我爸被人撞着拉医院去了，我就骑摩托车去找，找到老人民医院找，人家说：确实有一个老头，没有抢救过来，拉太平间里去了"/><CUS_JTSJ nameCN="具体时间" value="2013年8月29日"/></CUS_SJ><CUS_SJ nameCN="时间"><CUS_YW nameCN="原文" value="10、证人董某某证言，2013年8月29日7时许，我开机动三轮前往西关公交车上送货，当行驶到商城东路口时，看到商城北门对面，大同路的北侧，倒一辆红色的电动三轮车，头朝商城，是往西翻的，我走到跟前，有几个人将电动三轮车扶起来，从红色三轮车下来一个人有60多岁，平头，头高170多，身材较胖，没有看见穿的啥衣服，他拿着手机报的120，他说在商城北门我碰着人啦，赶紧过来将他拉走"/><CUS_SJYW nameCN="时间原文" value="10、证人董某某证言，2013年8月29日7时许，我开机动三轮前往西关公交车上送货，当行驶到商城东路口时，看到商城北门对面，大同路的北侧，倒一辆红色的电动三轮车，头朝商城，是往西翻的，我走到跟前，有几个人将电动三轮车扶起来，从红色三轮车下来一个人有60多岁，平头，头高170多，身材较胖，没有看见穿的啥衣服，他拿着手机报的120，他说在商城北门我碰着人啦，赶紧过来将他拉走"/><CUS_JTSJ nameCN="具体时间" value="2013年8月29日"/></CUS_SJ><CUS_SJ nameCN="时间"><CUS_YW nameCN="原文" value="12、证人马某某证言，2013年8月30日早起7时左右，我院120车去大同路商城北门去接诊，到现场看见一辆红色的拉客的电动三轮车，撞着一个老头，我们将伤者抬到120车上，要求伤者的家属去一个人，没有家属在场"/><CUS_SJYW nameCN="时间原文" value="12、证人马某某证言，2013年8月30日早起7时左右，我院120车去大同路商城北门去接诊，到现场看见一辆红色的拉客的电动三轮车，撞着一个老头，我们将伤者抬到120车上，要求伤者的家属去一个人，没有家属在场"/><CUS_JTSJ nameCN="具体时间" value="2013年8月30日"/></CUS_SJ><CUS_SJ nameCN="时间"><CUS_YW nameCN="原文" value="13、证人王某某证言，2013年8月29日具体几点我记不住了，是上午，我叔用他的手机给我打电话说：他碰着人了，他和碰伤的人都在北关人民医院，我到北关人民医院，见到我叔王东延，并询问伤者病情，医生说：人伤的不轻"/><CUS_SJYW nameCN="时间原文" value="13、证人王某某证言，2013年8月29日具体几点我记不住了，是上午，我叔用他的手机给我打电话说：他碰着人了，他和碰伤的人都在北关人民医院，我到北关人民医院，见到我叔王东延，并询问伤者病情，医生说：人伤的不轻"/><CUS_JTSJ nameCN="具体时间" value="2013年8月29日"/></CUS_SJ><CUS_SJ nameCN="时间"><CUS_YW nameCN="原文" value="2013年8月29日7时许，我驾驶电动三轮在大同路从东向西行驶，准备去西关车站，行驶到商城北门路段时，从路北的美食广场由北向南过来一个男的，我看见后刹车，没有刹住，往南打方向，我车的右侧后部撞着那个人了，我的车也刹车刹翻了，车头朝南，我赶紧出来，车压着那个人的腿哩，其他帮忙把车掀起来，我叫人打120，我也打了120，我的手机号15896755051，120车去了后，我也跟着去医院，给伤者拍CT，打上针，我有200元钱，给他交上，当时写的是无名者，后来医生说还交钱"/><CUS_SJYW nameCN="时间原文" value="2013年8月29日7时许，我驾驶电动三轮在大同路从东向西行驶，准备去西关车站，行驶到商城北门路段时，从路北的美食广场由北向南过来一个男的，我看见后刹车，没有刹住，往南打方向，我车的右侧后部撞着那个人了，我的车也刹车刹翻了，车头朝南，我赶紧出来，车压着那个人的腿哩，其他帮忙把车掀起来，我叫人打120，我也打了120，我的手机号15896755051，120车去了后，我也跟着去医院，给伤者拍CT，打上针，我有200元钱，给他交上，当时写的是无名者，后来医生说还交钱"/><CUS_JTSJ nameCN="具体时间" value="2013年8月29日"/></CUS_SJ><title value="王东廷犯交通肇事罪"/><subTitle value="刑事一审判决书"/><slzq value="25"/></QW></writ>