<?xml version="1.0" encoding="UTF-8"?>
<writ><QW nameCN="全文" value="云南省马龙县人民法院 刑事判决书 （2015）马少刑初字第4号 公诉机关马龙县人民检察院。 被告人毛连胜，男，1982年4月27日出生，汉族，云南省寻甸县人，驾驶员，小学文化，身份证号码：532231198204272110，住云南省昆明市寻甸回族彝族自治县倘甸镇白章村委会芭蕉树村85号。因涉嫌犯交通肇事罪，于2015年5月18日被马龙县公安局刑事拘留，2015年6月1日经马龙县人民检察院批准逮捕，同日被马龙县公安局执行逮捕。现羁押于马龙县看守所。 辩护人梁晋，云南万成（寻甸）律师事务所律师。 马龙县人民检察院以马检公诉刑诉（2015）27号起诉书指控被告人毛连胜犯交通肇事罪，于2015年6月29日向本院提起公诉。经审查，本院于2015年6月30日受理后，依法组成合议庭，于2015年8月5日公开开庭进行了审理。马龙县人民检察院依法指派检察员高龙等二人出庭支持公诉。被告人毛连胜及其辩护人梁晋到庭参加诉讼。本案现已审理终结。 马龙县人民检察院指控：2015年5月15日20时许，被告人毛连胜驾驶云AE1598号重型自卸货车，沿“沪瑞线”由曲靖市方向马龙县方向超载运输焦灰。23时许，毛连胜驾驶车辆行至“沪瑞线”K2656＋100M处时，其所驾驶车辆在超越前方同向行驶的由唐石生驾驶的云D53926号小型轿车（车载其妻杨利琴）过程中，遇唐石生驾驶车辆左转行驶，毛连胜驾驶车辆超越该车时，未按照操作规范安全驾驶，导致其所驾驶的车辆侧翻压于唐石生所驾驶的车辆上，造成唐石生及乘车人杨利琴当场死亡及两车不同程度受损的道路交通事故。经认定，毛连胜承担此次事故的全部责任。 事故发生后，毛连胜明知他人报案而在现场等待处理，其到案后如实供述自己的罪行。 据此，公诉机关认为，被告人毛连胜违反道路交通安全法律、法规，驾驶超载机动车辆上路行驶，未与前车保持足以采取紧急制动措施的安全距离，行至交叉路口时超车，未按照操作规范安全驾驶、文明驾驶，发生交通事故，致二人死亡、两车受损，情节特别恶劣，其行为已涉嫌触犯《中华人民共和国刑法》第一百三十三条之规定，应以交通肇事罪追究其刑事责任。同时，依据“刑法”第六十七条第一款之规定，毛连胜的行为具备自首情节，可以从轻或者减轻处罚。 在量刑方面，公诉机关建议本院对被告人毛连胜在有期徒刑三年至四年内判处刑罚。 针对指控的事实，公诉机关向本院移送了指控被告人犯罪的案件来源材料、证人证言、现场勘查笔录及照片、尸体检验意见书及照片、鉴定意见、道路交通事故责任认定书以及被告人供述及辩解等证据。 被告人毛连胜对公诉机关指控的犯罪事实、罪名及量刑建议均无异议，未提出辩解意见。 被告人毛连胜的辩护人提出如下辩护意见：1、被告人毛连胜在得知朋友报警后，在现场等待警察到来，归案后亦如实供述自己的罪行，系自首，可以从轻或者减轻处罚；2、被告人毛连胜在案发后其家属赔偿了被害人家属15万元，并已实际支付，取得被害人家属的谅解，应依法对其从轻处罚。综上所述，建议法庭对被告人毛连胜处三年以下有期徒刑并依法适用缓刑。 经审理查明：2015年5月15日，被告人毛连胜驾驶云AE1598号重型自卸货车（核定载人数2人，实际载人数3人；核定载质量16000kg，实际载质量18100kg）沿沪瑞线由曲靖市方向向马龙县方向行驶，22时50分许，行驶至沪瑞线（马龙县境内）k2656＋100M处时，其所驾车辆在超越前方同方向内行驶的由唐石生驾驶的云D53926号小型轿车（核定载人数5人，实际载人数3人；核定载质量16000kg，实际载人数2人）过程中，遇云D53926号车由西向东左转弯行驶时，车身右前部与云D53926号车车身左前部发生碰撞，碰撞过程中，云AE1598号车从左至右发生侧翻，车身右侧压于云D53926号车车身，造成云D53926号车驾驶人唐石生、云D53926号车乘车人杨利琴当场死亡、两车及道路周边设施不同程度受损的道路交通事故。2015年5月25日，马龙县公安局交通警察大队作出马公交认字（2015）第5303213201500005号道路交通事故认定书，认定被告人毛连胜承担此次事故的全部责任，唐石生、杨利琴不承担此事故的责任。 事故发生后，被告人毛连胜的熟人驾车经过案发现场，并用电话报了警，被告人毛连胜明知他人报案而在事故现场等待交警部门的调查处理，其到案后如实供述自己的犯罪事实及经过。 本次交通事故引起的民事赔偿纠纷，被害人的家属已与被告人毛连胜及其车辆登记挂靠公司、肇事车辆承保的保险公司等责任主体达成一致调解协议。被告人毛连胜及其车辆登记挂靠公司已履行赔偿义务。被害人的家属对被告人毛连胜的行为表示谅解，请求法院对其从轻处罚并适用缓刑。 上述事实，有以下经法庭举证、质证的证据予以证明，本院予以确认：1、受理道路事故案件登记表、接受刑事案件登记表、立案决定书及到案经过证明交通事故发生后，被告人毛连胜的熟人主动用电话报警后被告人毛连胜一直留在事故现场等待交警部门调查处理的事实。2、道路交通事故技术鉴定委托书（尸体检验）、昆明医科大学司法鉴定中心交通事故检验报告、死亡医学证明书证明本次交通事故造成唐石生、杨利琴死亡的事实。3、道路交通事故现场勘查笔录及照片、交通事故现场图证明本次交通事故发生的地点。4、道路交通事故技术鉴定委托书（车辆检验）、曲靖恒通司法鉴定所曲恒通（2015）车鉴字第535号鉴定意见书证明云AE1598号车在发生事故时转向系、制动系、灯光电器符合相关技术条件，车辆无机械故障，车速无法计算的事实。5、道路交通事故技术鉴定委托书（车辆检验）、曲靖恒通司法鉴定所曲恒通（2015）车鉴字第536号鉴定意见书证明云D53926号车在发生事故时转向系、制动系符合相关技术条件，车辆无机械故障，左、右后转向信号灯、制动灯灯具肇事严重损坏无法检验以及车速无法计算的事实。6、道路交通事故技术鉴定委托书（血液中酒精测定）、曲靖恒通司法鉴定所曲恒通（2015）毒检字第308号鉴定意见书证明被告人毛连胜交通肇事时不存在酒驾情形。7、道路交通事故技术鉴定委托书（血液中酒精测定）、曲靖恒通司法鉴定所曲恒通（2015）毒检字第307号鉴定意见书证明被害人唐石生交通肇事时不存在酒驾情形。8、马龙县公安局交通警察大队检验、鉴定告知书证明交警部门将被害人唐石生、杨利琴死亡原因的鉴定意见、肇事时双方驾驶员不存在酒驾情形及肇事车辆安全技术检验情况的鉴定意见告知事故当事人及被害人家属的事实。9、道路交通事故认定书证明被告人毛连胜负此次事故的全部责任，被害人唐石生、杨利琴无责任。10、被告人毛连胜的供述，被害人家属王某香、唐某琪、唐梦某及杨国云的陈述，证人雷丽琼、杨某应的证言，相互印证证明交通事故发生的时间、地点、经过及毛连胜到案后如实供述自己罪行的事实。12、被告人毛连胜的身份证复印件、常住人口信息表、违法犯罪前科查询结果单一份，证明被告人的年龄、身份及无违法犯罪记录等基本情况。 另有机动车驾驶证、机动车行驶证、过磅单、行政强制措施凭证、保险单、谅解书等证据证明本案审理查明的事实。 本院认为，被告人毛连胜违反道路交通运输管理法规，驾驶超载机动车辆上路行驶，未与前车保持足以采取紧急制动措施的安全距离，行至交叉路口时超车，未按照操作规范安全驾驶、文明驾驶，发生交通事故，致二人死亡，且对事故负全部责任，其行为已构成交通肇事罪。公诉机关指控的犯罪事实和罪名成立，本院予以支持。案发后，被告人明知他人报案而在事故现场等待处理并在归案后如实供述其犯罪事实，系自首，依法可以对其从轻处罚。庭审中，被告人认罪态度较好，具有一定的悔罪表现，且庭审后，被害人家属与被告人毛连胜及其车辆登记挂靠公司、肇事车辆承保的保险公司等责任主体就民事部分达成一致调解协议，被告人毛连胜及其车辆登记挂靠公司已履行赔偿义务，被害人家属对被告人的行为表示谅解，可酌情对被告人从轻处罚。 公诉机关提出的量刑建议，符合罪责刑相适应原则，本院予以采纳，但综合被告人的犯罪性质、情节，可对被告人宣告缓刑。对被告人毛连胜的辩护人提出的第1、2点辩护意见本院予以采纳，对其“建议法庭对被告人处三年以下有期徒刑”的辩护意见，与法律规定不符，本院不予采纳。 综上所述，根据被告人犯罪的事实、性质、情节、社会危害程度以及悔罪表现，依照《中华人民共和国刑法》第一百三十三条、第六十七条第一款、第七十二条、第七十三条第二款、第三款及《最高人民法院〈关于审理交通肇事刑事案件具体应用法律若干问题的解释〉》第四条之规定，判决如下： 被告人毛连胜犯交通肇事罪，判处有期徒刑三年，缓刑五年。（缓刑考验期限，从判决确定之日起计算。） 如不服本判决，可在接到判决书的第二日起十日内，通过本院或者直接向云南省曲靖市中级人民法院提出上诉。书面上诉的应当提交上诉状正本一份，副本三份。 审判长朱永平 审判员张雄采 人民陪审员杨丽娟 二〇一五年九月二十五日 书记员祖雯静 "><WS nameCN="文首" value="云南省马龙县人民法院 刑事判决书 （2015）马少刑初字第4号"><WSZZDW nameCN="文书制作单位" value="法院"/><FYWSZL nameCN="法院文书种类" value="裁判文书"/><JBFY nameCN="经办法院" value="云南省马龙县人民法院"><FYCJM nameCN="法院层级码" value="P43"/><BZFYMC nameCN="标准法院名称" value="马龙县人民法院"/><FYJB nameCN="法院级别" value="基层"/><XZQH_P nameCN="行政区划(省)" value="云南"/><XZQH_C nameCN="行政区划(市)" value="曲靖市"/></JBFY><WSMC nameCN="文书名称" value="刑事判决书"/><AH nameCN="案号" value="（2015）马少刑初字第4号"><ZH nameCN="字号" value="刑初字"/><LAND nameCN="立案年度" value="2015"/><FYJC nameCN="法院简称" value="马少"/><AHSXH nameCN="案号顺序号" value="4"/></AH><AJLB nameCN="案件类别" value="刑事案件"/><WSZL nameCN="文书种类" value="判决书"/><SPCX nameCN="审判程序" value="一审案件"/><AJLX nameCN="案件类型" value="刑事一审案件"/></WS><DSR nameCN="当事人" value=" 公诉机关马龙县人民检察院。 被告人毛连胜，男，1982年4月27日出生，汉族，云南省寻甸县人，驾驶员，小学文化，身份证号码：532231198204272110，住云南省昆明市寻甸回族彝族自治县倘甸镇白章村委会芭蕉树村85号。因涉嫌犯交通肇事罪，于2015年5月18日被马龙县公安局刑事拘留，2015年6月1日经马龙县人民检察院批准逮捕，同日被马龙县公安局执行逮捕。现羁押于马龙县看守所。 辩护人梁晋，云南万成（寻甸）律师事务所律师。"><GSF nameCN="公诉方" value="公诉机关马龙县人民检察院。"><SSCYR nameCN="诉讼参与人" value="马龙县人民检察院"/><SSSF nameCN="诉讼身份" value="公诉机关"/><DSRLB nameCN="当事人类别" value="公诉机关"/><BSSSDW nameCN="本审诉讼地位" value="公诉机关"/></GSF><YSF nameCN="应诉方" value="被告人毛连胜，男，1982年4月27日出生，汉族，云南省寻甸县人，驾驶员，小学文化，身份证号码：532231198204272110，住云南省昆明市寻甸回族彝族自治县倘甸镇白章村委会芭蕉树村85号。因涉嫌犯交通肇事罪，于2015年5月18日被马龙县公安局刑事拘留，2015年6月1日经马龙县人民检察院批准逮捕，同日被马龙县公安局执行逮捕。现羁押于马龙县看守所。"><SSCYR nameCN="诉讼参与人" value="毛连胜"/><SSSF nameCN="诉讼身份" value="被告人"/><DSRLX nameCN="当事人类型" value="自然人"/><XB nameCN="性别" value="男"/><MZ nameCN="民族" value="汉族"/><CSRQ nameCN="出生日期" value="1982年4月27日"/><WHCD nameCN="文化程度" value="小学毕业"/><XW nameCN="学位" value="其他"/><ZJLX nameCN="证件类型" value="身份证"><ZJHM nameCN="证件号码" value="532231198204272110"/><SFZXBDM nameCN="身份证性别代码" value="1"/><SFZCSRQ nameCN="身份证出生日期" value="1982年04月27日"/></ZJLX><DWZWFZ nameCN="单位职务分组"><ZW nameCN="职务" value="驾驶员"/></DWZWFZ><DSRDZ nameCN="当事人地址" value="云南省昆明市寻甸回族彝族自治县倘甸镇白章村委会芭蕉树村85号"/><GJ nameCN="国籍" value="中国"/><DSRLB nameCN="当事人类别" value="被告人"/><QZCS nameCN="强制措施"><QZCSZL nameCN="强制措施种类" value="拘留"/><QZCSZXSJ nameCN="强制措施执行时间" value="2015年5月18日"/><QZCSZXDW nameCN="强制措施执行单位" value="马龙县公安局"/><QZCSYYFZ nameCN="强制措施原因组"><QZCSYY nameCN="强制措施原因" value="交通肇事罪"/></QZCSYYFZ></QZCS><QZCS nameCN="强制措施"><QZCSZL nameCN="强制措施种类" value="逮捕"/><QZCSPZSJ nameCN="强制措施批准时间" value="2015年6月1日"/><QZCSPZDW nameCN="强制措施批准单位" value="马龙县人民检察院"/></QZCS><QZCS nameCN="强制措施"><QZCSZL nameCN="强制措施种类" value="逮捕"/><QZCSZXSJ nameCN="强制措施执行时间" value="2015年6月1日"/><QZCSZXDW nameCN="强制措施执行单位" value="马龙县公安局"/></QZCS><JYCS nameCN="羁押场所" value="马龙县看守所"/><BDBRQ nameCN="被逮捕日期" value="2015年6月1日"/><PZDBJG nameCN="批准逮捕机关" value="检察院"/><HXKYQNFZ nameCN="缓刑考验期内犯罪" value="否"/><JSKYQNFZ nameCN="假释考验期内犯罪" value="否"/><XSZRNL nameCN="刑事责任能力" value="完全刑事责任能力"/><BSSSDW nameCN="本审诉讼地位" value="被告人"/><SFBHR nameCN="是否被害人" value="否"/><ZRRSF nameCN="自然人身份" value="其他"/></YSF><DLR nameCN="代理人" value="辩护人梁晋，云南万成（寻甸）律师事务所律师。"><SSCYR nameCN="诉讼参与人" value="梁晋"/><SSSF nameCN="诉讼身份" value="辩护人"/><DSRLX nameCN="当事人类型" value="自然人"/><DWZWFZ nameCN="单位职务分组"><ZW nameCN="职务" value="律师"/><DWMC nameCN="单位名称" value="云南万成（寻甸）律师事务所"/><DWXZ nameCN="单位性质" value="事业单位"/></DWZWFZ><GJ nameCN="国籍" value="中国"/><DSRLB nameCN="当事人类别" value="代理人"/><CYRSSDW nameCN="参与人诉讼地位" value="辩护人"/><BHZL nameCN="辩护种类" value="委托辩护"/><BHDX nameCN="辩护对象" value="毛连胜"/><DLRBHRZYLX nameCN="代理人辩护人职业类型" value="职业律师"/><BHRHSSDLRLX nameCN="辩护人或诉讼代理人类型" value="律师"/><ZRRSF nameCN="自然人身份" value="职员"/></DLR><BGRQX nameCN="被告人缺席" value="无缺席"/></DSR><SSJL nameCN="诉讼记录" value=" 马龙县人民检察院以马检公诉刑诉（2015）27号起诉书指控被告人毛连胜犯交通肇事罪，于2015年6月29日向本院提起公诉。经审查，本院于2015年6月30日受理后，依法组成合议庭，于2015年8月5日公开开庭进行了审理。马龙县人民检察院依法指派检察员高龙等二人出庭支持公诉。被告人毛连胜及其辩护人梁晋到庭参加诉讼。本案现已审理终结。"><KTSL nameCN="开庭审理" value="是"/><KTSLXX nameCN="开庭审理信息" value="公开审理"/><KTRQ nameCN="开庭日期" value="2015年8月5日"/><CTJCYs nameCN="出庭检察员"><JCYFZ nameCN="检察员分组"><JS nameCN="角色" value="检察员"/><JCY nameCN="检察员" value="高龙等二人"/></JCYFZ></CTJCYs><SSXZ nameCN="诉讼性质" value="公诉"/><QSRQ nameCN="起诉日期" value="2015年6月29日"/><JCYJYYQSL nameCN="检察院建议延期审理" value="否"/><SNFT nameCN="少年法庭" value="否"/><ZKXX nameCN="指控信息"><ZKJL nameCN="指控记录"><ZKZM nameCN="指控罪名" value="交通肇事罪"><ZMDM nameCN="罪名代码" value="51"/><WZZM nameCN="完整罪名" value="交通肇事罪"/></ZKZM><XGR nameCN="相关人" value="毛连胜"/></ZKJL></ZKXX><QSZAY nameCN="起诉主案由" value="交通肇事罪"><ZMDM nameCN="罪名代码" value="51"/><WZZM nameCN="完整罪名" value="交通肇事罪"/></QSZAY><YSAJSYCX nameCN="一审案件适用程序" value="普通程序"/><JYSYJYCX nameCN="建议适用简易程序" value="无"/><DRSP nameCN="独任审判" value="否"/><YSAJLY nameCN="一审案件来源" value="新收公诉"/><GSJG nameCN="公诉机关" value="马龙县人民检察院"/><GSAH nameCN="公诉案号" value="马检公诉刑诉（2015）27号"/><JYZPT nameCN="简易转普通" value="否"/><SLRQ nameCN="受理日期" value="2015年6月30日"/><SPZZ nameCN="审判组织" value="合议庭"/><CTDSRXX nameCN="出庭当事人信息"><CTRXM nameCN="出庭人姓名" value="毛连胜"><SSDW nameCN="诉讼地位" value="被告人"/></CTRXM><CTRXM nameCN="出庭人姓名" value="梁晋"><SSDW nameCN="诉讼地位" value="辩护人"/></CTRXM></CTDSRXX></SSJL><AJJBQK nameCN="案件基本情况" value=" 马龙县人民检察院指控：2015年5月15日20时许，被告人毛连胜驾驶云AE1598号重型自卸货车，沿“沪瑞线”由曲靖市方向马龙县方向超载运输焦灰。23时许，毛连胜驾驶车辆行至“沪瑞线”K2656＋100M处时，其所驾驶车辆在超越前方同向行驶的由唐石生驾驶的云D53926号小型轿车（车载其妻杨利琴）过程中，遇唐石生驾驶车辆左转行驶，毛连胜驾驶车辆超越该车时，未按照操作规范安全驾驶，导致其所驾驶的车辆侧翻压于唐石生所驾驶的车辆上，造成唐石生及乘车人杨利琴当场死亡及两车不同程度受损的道路交通事故。经认定，毛连胜承担此次事故的全部责任。 事故发生后，毛连胜明知他人报案而在现场等待处理，其到案后如实供述自己的罪行。 据此，公诉机关认为，被告人毛连胜违反道路交通安全法律、法规，驾驶超载机动车辆上路行驶，未与前车保持足以采取紧急制动措施的安全距离，行至交叉路口时超车，未按照操作规范安全驾驶、文明驾驶，发生交通事故，致二人死亡、两车受损，情节特别恶劣，其行为已涉嫌触犯《中华人民共和国刑法》第一百三十三条之规定，应以交通肇事罪追究其刑事责任。同时，依据“刑法”第六十七条第一款之规定，毛连胜的行为具备自首情节，可以从轻或者减轻处罚。 在量刑方面，公诉机关建议本院对被告人毛连胜在有期徒刑三年至四年内判处刑罚。 针对指控的事实，公诉机关向本院移送了指控被告人犯罪的案件来源材料、证人证言、现场勘查笔录及照片、尸体检验意见书及照片、鉴定意见、道路交通事故责任认定书以及被告人供述及辩解等证据。 被告人毛连胜对公诉机关指控的犯罪事实、罪名及量刑建议均无异议，未提出辩解意见。 被告人毛连胜的辩护人提出如下辩护意见：1、被告人毛连胜在得知朋友报警后，在现场等待警察到来，归案后亦如实供述自己的罪行，系自首，可以从轻或者减轻处罚；2、被告人毛连胜在案发后其家属赔偿了被害人家属15万元，并已实际支付，取得被害人家属的谅解，应依法对其从轻处罚。综上所述，建议法庭对被告人毛连胜处三年以下有期徒刑并依法适用缓刑。 经审理查明：2015年5月15日，被告人毛连胜驾驶云AE1598号重型自卸货车（核定载人数2人，实际载人数3人；核定载质量16000kg，实际载质量18100kg）沿沪瑞线由曲靖市方向向马龙县方向行驶，22时50分许，行驶至沪瑞线（马龙县境内）k2656＋100M处时，其所驾车辆在超越前方同方向内行驶的由唐石生驾驶的云D53926号小型轿车（核定载人数5人，实际载人数3人；核定载质量16000kg，实际载人数2人）过程中，遇云D53926号车由西向东左转弯行驶时，车身右前部与云D53926号车车身左前部发生碰撞，碰撞过程中，云AE1598号车从左至右发生侧翻，车身右侧压于云D53926号车车身，造成云D53926号车驾驶人唐石生、云D53926号车乘车人杨利琴当场死亡、两车及道路周边设施不同程度受损的道路交通事故。2015年5月25日，马龙县公安局交通警察大队作出马公交认字（2015）第5303213201500005号道路交通事故认定书，认定被告人毛连胜承担此次事故的全部责任，唐石生、杨利琴不承担此事故的责任。 事故发生后，被告人毛连胜的熟人驾车经过案发现场，并用电话报了警，被告人毛连胜明知他人报案而在事故现场等待交警部门的调查处理，其到案后如实供述自己的犯罪事实及经过。 本次交通事故引起的民事赔偿纠纷，被害人的家属已与被告人毛连胜及其车辆登记挂靠公司、肇事车辆承保的保险公司等责任主体达成一致调解协议。被告人毛连胜及其车辆登记挂靠公司已履行赔偿义务。被害人的家属对被告人毛连胜的行为表示谅解，请求法院对其从轻处罚并适用缓刑。 上述事实，有以下经法庭举证、质证的证据予以证明，本院予以确认：1、受理道路事故案件登记表、接受刑事案件登记表、立案决定书及到案经过证明交通事故发生后，被告人毛连胜的熟人主动用电话报警后被告人毛连胜一直留在事故现场等待交警部门调查处理的事实。2、道路交通事故技术鉴定委托书（尸体检验）、昆明医科大学司法鉴定中心交通事故检验报告、死亡医学证明书证明本次交通事故造成唐石生、杨利琴死亡的事实。3、道路交通事故现场勘查笔录及照片、交通事故现场图证明本次交通事故发生的地点。4、道路交通事故技术鉴定委托书（车辆检验）、曲靖恒通司法鉴定所曲恒通（2015）车鉴字第535号鉴定意见书证明云AE1598号车在发生事故时转向系、制动系、灯光电器符合相关技术条件，车辆无机械故障，车速无法计算的事实。5、道路交通事故技术鉴定委托书（车辆检验）、曲靖恒通司法鉴定所曲恒通（2015）车鉴字第536号鉴定意见书证明云D53926号车在发生事故时转向系、制动系符合相关技术条件，车辆无机械故障，左、右后转向信号灯、制动灯灯具肇事严重损坏无法检验以及车速无法计算的事实。6、道路交通事故技术鉴定委托书（血液中酒精测定）、曲靖恒通司法鉴定所曲恒通（2015）毒检字第308号鉴定意见书证明被告人毛连胜交通肇事时不存在酒驾情形。7、道路交通事故技术鉴定委托书（血液中酒精测定）、曲靖恒通司法鉴定所曲恒通（2015）毒检字第307号鉴定意见书证明被害人唐石生交通肇事时不存在酒驾情形。8、马龙县公安局交通警察大队检验、鉴定告知书证明交警部门将被害人唐石生、杨利琴死亡原因的鉴定意见、肇事时双方驾驶员不存在酒驾情形及肇事车辆安全技术检验情况的鉴定意见告知事故当事人及被害人家属的事实。9、道路交通事故认定书证明被告人毛连胜负此次事故的全部责任，被害人唐石生、杨利琴无责任。10、被告人毛连胜的供述，被害人家属王某香、唐某琪、唐梦某及杨国云的陈述，证人雷丽琼、杨某应的证言，相互印证证明交通事故发生的时间、地点、经过及毛连胜到案后如实供述自己罪行的事实。12、被告人毛连胜的身份证复印件、常住人口信息表、违法犯罪前科查询结果单一份，证明被告人的年龄、身份及无违法犯罪记录等基本情况。 另有机动车驾驶证、机动车行驶证、过磅单、行政强制措施凭证、保险单、谅解书等证据证明本案审理查明的事实。 "><ZZQK nameCN="质证情况" value="质证"/><BHR nameCN="被害人"><BHRXM nameCN="被害人姓名" value="唐石生"/><SFSW nameCN="是否死亡" value="是"/></BHR><BHR nameCN="被害人"><BHRXM nameCN="被害人姓名" value="杨利琴"/><SFSW nameCN="是否死亡" value="是"/></BHR><ZKDL nameCN="指控段落" value=" 马龙县人民检察院指控：2015年5月15日20时许，被告人毛连胜驾驶云AE1598号重型自卸货车，沿“沪瑞线”由曲靖市方向马龙县方向超载运输焦灰。23时许，毛连胜驾驶车辆行至“沪瑞线”K2656＋100M处时，其所驾驶车辆在超越前方同向行驶的由唐石生驾驶的云D53926号小型轿车（车载其妻杨利琴）过程中，遇唐石生驾驶车辆左转行驶，毛连胜驾驶车辆超越该车时，未按照操作规范安全驾驶，导致其所驾驶的车辆侧翻压于唐石生所驾驶的车辆上，造成唐石生及乘车人杨利琴当场死亡及两车不同程度受损的道路交通事故。经认定，毛连胜承担此次事故的全部责任。 事故发生后，毛连胜明知他人报案而在现场等待处理，其到案后如实供述自己的罪行。 据此，公诉机关认为，被告人毛连胜违反道路交通安全法律、法规，驾驶超载机动车辆上路行驶，未与前车保持足以采取紧急制动措施的安全距离，行至交叉路口时超车，未按照操作规范安全驾驶、文明驾驶，发生交通事故，致二人死亡、两车受损，情节特别恶劣，其行为已涉嫌触犯《中华人民共和国刑法》第一百三十三条之规定，应以交通肇事罪追究其刑事责任。同时，依据“刑法”第六十七条第一款之规定，毛连胜的行为具备自首情节，可以从轻或者减轻处罚。 在量刑方面，公诉机关建议本院对被告人毛连胜在有期徒刑三年至四年内判处刑罚。 针对指控的事实，公诉机关向本院移送了指控被告人犯罪的案件来源材料、证人证言、现场勘查笔录及照片、尸体检验意见书及照片、鉴定意见、道路交通事故责任认定书以及被告人供述及辩解等证据。 "><ZKSS nameCN="指控事实" value="马龙县人民检察院指控：2015年5月15日20时许，被告人毛连胜驾驶云AE1598号重型自卸货车，沿“沪瑞线”由曲靖市方向马龙县方向超载运输焦灰。23时许，毛连胜驾驶车辆行至“沪瑞线”K2656＋100M处时，其所驾驶车辆在超越前方同向行驶的由唐石生驾驶的云D53926号小型轿车（车载其妻杨利琴）过程中，遇唐石生驾驶车辆左转行驶，毛连胜驾驶车辆超越该车时，未按照操作规范安全驾驶，导致其所驾驶的车辆侧翻压于唐石生所驾驶的车辆上，造成唐石生及乘车人杨利琴当场死亡及两车不同程度受损的道路交通事故。经认定，毛连胜承担此次事故的全部责任。 事故发生后，毛连胜明知他人报案而在现场等待处理，其到案后如实供述自己的罪行。 "/><ZKZJ nameCN="指控证据" value="针对指控的事实，公诉机关向本院移送了指控被告人犯罪的案件来源材料、证人证言、现场勘查笔录及照片、尸体检验意见书及照片、鉴定意见、道路交通事故责任认定书以及被告人供述及辩解等证据。"/><ZKYJ nameCN="指控意见" value="据此，公诉机关认为，被告人毛连胜违反道路交通安全法律、法规，驾驶超载机动车辆上路行驶，未与前车保持足以采取紧急制动措施的安全距离，行至交叉路口时超车，未按照操作规范安全驾驶、文明驾驶，发生交通事故，致二人死亡、两车受损，情节特别恶劣，其行为已涉嫌触犯《中华人民共和国刑法》第一百三十三条之规定，应以交通肇事罪追究其刑事责任。同时，依据“刑法”第六十七条第一款之规定，毛连胜的行为具备自首情节，可以从轻或者减轻处罚。 在量刑方面，公诉机关建议本院对被告人毛连胜在有期徒刑三年至四年内判处刑罚。 "/></ZKDL><BHDL nameCN="辩护段落" value="被告人毛连胜对公诉机关指控的犯罪事实、罪名及量刑建议均无异议，未提出辩解意见。 被告人毛连胜的辩护人提出如下辩护意见：1、被告人毛连胜在得知朋友报警后，在现场等待警察到来，归案后亦如实供述自己的罪行，系自首，可以从轻或者减轻处罚；2、被告人毛连胜在案发后其家属赔偿了被害人家属15万元，并已实际支付，取得被害人家属的谅解，应依法对其从轻处罚。综上所述，建议法庭对被告人毛连胜处三年以下有期徒刑并依法适用缓刑。 "><BGRBC nameCN="被告人辩称" value="被告人毛连胜对公诉机关指控的犯罪事实、罪名及量刑建议均无异议，未提出辩解意见。 "/><BHRBH nameCN="辩护人辩护" value="被告人毛连胜的辩护人提出如下辩护意见：1、被告人毛连胜在得知朋友报警后，在现场等待警察到来，归案后亦如实供述自己的罪行，系自首，可以从轻或者减轻处罚；2、被告人毛连胜在案发后其家属赔偿了被害人家属15万元，并已实际支付，取得被害人家属的谅解，应依法对其从轻处罚。综上所述，建议法庭对被告人毛连胜处三年以下有期徒刑并依法适用缓刑。"><BHYJ nameCN="辩护意见"><BGRXM nameCN="被告人姓名" value="毛连胜"/><BHYJZL nameCN="辩护意见种类" value="罪轻辩护"/></BHYJ></BHRBH></BHDL><BSSLD nameCN="本审审理段" value="经审理查明：2015年5月15日，被告人毛连胜驾驶云AE1598号重型自卸货车（核定载人数2人，实际载人数3人；核定载质量16000kg，实际载质量18100kg）沿沪瑞线由曲靖市方向向马龙县方向行驶，22时50分许，行驶至沪瑞线（马龙县境内）k2656＋100M处时，其所驾车辆在超越前方同方向内行驶的由唐石生驾驶的云D53926号小型轿车（核定载人数5人，实际载人数3人；核定载质量16000kg，实际载人数2人）过程中，遇云D53926号车由西向东左转弯行驶时，车身右前部与云D53926号车车身左前部发生碰撞，碰撞过程中，云AE1598号车从左至右发生侧翻，车身右侧压于云D53926号车车身，造成云D53926号车驾驶人唐石生、云D53926号车乘车人杨利琴当场死亡、两车及道路周边设施不同程度受损的道路交通事故。2015年5月25日，马龙县公安局交通警察大队作出马公交认字（2015）第5303213201500005号道路交通事故认定书，认定被告人毛连胜承担此次事故的全部责任，唐石生、杨利琴不承担此事故的责任。 事故发生后，被告人毛连胜的熟人驾车经过案发现场，并用电话报了警，被告人毛连胜明知他人报案而在事故现场等待交警部门的调查处理，其到案后如实供述自己的犯罪事实及经过。 本次交通事故引起的民事赔偿纠纷，被害人的家属已与被告人毛连胜及其车辆登记挂靠公司、肇事车辆承保的保险公司等责任主体达成一致调解协议。被告人毛连胜及其车辆登记挂靠公司已履行赔偿义务。被害人的家属对被告人毛连胜的行为表示谅解，请求法院对其从轻处罚并适用缓刑。 上述事实，有以下经法庭举证、质证的证据予以证明，本院予以确认：1、受理道路事故案件登记表、接受刑事案件登记表、立案决定书及到案经过证明交通事故发生后，被告人毛连胜的熟人主动用电话报警后被告人毛连胜一直留在事故现场等待交警部门调查处理的事实。2、道路交通事故技术鉴定委托书（尸体检验）、昆明医科大学司法鉴定中心交通事故检验报告、死亡医学证明书证明本次交通事故造成唐石生、杨利琴死亡的事实。3、道路交通事故现场勘查笔录及照片、交通事故现场图证明本次交通事故发生的地点。4、道路交通事故技术鉴定委托书（车辆检验）、曲靖恒通司法鉴定所曲恒通（2015）车鉴字第535号鉴定意见书证明云AE1598号车在发生事故时转向系、制动系、灯光电器符合相关技术条件，车辆无机械故障，车速无法计算的事实。5、道路交通事故技术鉴定委托书（车辆检验）、曲靖恒通司法鉴定所曲恒通（2015）车鉴字第536号鉴定意见书证明云D53926号车在发生事故时转向系、制动系符合相关技术条件，车辆无机械故障，左、右后转向信号灯、制动灯灯具肇事严重损坏无法检验以及车速无法计算的事实。6、道路交通事故技术鉴定委托书（血液中酒精测定）、曲靖恒通司法鉴定所曲恒通（2015）毒检字第308号鉴定意见书证明被告人毛连胜交通肇事时不存在酒驾情形。7、道路交通事故技术鉴定委托书（血液中酒精测定）、曲靖恒通司法鉴定所曲恒通（2015）毒检字第307号鉴定意见书证明被害人唐石生交通肇事时不存在酒驾情形。8、马龙县公安局交通警察大队检验、鉴定告知书证明交警部门将被害人唐石生、杨利琴死亡原因的鉴定意见、肇事时双方驾驶员不存在酒驾情形及肇事车辆安全技术检验情况的鉴定意见告知事故当事人及被害人家属的事实。9、道路交通事故认定书证明被告人毛连胜负此次事故的全部责任，被害人唐石生、杨利琴无责任。10、被告人毛连胜的供述，被害人家属王某香、唐某琪、唐梦某及杨国云的陈述，证人雷丽琼、杨某应的证言，相互印证证明交通事故发生的时间、地点、经过及毛连胜到案后如实供述自己罪行的事实。12、被告人毛连胜的身份证复印件、常住人口信息表、违法犯罪前科查询结果单一份，证明被告人的年龄、身份及无违法犯罪记录等基本情况。 另有机动车驾驶证、机动车行驶证、过磅单、行政强制措施凭证、保险单、谅解书等证据证明本案审理查明的事实。 "><ZJXX nameCN="证据信息"><ZJFZ nameCN="证据分组"><RDSS nameCN="认定事实" value="经审理查明：2015年5月15日，被告人毛连胜驾驶云AE1598号重型自卸货车（核定载人数2人，实际载人数3人；核定载质量16000kg，实际载质量18100kg）沿沪瑞线由曲靖市方向向马龙县方向行驶，22时50分许，行驶至沪瑞线（马龙县境内）k2656＋100M处时，其所驾车辆在超越前方同方向内行驶的由唐石生驾驶的云D53926号小型轿车（核定载人数5人，实际载人数3人；核定载质量16000kg，实际载人数2人）过程中，遇云D53926号车由西向东左转弯行驶时，车身右前部与云D53926号车车身左前部发生碰撞，碰撞过程中，云AE1598号车从左至右发生侧翻，车身右侧压于云D53926号车车身，造成云D53926号车驾驶人唐石生、云D53926号车乘车人杨利琴当场死亡、两车及道路周边设施不同程度受损的道路交通事故。2015年5月25日，马龙县公安局交通警察大队作出马公交认字（2015）第5303213201500005号道路交通事故认定书，认定被告人毛连胜承担此次事故的全部责任，唐石生、杨利琴不承担此事故的责任。 事故发生后，被告人毛连胜的熟人驾车经过案发现场，并用电话报了警，被告人毛连胜明知他人报案而在事故现场等待交警部门的调查处理，其到案后如实供述自己的犯罪事实及经过。 本次交通事故引起的民事赔偿纠纷，被害人的家属已与被告人毛连胜及其车辆登记挂靠公司、肇事车辆承保的保险公司等责任主体达成一致调解协议。被告人毛连胜及其车辆登记挂靠公司已履行赔偿义务。被害人的家属对被告人毛连胜的行为表示谅解，请求法院对其从轻处罚并适用缓刑。 "/><ZJJL nameCN="证据记录" value="本院予以确认：1、受理道路事故案件登记表、接受刑事案件登记表、立案决定书及到案经过证明交通事故发生后，被告人毛连胜的熟人主动用电话报警后被告人毛连胜一直留在事故现场等待交警部门调查处理的事实。2、道路交通事故技术鉴定委托书（尸体检验）、昆明医科大学司法鉴定中心交通事故检验报告、死亡医学证明书证明本次交通事故造成唐石生、杨利琴死亡的事实。3、道路交通事故现场勘查笔录及照片、交通事故现场图证明本次交通事故发生的地点。4、道路交通事故技术鉴定委托书（车辆检验）、曲靖恒通司法鉴定所曲恒通（2015）车鉴字第535号鉴定意见书证明云AE1598号车在发生事故时转向系、制动系、灯光电器符合相关技术条件，车辆无机械故障，车速无法计算的事实。5、道路交通事故技术鉴定委托书（车辆检验）、曲靖恒通司法鉴定所曲恒通（2015）车鉴字第536号鉴定意见书证明云D53926号车在发生事故时转向系、制动系符合相关技术条件，车辆无机械故障，左、右后转向信号灯、制动灯灯具肇事严重损坏无法检验以及车速无法计算的事实。6、道路交通事故技术鉴定委托书（血液中酒精测定）、曲靖恒通司法鉴定所曲恒通（2015）毒检字第308号鉴定意见书证明被告人毛连胜交通肇事时不存在酒驾情形。7、道路交通事故技术鉴定委托书（血液中酒精测定）、曲靖恒通司法鉴定所曲恒通（2015）毒检字第307号鉴定意见书证明被害人唐石生交通肇事时不存在酒驾情形。8、马龙县公安局交通警察大队检验、鉴定告知书证明交警部门将被害人唐石生、杨利琴死亡原因的鉴定意见、肇事时双方驾驶员不存在酒驾情形及肇事车辆安全技术检验情况的鉴定意见告知事故当事人及被害人家属的事实。9、道路交通事故认定书证明被告人毛连胜负此次事故的全部责任，被害人唐石生、杨利琴无责任。10、被告人毛连胜的供述，被害人家属王某香、唐某琪、唐梦某及杨国云的陈述，证人雷丽琼、杨某应的证言，相互印证证明交通事故发生的时间、地点、经过及毛连胜到案后如实供述自己罪行的事实。12、被告人毛连胜的身份证复印件、常住人口信息表、违法犯罪前科查询结果单一份，证明被告人的年龄、身份及无违法犯罪记录等基本情况。 "><ZJMX nameCN="证据明细"><MC nameCN="名称" value="本院予以确认"/><ZL nameCN="种类" value="其他"/><TJR nameCN="提交人" value="2、道路交通事故技术鉴定委托书（尸体检验）、昆明医科大学司法鉴定中心"/></ZJMX></ZJJL></ZJFZ><ZJFZ nameCN="证据分组"><ZJJL nameCN="证据记录" value="本案审理查明的事实。"><ZJMX nameCN="证据明细"><MC nameCN="名称" value="本案审理查明的事实"/><ZL nameCN="种类" value="其他"/></ZJMX></ZJJL></ZJFZ></ZJXX><ZRXX nameCN="证人信息"><ZR nameCN="证人" value="雷丽琼"/><ZR nameCN="证人" value="杨某应"/></ZRXX></BSSLD></AJJBQK><CPFXGC nameCN="裁判分析过程" value="本院认为，被告人毛连胜违反道路交通运输管理法规，驾驶超载机动车辆上路行驶，未与前车保持足以采取紧急制动措施的安全距离，行至交叉路口时超车，未按照操作规范安全驾驶、文明驾驶，发生交通事故，致二人死亡，且对事故负全部责任，其行为已构成交通肇事罪。公诉机关指控的犯罪事实和罪名成立，本院予以支持。案发后，被告人明知他人报案而在事故现场等待处理并在归案后如实供述其犯罪事实，系自首，依法可以对其从轻处罚。庭审中，被告人认罪态度较好，具有一定的悔罪表现，且庭审后，被害人家属与被告人毛连胜及其车辆登记挂靠公司、肇事车辆承保的保险公司等责任主体就民事部分达成一致调解协议，被告人毛连胜及其车辆登记挂靠公司已履行赔偿义务，被害人家属对被告人的行为表示谅解，可酌情对被告人从轻处罚。 公诉机关提出的量刑建议，符合罪责刑相适应原则，本院予以采纳，但综合被告人的犯罪性质、情节，可对被告人宣告缓刑。对被告人毛连胜的辩护人提出的第1、2点辩护意见本院予以采纳，对其“建议法庭对被告人处三年以下有期徒刑”的辩护意见，与法律规定不符，本院不予采纳。 综上所述，根据被告人犯罪的事实、性质、情节、社会危害程度以及悔罪表现，依照《中华人民共和国刑法》第一百三十三条、第六十七条第一款、第七十二条、第七十三条第二款、第三款及《最高人民法院〈关于审理交通肇事刑事案件具体应用法律若干问题的解释〉》第四条之规定，判决如下："><LXQJ nameCN="量刑情节"><FDLXQJ nameCN="法定量刑情节"><XGR nameCN="相关人" value="毛连胜"/><QJ nameCN="情节" value="自首"/><LXQJLB nameCN="量刑情节类别" value="法定可以从轻情节"/></FDLXQJ><ZDLXQJ nameCN="酌定量刑情节"><XGR nameCN="相关人" value="毛连胜"/><QJ nameCN="情节" value="认罪态度好"/><LXQJLB nameCN="量刑情节类别" value="酌定从轻情节"/></ZDLXQJ></LXQJ><BGRTYRZCX nameCN="被告人同意认罪程序" value="是"/><FLFTYY nameCN="法律法条引用"><FLFTFZ nameCN="法律法条分组"><MC nameCN="名称" value="《中华人民共和国刑法》"/><T nameCN="条" value="第一百三十三条"/><T nameCN="条" value="第六十七条"><K nameCN="款" value="第一款"/></T><T nameCN="条" value="第七十二条"/><T nameCN="条" value="第七十三条"><K nameCN="款" value="第二款"/><K nameCN="款" value="第三款"/></T></FLFTFZ><FLFTFZ nameCN="法律法条分组"><MC nameCN="名称" value="《最高人民法院〈关于审理交通肇事刑事案件具体应用法律若干问题的解释〉》"/><T nameCN="条" value="第四条"/></FLFTFZ></FLFTYY><CUS_FLFT_FZ_RY nameCN="法律法条分组冗余"><CUS_FLFT_RY nameCN="法律法条" value="《中华人民共和国刑法》第一百三十三条"/><CUS_FLFT_RY nameCN="法律法条" value="《中华人民共和国刑法》第六十七条第一款"/><CUS_FLFT_RY nameCN="法律法条" value="《中华人民共和国刑法》第七十二条"/><CUS_FLFT_RY nameCN="法律法条" value="《中华人民共和国刑法》第七十三条第二款"/><CUS_FLFT_RY nameCN="法律法条" value="《中华人民共和国刑法》第七十三条第三款"/><CUS_FLFT_RY nameCN="法律法条" value="《最高人民法院〈关于审理交通肇事刑事案件具体应用法律若干问题的解释〉》第四条"/></CUS_FLFT_FZ_RY></CPFXGC><PJJG nameCN="判决结果" value=" 被告人毛连胜犯交通肇事罪，判处有期徒刑三年，缓刑五年。（缓刑考验期限，从判决确定之日起计算。） 如不服本判决，可在接到判决书的第二日起十日内，通过本院或者直接向云南省曲靖市中级人民法院提出上诉。书面上诉的应当提交上诉状正本一份，副本三份。"><GXQYY nameCN="提出管辖权异议" value="否"/><YSJAFS nameCN="一审结案方式" value="判决"/><YSXSBFCPJG nameCN="一审刑事部分裁判结果" value="判决"/><XSPJJGFZ nameCN="刑事判决结果分组"><SSCYR nameCN="诉讼参与人" value="毛连胜"/><BSPJJG nameCN="本审判决结果"><DZPF nameCN="单罪判罚" value="犯交通肇事罪，判处有期徒刑三年，缓刑五年。（缓刑考验期限，从判决确定之日起计算。）"><ZM nameCN="罪名" value="交通肇事罪"><ZMDM nameCN="罪名代码" value="51"/><WZZM nameCN="完整罪名" value="交通肇事罪"/></ZM><HX nameCN="缓刑"><HXLB nameCN="缓刑类别" value="普通缓刑"/><HXXQ nameCN="缓刑刑期" value="五年"/></HX><ZX nameCN="主刑"><ZXLB nameCN="主刑类别" value="有期徒刑"/><ZXXQ nameCN="主刑刑期" value="三年"/></ZX><PJJGLX nameCN="判决结果类型" value="给予刑事处罚"/></DZPF><ZXPF nameCN="执行判罚" value="犯交通肇事罪，判处有期徒刑三年，缓刑五年。（缓刑考验期限，从判决确定之日起计算。）"><HX nameCN="缓刑"><HXLB nameCN="缓刑类别" value="普通缓刑"/><HXXQ nameCN="缓刑刑期" value="五年"/></HX><ZX nameCN="主刑"><ZXLB nameCN="主刑类别" value="有期徒刑"/><ZXXQ nameCN="主刑刑期" value="三年"/></ZX><PJJGLX nameCN="判决结果类型" value="给予刑事处罚"/></ZXPF><PJZZM nameCN="判决主罪名" value="交通肇事罪"><ZMDM nameCN="罪名代码" value="51"/><WZZM nameCN="完整罪名" value="交通肇事罪"/></PJZZM></BSPJJG><MXHWZSF nameCN="免刑或无罪释放" value="否"/><SZBF nameCN="数罪并罚" value="否"/><HBLX nameCN="合并量刑" value="否"/></XSPJJGFZ><KSSZ nameCN="可上诉至" value="云南省曲靖市中级人民法院"/><SSTJCL nameCN="上诉提交材料" value="上诉状正本一份，副本三份"/><SSQX nameCN="上诉期限" value="十日"/></PJJG><WW nameCN="文尾" value=" 审判长朱永平 审判员张雄采 人民陪审员杨丽娟 二〇一五年九月二十五日 书记员祖雯静 "><CPSJ nameCN="裁判时间" value="2015年9月25日"><JAND nameCN="结案年度" value="2015"/><CUS_JANYR nameCN="结案年月日" value="2015年9月25日"/><CUS_JANY nameCN="结案年月" value="2015-9"/><CUS_JAYF nameCN="结案月份" value="9"/></CPSJ><SPZZCY nameCN="审判组织成员"><SPRYXM nameCN="审判人员姓名" value="朱永平"/><SPRYJS nameCN="审判人员角色" value="审判长"/></SPZZCY><SPZZCY nameCN="审判组织成员"><SPRYXM nameCN="审判人员姓名" value="张雄采"/><SPRYJS nameCN="审判人员角色" value="审判员"/></SPZZCY><SPZZCY nameCN="审判组织成员"><SPRYXM nameCN="审判人员姓名" value="杨丽娟"/><SPRYJS nameCN="审判人员角色" value="人民陪审员"/></SPZZCY><SPZZCY nameCN="审判组织成员"><SPRYXM nameCN="审判人员姓名" value="祖雯静"/><SPRYJS nameCN="审判人员角色" value="书记员"/></SPZZCY></WW><WSSFMH nameCN="文书是否模糊" value="否"/><CUS_SJ nameCN="时间"><CUS_YW nameCN="原文" value="马龙县人民检察院以马检公诉刑诉（2015）27号起诉书指控被告人毛连胜犯交通肇事罪，于2015年6月29日向本院提起公诉"/><CUS_SJYW nameCN="时间原文" value="马龙县人民检察院以马检公诉刑诉（2015）27号起诉书指控被告人毛连胜犯交通肇事罪，于2015年6月29日向本院提起公诉"/><CUS_JTSJ nameCN="具体时间" value="2015年6月29日"/></CUS_SJ><CUS_SJ nameCN="时间"><CUS_YW nameCN="原文" value="经审查，本院于2015年6月30日受理后，依法组成合议庭，于2015年8月5日公开开庭进行了审理"/><CUS_SJYW nameCN="时间原文" value="经审查，本院于2015年6月30日受理后，依法组成合议庭，于2015年8月5日公开开庭进行了审理"/><CUS_JTSJ nameCN="具体时间" value="2015年6月30日"/></CUS_SJ><CUS_SJ nameCN="时间"><CUS_YW nameCN="原文" value="马龙县人民检察院指控：2015年5月15日20时许，被告人毛连胜驾驶云AE1598号重型自卸货车，沿“沪瑞线”由曲靖市方向马龙县方向超载运输焦灰"/><CUS_SJYW nameCN="时间原文" value="马龙县人民检察院指控：2015年5月15日20时许，被告人毛连胜驾驶云AE1598号重型自卸货车，沿“沪瑞线”由曲靖市方向马龙县方向超载运输焦灰"/><CUS_JTSJ nameCN="具体时间" value="2015年5月15日"/></CUS_SJ><CUS_SJ nameCN="时间"><CUS_YW nameCN="原文" value="经审理查明：2015年5月15日，被告人毛连胜驾驶云AE1598号重型自卸货车（核定载人数2人，实际载人数3人"/><CUS_SJYW nameCN="时间原文" value="经审理查明：2015年5月15日，被告人毛连胜驾驶云AE1598号重型自卸货车（核定载人数2人，实际载人数3人"/><CUS_JTSJ nameCN="具体时间" value="2015年5月15日"/></CUS_SJ><CUS_SJ nameCN="时间"><CUS_YW nameCN="原文" value="2015年5月25日，马龙县公安局交通警察大队作出马公交认字（2015）第5303213201500005号道路交通事故认定书，认定被告人毛连胜承担此次事故的全部责任，唐石生、杨利琴不承担此事故的责任"/><CUS_SJYW nameCN="时间原文" value="2015年5月25日，马龙县公安局交通警察大队作出马公交认字（2015）第5303213201500005号道路交通事故认定书，认定被告人毛连胜承担此次事故的全部责任，唐石生、杨利琴不承担此事故的责任"/><CUS_JTSJ nameCN="具体时间" value="2015年5月25日"/></CUS_SJ><title value="毛连胜犯交通肇事罪"/><subTitle value="刑事一审判决书"/><slzq value="88"/></QW></writ>