<?xml version="1.0" encoding="UTF-8"?>
<writ><QW nameCN="全文" value=" 贵州省麻江县人民法院 刑事判决书 （2014）麻刑初字第86号 公诉机关贵州省麻江县人民检察院。 被告人宋建波，男，个人信息略。因涉嫌交通肇事罪于2014年7月15日被麻江县公安局取保候审。经本院决定，2014年12月4日被依法逮捕。现羁押于麻江县看守所。 辩护人何东，望江律师事务所律师。 麻江县人民检察院以麻检公诉刑诉（2014）73号起诉书指控被告人宋建波犯交通肇事罪，于2014年10月11日向本院提起公诉。本院依法组成合议庭，公开开庭审理了本案。麻江县人民检察院指派检察员陈摔出庭支持公诉，被告人宋建波及其辩护人何东到庭参加诉讼。现已审理终结。 麻江县人民检察院指控：2014年4月29日，被告人宋建波驾驶贵JP8385号小型普通客车在210国道由福泉往都匀方向行驶，22时30分，当行驶至210国道2459Km＋350m处时，遇对向来车未减速靠右通行，占线与对向由被害人张某学驾驶的贵HC9332号普通二轮摩托车碰撞，后被告人宋建波驾车逃离现场，造成摩托车驾驶员张某学经抢救无效于次日07：05分死亡及摩托车乘客宋某金受伤的道路交通事故。经麻江县公安局交警大队认定，被告人宋建波承担本次事故的全部责任。另查明，被告人宋建波已支付丧葬费、医疗费等费用共计7．548万元；保险公司也已支付1万元费用。 为支持其公诉，公诉机关向法庭提供的证据有：1、肇事车辆等物证；2、户籍证明、事故认定书等书证；3、证人罗某江等人的证言；4、被害人宋某金的陈述；5、被告人宋建波的供述与辩解；6、司法鉴定检验报告书、事故车辆检验报告；7、现场勘验笔录、现场图及照片等证据。 该院认为，被告人宋建波违反交通管理法规，发生1人死亡、1人受伤的道路交通事故，为逃避法律追究而逃离事故现场，其行为触犯了《中华人民共和国刑法》第一百三十三条的规定，应当以交通肇事罪追究刑事责任。现提起公诉，请依法判处。 被告人宋建波对公诉机关的指控无异议。 辩护人何东提出的辩护意见是：一、被害人张某学系非法营运，具有一定过错；二、被告人宋建波具有自首情节，应对其减轻处罚。 经审理查明，2014年4月29日，被告人宋建波驾驶贵JP8385号小型普通客车在210国道由福泉方向往都匀方向行驶，22时30分许，当行驶至210国道2459Km＋350m处时，遇对向来车未减速靠右通行，占线与对向由张某学驾驶的贵HC9332号普通二轮摩托车发生碰撞，造成张某学经抢救无效于次日07：05分死亡及乘客宋某金受伤的道路交通事故。被告人宋建波交通肇事后，为逃避法律追究而驾车逃逸现场。经麻江县公安局交通警察大队认定，宋建波承担事故的全部责任。 另查明，事发后被告人宋建波支付了死者张某学家属人民币5万元。 上述事实，有下列经庭审举证、质证、认证的证据予以证实： 1、道路交通事故现场勘查笔录、现场图、现场照片、交通事故车辆指认和现场记录及照片证实现场位于国道210线2459KM＋350M处，肇事车辆为贵JP8385小型普通客车；并用照片固定现场遗留物储水罐、红色塑料、黑色胶条等。 2、证人罗某江证言证实：2014年4月29日晚上十点过钟，我和妻子放水浇田，我脚痛就坐在公路旁的护栏石上休息，妻子一人去放水，她走得约一分钟左右，就有一辆从良田方向过来的二轮摩托车从我面前过，一两秒钟，我就听到“嘭”的一声，我朝声音的方向看，看见一辆小车从马场坪方向开过来，当时我知道撞车了，我看那小车没有停车，我用拐杖向小车摇晃，想让车停下来，但是小车加油朝良田街上跑了。我马上朝公路坎下喊：“小松，快拿电筒来，上面出事了。”小松等人打电筒上来看见一辆二轮摩托车倒在靠公路外坎的路面上，有一个人躺在摩托车旁边受伤严重，这时我们又听见公路外坎下面有人在哼，我们下去看，才发现还有一个伤员在路坎下面。这时从马场坪方向过来一辆小车，车上的人下来看见是出事就电话报警了，随后警察和救护车就来了。 3、证人陶某相证言证实：2014年4月29日晚上，我开车和潘杰校长从又诗小学返回麻江县城，晚上十点半左右经过新田坳时，看见有群众在路上围观，我停车下来看见一辆二轮摩托车倒在路上，驾驶员躺在摩托车旁边，伤得很严重，还有一个伤员在左边的路坎下面，听旁群众说好象是面包车撞的，面包车已经朝良田街上跑了，于是我就报警了，我还拿得车上的三角警示牌摆在路上，一直等到警察来了我才离开的。我看见现场有很多碎片，摩托车上卡着一块逃逸小车的保险杠护板，是黑色的。 4、证人施某香证言证实：宋建波是我的儿子，2014年4月29日那天下午4点过钟，我、女儿宋某英乘坐宋建波驾驶的贵JP8385号面包车从甘粑哨去麻江县土桥河我姐夫王某平家吊唁姑妈。晚饭后，宋建波开车送宋某英回马场坪，我在亲戚家守夜。晚上宋建波打电话给我，说来接我回家，等了一晚上宋建波都没有来，打电话给宋建波一直占线联系不上。第二天上午大概10点过钟，我接到侄子宋建华的电话，说宋建波开车在麻江发生车祸，麻江交警队在马场坪找宋建波，我回家看见宋建波在家里躺着，我问宋建波，他说29号晚上在麻江境内驾驶的面包车和一辆二轮摩托车碰了。过了一会儿，马场坪交警、麻江交警和宋建华来到我家把宋建波带走了。 5、证人宋某金证言证实：2014年4月29日晚上十点过钟我在麻江汽车站对面找得羊昌坡桐子园姓张的摩托车回两路口，到新田坳路段时，从马场坪方向有一辆小车超车过来，占着我们的线路把我们的摩托车撞了，我就昏过去了。 6、《驾驶人信息查询结果单》及宋继波和张某学《驾驶证》复印件分别证实二人准驾车型为C1和D；《机动车信息查询结果单》及贵JP8385号五菱车小型普通客车和贵HC9332普通二轮摩托车《行驶证》复印件分别证实车主系宋继波和张某学；《道路交通事故车辆技术检验报告》及照片证实贵JP8385号五菱车小型普通客车和贵HC9332普通二轮摩托车均符合机动车运行安全技术条件要求。 7、贵州省麻江县公安司法鉴定中心出具的（麻）公（司）鉴（尸）字（2014）027号《法医学尸体检验报告》及照片证实医院对张某学抢救记录为：经常规抢救30多分钟，患者未恢复自主心率，双侧瞳孔散大，对光反射消失，颈动脉未扪及波动感，四肢冰冷，行心电图检查回示为直线，与患者家属交代病情，患者家属同意后于2014年4月30日7：05分放弃抢救，宣布死亡，死亡原因脑干功能衰竭；鉴定意见张某学系交通事故致颅脑、胸腹腔脏器复合损伤死亡。 8、《道路交通事故逃逸嫌疑车辆痕迹勘验笔录》及照片证实勘验地点位于福泉市陆坪镇浪波河村长冲组26号李兵家院坝内；勘验对象系白色“贵JP8385号小型普通客车；勘验内容：（1）、前号牌脱落置于该车内，车后悬挂有贵JB8385号小型汽车号牌；（2）、该车前挡风玻璃呈粉碎状破损，前挡风玻璃框左上端处凹陷变形，并附着有毛发；（3）、该车左后视镜壳与底座断落，由导线连接，断口呈新印；（4）、引擎盖左侧面板凹陷变形，凹陷面板上有两条纵向红色漆印；（5）、该车左前大灯破损，破口呈新印，灯壳部分缺损；（6）、该车前保险杠左端破损缺失；（7）、该车中网左端破损缺失，破口呈新印；（8）、前保险杠下护板缺失；（9）、该车左前轮叶子板和防撞护板夹缝处嵌有一块破损的黑色胶条，上印有“一帆风顺”字样，胶条由螺丝连接一块破损的红色塑料，破口呈新印，红色塑料上有“吉祥”、“快车”、“平”字样和鹰形图案；（10）、勘验人员提取并保存了（9）中的黑色胶条和红色塑料。 9、《道路交通事故肇事车辆痕迹勘验笔录》及照片证实经过将事故现场提取物与疑似肇事车的损坏现状进行对比，结论为：（1）、白色保险杠碎片对比其位置、材质、颜色等对比吻合；（2）、一块银色塑料条与该车中网缺失部分对比其位置、材质、颜色等对比吻合；（3）、两块黑色塑料板拼合后于车前保险杠下端，符合其特征；（4）、该车挡风玻璃清洗液罐缺失，并与事故现场提取的贮水罐吻合；（5）、从逃逸嫌疑车辆（贵JP8385号）上左前轮叶子板与防撞护板夹缝处提取的红色塑料和黑色胶条与摩托车右侧挡风板破损处作比对，提取的红色塑料与该车右侧挡风板处红色塑料破损边缘完全吻合。 10、麻江县公安局交通警察大队出具的麻公交认字（2014）第A00012号《道路交通事故认定书》认定被告人宋建波承担此事故的全部责任。 11、《丧葬协议书》及《收条》证实被告人宋建波案发后已支付被害人张某学经济损失五万元。 12、麻江县公安局交通警察大队出具的《常住人口基本信息》证实被告人宋建波生于1991年12月11日。 被告人宋建波对上述查明的事实予以供认。 对于辩护人提出被害人张某学系非法营运具有一定过错的辩护意见。经查，被害人张某学此次交通事故中，经交警部门认定，其无过错责任，故该辩护意见不能成立，本院不予采纳。 对于辩护人提出被告人宋建波具有自首情节，建议对其减轻处罚的辩护意见。经查，被告人宋建波交通肇事逃逸后，虽然得知交警部门找其调查而在家等候，但其交通肇事逃逸后并没有报案，也没有委托他人报案，其行为不具备我国法律规定有关自首情节的规定。该辩护意见不能成立，本院不予采纳。 本院认为，被告人宋建波违反交通运输管理法规，造成一人死亡、一人受伤的重大交通事故，其行为已触犯我国刑律，构成交通肇事罪，应当追究刑事责任。被告人宋建波肇事后为逃避法律追究而驾车逃逸，对其应在三年以上七年以下有期徒刑量刑。公诉机关的指控，事实清楚，证据确实、充分，定性准确，本院予以确认。鉴于被告人宋建波当庭认罪，可酌情对其从轻处罚。据此，依照《中华人民共和国刑法》第一百三十三条之规定，判决如下： 被告人宋建波犯交通肇事罪，判处有期徒刑三年零六个月。 （刑期从判决执行之日起计算。判决执行以前先行羁押的，羁押一日折抵刑期一日。即自2014年12月4日起至2018年6月3日止。） 如不服本判决，可在接到判决书的第二日起十日内，通过本院或者直接向贵州省黔东南苗族侗族自治州中级人民法院提出上诉。书面上诉的，应当提交上诉状正本一份，副本二份。 审判长赵镛 审判员潘朝金 审判员唐树佳 二〇一四年十二月四日 书记员陆双勤 "><WS nameCN="文首" value=" 贵州省麻江县人民法院 刑事判决书 （2014）麻刑初字第86号 "><WSZZDW nameCN="文书制作单位" value="法院"/><FYWSZL nameCN="法院文书种类" value="裁判文书"/><JBFY nameCN="经办法院" value="贵州省麻江县人民法院"><FYCJM nameCN="法院层级码" value="O8F"/><BZFYMC nameCN="标准法院名称" value="麻江县人民法院"/><FYJB nameCN="法院级别" value="基层"/><XZQH_P nameCN="行政区划(省)" value="贵州"/><XZQH_C nameCN="行政区划(市)" value="黔东南苗族侗族自治州"/></JBFY><WSMC nameCN="文书名称" value="刑事判决书"/><AH nameCN="案号" value="（2014）麻刑初字第86号"><ZH nameCN="字号" value="刑初字"/><LAND nameCN="立案年度" value="2014"/><FYJC nameCN="法院简称" value="麻"/><AHSXH nameCN="案号顺序号" value="86"/></AH><AJLB nameCN="案件类别" value="刑事案件"/><WSZL nameCN="文书种类" value="判决书"/><SPCX nameCN="审判程序" value="一审案件"/><AJLX nameCN="案件类型" value="刑事一审案件"/></WS><DSR nameCN="当事人" value="公诉机关贵州省麻江县人民检察院。 被告人宋建波，男，个人信息略。因涉嫌交通肇事罪于2014年7月15日被麻江县公安局取保候审。经本院决定，2014年12月4日被依法逮捕。现羁押于麻江县看守所。 辩护人何东，望江律师事务所律师。"><GSF nameCN="公诉方" value="公诉机关贵州省麻江县人民检察院。"><SSCYR nameCN="诉讼参与人" value="贵州省麻江县人民检察院"/><SSSF nameCN="诉讼身份" value="公诉机关"/><DSRLB nameCN="当事人类别" value="公诉机关"/><BSSSDW nameCN="本审诉讼地位" value="公诉机关"/></GSF><YSF nameCN="应诉方" value="被告人宋建波，男，个人信息略。因涉嫌交通肇事罪于2014年7月15日被麻江县公安局取保候审。经本院决定，2014年12月4日被依法逮捕。现羁押于麻江县看守所。"><SSCYR nameCN="诉讼参与人" value="宋建波"/><SSSF nameCN="诉讼身份" value="被告人"/><DSRLX nameCN="当事人类型" value="自然人"/><XB nameCN="性别" value="男"/><GJ nameCN="国籍" value="中国"/><DSRLB nameCN="当事人类别" value="被告人"/><QZCS nameCN="强制措施"><QZCSZL nameCN="强制措施种类" value="取保候审"/><QZCSZXSJ nameCN="强制措施执行时间" value="2014年7月15日"/><QZCSZXDW nameCN="强制措施执行单位" value="麻江县公安局"/><QZCSYYFZ nameCN="强制措施原因组"><QZCSYY nameCN="强制措施原因" value="交通肇事罪"/></QZCSYYFZ></QZCS><QZCS nameCN="强制措施"><QZCSZL nameCN="强制措施种类" value="逮捕"/><QZCSZXSJ nameCN="强制措施执行时间" value="2014年12月4日"/><QZCSJDDW nameCN="强制措施决定单位" value="贵州省麻江县人民法院"/></QZCS><JYCS nameCN="羁押场所" value="麻江县看守所"/><BDBRQ nameCN="被逮捕日期" value="2014年12月4日"/><JDDBJG nameCN="决定逮捕机关" value="法院"/><HXKYQNFZ nameCN="缓刑考验期内犯罪" value="否"/><JSKYQNFZ nameCN="假释考验期内犯罪" value="否"/><XSZRNL nameCN="刑事责任能力" value="完全刑事责任能力"/><BSSSDW nameCN="本审诉讼地位" value="被告人"/><SFBHR nameCN="是否被害人" value="否"/><ZRRSF nameCN="自然人身份" value="其他"/></YSF><DLR nameCN="代理人" value="辩护人何东，望江律师事务所律师。"><SSCYR nameCN="诉讼参与人" value="何东"/><SSSF nameCN="诉讼身份" value="辩护人"/><DSRLX nameCN="当事人类型" value="自然人"/><DWZWFZ nameCN="单位职务分组"><ZW nameCN="职务" value="律师"/><DWMC nameCN="单位名称" value="望江律师事务所"/><DWXZ nameCN="单位性质" value="事业单位"/></DWZWFZ><GJ nameCN="国籍" value="中国"/><DSRLB nameCN="当事人类别" value="代理人"/><CYRSSDW nameCN="参与人诉讼地位" value="辩护人"/><BHZL nameCN="辩护种类" value="委托辩护"/><BHDX nameCN="辩护对象" value="宋建波"/><DLRBHRZYLX nameCN="代理人辩护人职业类型" value="职业律师"/><BHRHSSDLRLX nameCN="辩护人或诉讼代理人类型" value="律师"/><ZRRSF nameCN="自然人身份" value="职员"/></DLR><BGRQX nameCN="被告人缺席" value="无缺席"/></DSR><SSJL nameCN="诉讼记录" value=" 麻江县人民检察院以麻检公诉刑诉（2014）73号起诉书指控被告人宋建波犯交通肇事罪，于2014年10月11日向本院提起公诉。本院依法组成合议庭，公开开庭审理了本案。麻江县人民检察院指派检察员陈摔出庭支持公诉，被告人宋建波及其辩护人何东到庭参加诉讼。现已审理终结。"><KTSL nameCN="开庭审理" value="是"/><KTSLXX nameCN="开庭审理信息" value="公开审理"/><CTJCYs nameCN="出庭检察员"><JCYFZ nameCN="检察员分组"><JS nameCN="角色" value="检察员"/><JCY nameCN="检察员" value="陈摔"/></JCYFZ></CTJCYs><SSXZ nameCN="诉讼性质" value="公诉"/><QSRQ nameCN="起诉日期" value="2014年10月11日"/><JCYJYYQSL nameCN="检察院建议延期审理" value="否"/><SNFT nameCN="少年法庭" value="否"/><ZKXX nameCN="指控信息"><ZKJL nameCN="指控记录"><ZKZM nameCN="指控罪名" value="交通肇事罪"><ZMDM nameCN="罪名代码" value="51"/><WZZM nameCN="完整罪名" value="交通肇事罪"/></ZKZM><XGR nameCN="相关人" value="宋建波"/></ZKJL></ZKXX><QSZAY nameCN="起诉主案由" value="交通肇事罪"><ZMDM nameCN="罪名代码" value="51"/><WZZM nameCN="完整罪名" value="交通肇事罪"/></QSZAY><YSAJSYCX nameCN="一审案件适用程序" value="普通程序"/><JYSYJYCX nameCN="建议适用简易程序" value="无"/><DRSP nameCN="独任审判" value="否"/><YSAJLY nameCN="一审案件来源" value="新收公诉"/><GSJG nameCN="公诉机关" value="贵州省麻江县人民检察院"/><GSAH nameCN="公诉案号" value="麻检公诉刑诉（2014）73号"/><JYZPT nameCN="简易转普通" value="否"/><SPZZ nameCN="审判组织" value="合议庭"/><CTDSRXX nameCN="出庭当事人信息"><CTRXM nameCN="出庭人姓名" value="宋建波"><SSDW nameCN="诉讼地位" value="被告人"/></CTRXM><CTRXM nameCN="出庭人姓名" value="何东"><SSDW nameCN="诉讼地位" value="辩护人"/></CTRXM></CTDSRXX></SSJL><AJJBQK nameCN="案件基本情况" value=" 麻江县人民检察院指控：2014年4月29日，被告人宋建波驾驶贵JP8385号小型普通客车在210国道由福泉往都匀方向行驶，22时30分，当行驶至210国道2459Km＋350m处时，遇对向来车未减速靠右通行，占线与对向由被害人张某学驾驶的贵HC9332号普通二轮摩托车碰撞，后被告人宋建波驾车逃离现场，造成摩托车驾驶员张某学经抢救无效于次日07：05分死亡及摩托车乘客宋某金受伤的道路交通事故。经麻江县公安局交警大队认定，被告人宋建波承担本次事故的全部责任。另查明，被告人宋建波已支付丧葬费、医疗费等费用共计7．548万元；保险公司也已支付1万元费用。 为支持其公诉，公诉机关向法庭提供的证据有：1、肇事车辆等物证；2、户籍证明、事故认定书等书证；3、证人罗某江等人的证言；4、被害人宋某金的陈述；5、被告人宋建波的供述与辩解；6、司法鉴定检验报告书、事故车辆检验报告；7、现场勘验笔录、现场图及照片等证据。 该院认为，被告人宋建波违反交通管理法规，发生1人死亡、1人受伤的道路交通事故，为逃避法律追究而逃离事故现场，其行为触犯了《中华人民共和国刑法》第一百三十三条的规定，应当以交通肇事罪追究刑事责任。现提起公诉，请依法判处。 被告人宋建波对公诉机关的指控无异议。 辩护人何东提出的辩护意见是：一、被害人张某学系非法营运，具有一定过错；二、被告人宋建波具有自首情节，应对其减轻处罚。 经审理查明，2014年4月29日，被告人宋建波驾驶贵JP8385号小型普通客车在210国道由福泉方向往都匀方向行驶，22时30分许，当行驶至210国道2459Km＋350m处时，遇对向来车未减速靠右通行，占线与对向由张某学驾驶的贵HC9332号普通二轮摩托车发生碰撞，造成张某学经抢救无效于次日07：05分死亡及乘客宋某金受伤的道路交通事故。被告人宋建波交通肇事后，为逃避法律追究而驾车逃逸现场。经麻江县公安局交通警察大队认定，宋建波承担事故的全部责任。 另查明，事发后被告人宋建波支付了死者张某学家属人民币5万元。 上述事实，有下列经庭审举证、质证、认证的证据予以证实： 1、道路交通事故现场勘查笔录、现场图、现场照片、交通事故车辆指认和现场记录及照片证实现场位于国道210线2459KM＋350M处，肇事车辆为贵JP8385小型普通客车；并用照片固定现场遗留物储水罐、红色塑料、黑色胶条等。 2、证人罗某江证言证实：2014年4月29日晚上十点过钟，我和妻子放水浇田，我脚痛就坐在公路旁的护栏石上休息，妻子一人去放水，她走得约一分钟左右，就有一辆从良田方向过来的二轮摩托车从我面前过，一两秒钟，我就听到“嘭”的一声，我朝声音的方向看，看见一辆小车从马场坪方向开过来，当时我知道撞车了，我看那小车没有停车，我用拐杖向小车摇晃，想让车停下来，但是小车加油朝良田街上跑了。我马上朝公路坎下喊：“小松，快拿电筒来，上面出事了。”小松等人打电筒上来看见一辆二轮摩托车倒在靠公路外坎的路面上，有一个人躺在摩托车旁边受伤严重，这时我们又听见公路外坎下面有人在哼，我们下去看，才发现还有一个伤员在路坎下面。这时从马场坪方向过来一辆小车，车上的人下来看见是出事就电话报警了，随后警察和救护车就来了。 3、证人陶某相证言证实：2014年4月29日晚上，我开车和潘杰校长从又诗小学返回麻江县城，晚上十点半左右经过新田坳时，看见有群众在路上围观，我停车下来看见一辆二轮摩托车倒在路上，驾驶员躺在摩托车旁边，伤得很严重，还有一个伤员在左边的路坎下面，听旁群众说好象是面包车撞的，面包车已经朝良田街上跑了，于是我就报警了，我还拿得车上的三角警示牌摆在路上，一直等到警察来了我才离开的。我看见现场有很多碎片，摩托车上卡着一块逃逸小车的保险杠护板，是黑色的。 4、证人施某香证言证实：宋建波是我的儿子，2014年4月29日那天下午4点过钟，我、女儿宋某英乘坐宋建波驾驶的贵JP8385号面包车从甘粑哨去麻江县土桥河我姐夫王某平家吊唁姑妈。晚饭后，宋建波开车送宋某英回马场坪，我在亲戚家守夜。晚上宋建波打电话给我，说来接我回家，等了一晚上宋建波都没有来，打电话给宋建波一直占线联系不上。第二天上午大概10点过钟，我接到侄子宋建华的电话，说宋建波开车在麻江发生车祸，麻江交警队在马场坪找宋建波，我回家看见宋建波在家里躺着，我问宋建波，他说29号晚上在麻江境内驾驶的面包车和一辆二轮摩托车碰了。过了一会儿，马场坪交警、麻江交警和宋建华来到我家把宋建波带走了。 5、证人宋某金证言证实：2014年4月29日晚上十点过钟我在麻江汽车站对面找得羊昌坡桐子园姓张的摩托车回两路口，到新田坳路段时，从马场坪方向有一辆小车超车过来，占着我们的线路把我们的摩托车撞了，我就昏过去了。 6、《驾驶人信息查询结果单》及宋继波和张某学《驾驶证》复印件分别证实二人准驾车型为C1和D；《机动车信息查询结果单》及贵JP8385号五菱车小型普通客车和贵HC9332普通二轮摩托车《行驶证》复印件分别证实车主系宋继波和张某学；《道路交通事故车辆技术检验报告》及照片证实贵JP8385号五菱车小型普通客车和贵HC9332普通二轮摩托车均符合机动车运行安全技术条件要求。 7、贵州省麻江县公安司法鉴定中心出具的（麻）公（司）鉴（尸）字（2014）027号《法医学尸体检验报告》及照片证实医院对张某学抢救记录为：经常规抢救30多分钟，患者未恢复自主心率，双侧瞳孔散大，对光反射消失，颈动脉未扪及波动感，四肢冰冷，行心电图检查回示为直线，与患者家属交代病情，患者家属同意后于2014年4月30日7：05分放弃抢救，宣布死亡，死亡原因脑干功能衰竭；鉴定意见张某学系交通事故致颅脑、胸腹腔脏器复合损伤死亡。 8、《道路交通事故逃逸嫌疑车辆痕迹勘验笔录》及照片证实勘验地点位于福泉市陆坪镇浪波河村长冲组26号李兵家院坝内；勘验对象系白色“贵JP8385号小型普通客车；勘验内容：（1）、前号牌脱落置于该车内，车后悬挂有贵JB8385号小型汽车号牌；（2）、该车前挡风玻璃呈粉碎状破损，前挡风玻璃框左上端处凹陷变形，并附着有毛发；（3）、该车左后视镜壳与底座断落，由导线连接，断口呈新印；（4）、引擎盖左侧面板凹陷变形，凹陷面板上有两条纵向红色漆印；（5）、该车左前大灯破损，破口呈新印，灯壳部分缺损；（6）、该车前保险杠左端破损缺失；（7）、该车中网左端破损缺失，破口呈新印；（8）、前保险杠下护板缺失；（9）、该车左前轮叶子板和防撞护板夹缝处嵌有一块破损的黑色胶条，上印有“一帆风顺”字样，胶条由螺丝连接一块破损的红色塑料，破口呈新印，红色塑料上有“吉祥”、“快车”、“平”字样和鹰形图案；（10）、勘验人员提取并保存了（9）中的黑色胶条和红色塑料。 9、《道路交通事故肇事车辆痕迹勘验笔录》及照片证实经过将事故现场提取物与疑似肇事车的损坏现状进行对比，结论为：（1）、白色保险杠碎片对比其位置、材质、颜色等对比吻合；（2）、一块银色塑料条与该车中网缺失部分对比其位置、材质、颜色等对比吻合；（3）、两块黑色塑料板拼合后于车前保险杠下端，符合其特征；（4）、该车挡风玻璃清洗液罐缺失，并与事故现场提取的贮水罐吻合；（5）、从逃逸嫌疑车辆（贵JP8385号）上左前轮叶子板与防撞护板夹缝处提取的红色塑料和黑色胶条与摩托车右侧挡风板破损处作比对，提取的红色塑料与该车右侧挡风板处红色塑料破损边缘完全吻合。 10、麻江县公安局交通警察大队出具的麻公交认字（2014）第A00012号《道路交通事故认定书》认定被告人宋建波承担此事故的全部责任。 11、《丧葬协议书》及《收条》证实被告人宋建波案发后已支付被害人张某学经济损失五万元。 12、麻江县公安局交通警察大队出具的《常住人口基本信息》证实被告人宋建波生于1991年12月11日。 被告人宋建波对上述查明的事实予以供认。 对于辩护人提出被害人张某学系非法营运具有一定过错的辩护意见。经查，被害人张某学此次交通事故中，经交警部门认定，其无过错责任，故该辩护意见不能成立，本院不予采纳。 对于辩护人提出被告人宋建波具有自首情节，建议对其减轻处罚的辩护意见。经查，被告人宋建波交通肇事逃逸后，虽然得知交警部门找其调查而在家等候，但其交通肇事逃逸后并没有报案，也没有委托他人报案，其行为不具备我国法律规定有关自首情节的规定。该辩护意见不能成立，本院不予采纳。 "><ZZQK nameCN="质证情况" value="质证"/><BHR nameCN="被害人"><BHRXM nameCN="被害人姓名" value="宋某金"/><SFSW nameCN="是否死亡" value="否"/></BHR><ZKDL nameCN="指控段落" value=" 麻江县人民检察院指控：2014年4月29日，被告人宋建波驾驶贵JP8385号小型普通客车在210国道由福泉往都匀方向行驶，22时30分，当行驶至210国道2459Km＋350m处时，遇对向来车未减速靠右通行，占线与对向由被害人张某学驾驶的贵HC9332号普通二轮摩托车碰撞，后被告人宋建波驾车逃离现场，造成摩托车驾驶员张某学经抢救无效于次日07：05分死亡及摩托车乘客宋某金受伤的道路交通事故。经麻江县公安局交警大队认定，被告人宋建波承担本次事故的全部责任。另查明，被告人宋建波已支付丧葬费、医疗费等费用共计7．548万元；保险公司也已支付1万元费用。 为支持其公诉，公诉机关向法庭提供的证据有：1、肇事车辆等物证；2、户籍证明、事故认定书等书证；3、证人罗某江等人的证言；4、被害人宋某金的陈述；5、被告人宋建波的供述与辩解；6、司法鉴定检验报告书、事故车辆检验报告；7、现场勘验笔录、现场图及照片等证据。 该院认为，被告人宋建波违反交通管理法规，发生1人死亡、1人受伤的道路交通事故，为逃避法律追究而逃离事故现场，其行为触犯了《中华人民共和国刑法》第一百三十三条的规定，应当以交通肇事罪追究刑事责任。现提起公诉，请依法判处。 "><ZKSS nameCN="指控事实" value="麻江县人民检察院指控：2014年4月29日，被告人宋建波驾驶贵JP8385号小型普通客车在210国道由福泉往都匀方向行驶，22时30分，当行驶至210国道2459Km＋350m处时，遇对向来车未减速靠右通行，占线与对向由被害人张某学驾驶的贵HC9332号普通二轮摩托车碰撞，后被告人宋建波驾车逃离现场，造成摩托车驾驶员张某学经抢救无效于次日07：05分死亡及摩托车乘客宋某金受伤的道路交通事故。经麻江县公安局交警大队认定，被告人宋建波承担本次事故的全部责任。另查明，被告人宋建波已支付丧葬费、医疗费等费用共计7．548万元；保险公司也已支付1万元费用。 "/><ZKZJ nameCN="指控证据" value="为支持其公诉，公诉机关向法庭提供的证据有：1、肇事车辆等物证；2、户籍证明、事故认定书等书证；3、证人罗某江等人的证言；4、被害人宋某金的陈述；5、被告人宋建波的供述与辩解；6、司法鉴定检验报告书、事故车辆检验报告；7、现场勘验笔录、现场图及照片等证据。 "><ZJXX nameCN="证据信息"><ZJFZ nameCN="证据分组"><ZJJL nameCN="证据记录" value="1、肇事车辆等物证；"><ZJMX nameCN="证据明细"><MC nameCN="名称" value="肇事车辆等物证"/><ZL nameCN="种类" value="物证"/></ZJMX></ZJJL><ZJJL nameCN="证据记录" value="2、户籍证明、事故认定书等书证；"><ZJMX nameCN="证据明细"><MC nameCN="名称" value="户籍证明、事故认定书等书证"/><ZL nameCN="种类" value="鉴定结论"/></ZJMX></ZJJL><ZJJL nameCN="证据记录" value="3、证人罗某江等人的证言；"><ZJMX nameCN="证据明细"><MC nameCN="名称" value="罗某江等人的证言"/><ZL nameCN="种类" value="证人证言"/><TJR nameCN="提交人" value="罗某江"/></ZJMX></ZJJL><ZJJL nameCN="证据记录" value="4、被害人宋某金的陈述；"><ZJMX nameCN="证据明细"><MC nameCN="名称" value="宋某金的陈述"/><ZL nameCN="种类" value="被害人陈述"/><TJR nameCN="提交人" value="宋某金"/></ZJMX></ZJJL><ZJJL nameCN="证据记录" value="5、被告人宋建波的供述与辩解；"><ZJMX nameCN="证据明细"><MC nameCN="名称" value="宋建波的供述"/><ZL nameCN="种类" value="被告人供述和辩解"/><TJR nameCN="提交人" value="宋建波"/></ZJMX></ZJJL><ZJJL nameCN="证据记录" value="6、司法鉴定检验报告书、事故车辆检验报告；"><ZJMX nameCN="证据明细"><MC nameCN="名称" value="司法鉴定检验报告书、事故车辆检验报告"/><ZL nameCN="种类" value="鉴定结论"/></ZJMX></ZJJL><ZJJL nameCN="证据记录" value="7、现场勘验笔录、现场图及照片等证据。"><ZJMX nameCN="证据明细"><MC nameCN="名称" value="现场勘验笔录、现场图及照片等证据"/><ZL nameCN="种类" value="勘验、检查笔录"/></ZJMX></ZJJL></ZJFZ></ZJXX><ZRXX nameCN="证人信息"><ZR nameCN="证人" value="罗某江"/></ZRXX></ZKZJ><ZKYJ nameCN="指控意见" value="该院认为，被告人宋建波违反交通管理法规，发生1人死亡、1人受伤的道路交通事故，为逃避法律追究而逃离事故现场，其行为触犯了《中华人民共和国刑法》第一百三十三条的规定，应当以交通肇事罪追究刑事责任。现提起公诉，请依法判处。"/></ZKDL><BHDL nameCN="辩护段落" value="被告人宋建波对公诉机关的指控无异议。 辩护人何东提出的辩护意见是：一、被害人张某学系非法营运，具有一定过错；二、被告人宋建波具有自首情节，应对其减轻处罚。 "><BGRBC nameCN="被告人辩称" value="被告人宋建波对公诉机关的指控无异议。 "/><BHRBH nameCN="辩护人辩护" value="辩护人何东提出的辩护意见是：一、被害人张某学系非法营运，具有一定过错；二、被告人宋建波具有自首情节，应对其减轻处罚。"><BHYJ nameCN="辩护意见"><BGRXM nameCN="被告人姓名" value="宋建波"/><BHYJZL nameCN="辩护意见种类" value="罪轻辩护"/></BHYJ></BHRBH></BHDL><BSSLD nameCN="本审审理段" value="经审理查明，2014年4月29日，被告人宋建波驾驶贵JP8385号小型普通客车在210国道由福泉方向往都匀方向行驶，22时30分许，当行驶至210国道2459Km＋350m处时，遇对向来车未减速靠右通行，占线与对向由张某学驾驶的贵HC9332号普通二轮摩托车发生碰撞，造成张某学经抢救无效于次日07：05分死亡及乘客宋某金受伤的道路交通事故。被告人宋建波交通肇事后，为逃避法律追究而驾车逃逸现场。经麻江县公安局交通警察大队认定，宋建波承担事故的全部责任。 另查明，事发后被告人宋建波支付了死者张某学家属人民币5万元。 上述事实，有下列经庭审举证、质证、认证的证据予以证实： 1、道路交通事故现场勘查笔录、现场图、现场照片、交通事故车辆指认和现场记录及照片证实现场位于国道210线2459KM＋350M处，肇事车辆为贵JP8385小型普通客车；并用照片固定现场遗留物储水罐、红色塑料、黑色胶条等。 2、证人罗某江证言证实：2014年4月29日晚上十点过钟，我和妻子放水浇田，我脚痛就坐在公路旁的护栏石上休息，妻子一人去放水，她走得约一分钟左右，就有一辆从良田方向过来的二轮摩托车从我面前过，一两秒钟，我就听到“嘭”的一声，我朝声音的方向看，看见一辆小车从马场坪方向开过来，当时我知道撞车了，我看那小车没有停车，我用拐杖向小车摇晃，想让车停下来，但是小车加油朝良田街上跑了。我马上朝公路坎下喊：“小松，快拿电筒来，上面出事了。”小松等人打电筒上来看见一辆二轮摩托车倒在靠公路外坎的路面上，有一个人躺在摩托车旁边受伤严重，这时我们又听见公路外坎下面有人在哼，我们下去看，才发现还有一个伤员在路坎下面。这时从马场坪方向过来一辆小车，车上的人下来看见是出事就电话报警了，随后警察和救护车就来了。 3、证人陶某相证言证实：2014年4月29日晚上，我开车和潘杰校长从又诗小学返回麻江县城，晚上十点半左右经过新田坳时，看见有群众在路上围观，我停车下来看见一辆二轮摩托车倒在路上，驾驶员躺在摩托车旁边，伤得很严重，还有一个伤员在左边的路坎下面，听旁群众说好象是面包车撞的，面包车已经朝良田街上跑了，于是我就报警了，我还拿得车上的三角警示牌摆在路上，一直等到警察来了我才离开的。我看见现场有很多碎片，摩托车上卡着一块逃逸小车的保险杠护板，是黑色的。 4、证人施某香证言证实：宋建波是我的儿子，2014年4月29日那天下午4点过钟，我、女儿宋某英乘坐宋建波驾驶的贵JP8385号面包车从甘粑哨去麻江县土桥河我姐夫王某平家吊唁姑妈。晚饭后，宋建波开车送宋某英回马场坪，我在亲戚家守夜。晚上宋建波打电话给我，说来接我回家，等了一晚上宋建波都没有来，打电话给宋建波一直占线联系不上。第二天上午大概10点过钟，我接到侄子宋建华的电话，说宋建波开车在麻江发生车祸，麻江交警队在马场坪找宋建波，我回家看见宋建波在家里躺着，我问宋建波，他说29号晚上在麻江境内驾驶的面包车和一辆二轮摩托车碰了。过了一会儿，马场坪交警、麻江交警和宋建华来到我家把宋建波带走了。 5、证人宋某金证言证实：2014年4月29日晚上十点过钟我在麻江汽车站对面找得羊昌坡桐子园姓张的摩托车回两路口，到新田坳路段时，从马场坪方向有一辆小车超车过来，占着我们的线路把我们的摩托车撞了，我就昏过去了。 6、《驾驶人信息查询结果单》及宋继波和张某学《驾驶证》复印件分别证实二人准驾车型为C1和D；《机动车信息查询结果单》及贵JP8385号五菱车小型普通客车和贵HC9332普通二轮摩托车《行驶证》复印件分别证实车主系宋继波和张某学；《道路交通事故车辆技术检验报告》及照片证实贵JP8385号五菱车小型普通客车和贵HC9332普通二轮摩托车均符合机动车运行安全技术条件要求。 7、贵州省麻江县公安司法鉴定中心出具的（麻）公（司）鉴（尸）字（2014）027号《法医学尸体检验报告》及照片证实医院对张某学抢救记录为：经常规抢救30多分钟，患者未恢复自主心率，双侧瞳孔散大，对光反射消失，颈动脉未扪及波动感，四肢冰冷，行心电图检查回示为直线，与患者家属交代病情，患者家属同意后于2014年4月30日7：05分放弃抢救，宣布死亡，死亡原因脑干功能衰竭；鉴定意见张某学系交通事故致颅脑、胸腹腔脏器复合损伤死亡。 8、《道路交通事故逃逸嫌疑车辆痕迹勘验笔录》及照片证实勘验地点位于福泉市陆坪镇浪波河村长冲组26号李兵家院坝内；勘验对象系白色“贵JP8385号小型普通客车；勘验内容：（1）、前号牌脱落置于该车内，车后悬挂有贵JB8385号小型汽车号牌；（2）、该车前挡风玻璃呈粉碎状破损，前挡风玻璃框左上端处凹陷变形，并附着有毛发；（3）、该车左后视镜壳与底座断落，由导线连接，断口呈新印；（4）、引擎盖左侧面板凹陷变形，凹陷面板上有两条纵向红色漆印；（5）、该车左前大灯破损，破口呈新印，灯壳部分缺损；（6）、该车前保险杠左端破损缺失；（7）、该车中网左端破损缺失，破口呈新印；（8）、前保险杠下护板缺失；（9）、该车左前轮叶子板和防撞护板夹缝处嵌有一块破损的黑色胶条，上印有“一帆风顺”字样，胶条由螺丝连接一块破损的红色塑料，破口呈新印，红色塑料上有“吉祥”、“快车”、“平”字样和鹰形图案；（10）、勘验人员提取并保存了（9）中的黑色胶条和红色塑料。 9、《道路交通事故肇事车辆痕迹勘验笔录》及照片证实经过将事故现场提取物与疑似肇事车的损坏现状进行对比，结论为：（1）、白色保险杠碎片对比其位置、材质、颜色等对比吻合；（2）、一块银色塑料条与该车中网缺失部分对比其位置、材质、颜色等对比吻合；（3）、两块黑色塑料板拼合后于车前保险杠下端，符合其特征；（4）、该车挡风玻璃清洗液罐缺失，并与事故现场提取的贮水罐吻合；（5）、从逃逸嫌疑车辆（贵JP8385号）上左前轮叶子板与防撞护板夹缝处提取的红色塑料和黑色胶条与摩托车右侧挡风板破损处作比对，提取的红色塑料与该车右侧挡风板处红色塑料破损边缘完全吻合。 10、麻江县公安局交通警察大队出具的麻公交认字（2014）第A00012号《道路交通事故认定书》认定被告人宋建波承担此事故的全部责任。 11、《丧葬协议书》及《收条》证实被告人宋建波案发后已支付被害人张某学经济损失五万元。 12、麻江县公安局交通警察大队出具的《常住人口基本信息》证实被告人宋建波生于1991年12月11日。 被告人宋建波对上述查明的事实予以供认。 对于辩护人提出被害人张某学系非法营运具有一定过错的辩护意见。经查，被害人张某学此次交通事故中，经交警部门认定，其无过错责任，故该辩护意见不能成立，本院不予采纳。 对于辩护人提出被告人宋建波具有自首情节，建议对其减轻处罚的辩护意见。经查，被告人宋建波交通肇事逃逸后，虽然得知交警部门找其调查而在家等候，但其交通肇事逃逸后并没有报案，也没有委托他人报案，其行为不具备我国法律规定有关自首情节的规定。该辩护意见不能成立，本院不予采纳。 "><ZJXX nameCN="证据信息"><ZJFZ nameCN="证据分组"><RDSS nameCN="认定事实" value="经审理查明，2014年4月29日，被告人宋建波驾驶贵JP8385号小型普通客车在210国道由福泉方向往都匀方向行驶，22时30分许，当行驶至210国道2459Km＋350m处时，遇对向来车未减速靠右通行，占线与对向由张某学驾驶的贵HC9332号普通二轮摩托车发生碰撞，造成张某学经抢救无效于次日07：05分死亡及乘客宋某金受伤的道路交通事故。被告人宋建波交通肇事后，为逃避法律追究而驾车逃逸现场。经麻江县公安局交通警察大队认定，宋建波承担事故的全部责任。 另查明，事发后被告人宋建波支付了死者张某学家属人民币5万元。 "/><ZJJL nameCN="证据记录" value="1、道路交通事故现场勘查笔录、现场图、现场照片、交通事故车辆指认和现场记录及照片证实现场位于国道210线2459KM＋350M处，肇事车辆为贵JP8385小型普通客车；并用照片固定现场遗留物储水罐、红色塑料、黑色胶条等。"><ZJMX nameCN="证据明细"><MC nameCN="名称" value="道路交通事故现场勘查笔录、现场图、现场照片、交通事故车辆指认和现场记录及照片"/><ZL nameCN="种类" value="勘验、检查笔录"/></ZJMX></ZJJL><ZJJL nameCN="证据记录" value="2、证人罗某江证言证实：2014年4月29日晚上十点过钟，我和妻子放水浇田，我脚痛就坐在公路旁的护栏石上休息，妻子一人去放水，她走得约一分钟左右，就有一辆从良田方向过来的二轮摩托车从我面前过，一两秒钟，我就听到“嘭”的一声，我朝声音的方向看，看见一辆小车从马场坪方向开过来，当时我知道撞车了，我看那小车没有停车，我用拐杖向小车摇晃，想让车停下来，但是小车加油朝良田街上跑了。我马上朝公路坎下喊：“小松，快拿电筒来，上面出事了。”小松等人打电筒上来看见一辆二轮摩托车倒在靠公路外坎的路面上，有一个人躺在摩托车旁边受伤严重，这时我们又听见公路外坎下面有人在哼，我们下去看，才发现还有一个伤员在路坎下面。这时从马场坪方向过来一辆小车，车上的人下来看见是出事就电话报警了，随后警察和救护车就来了。"><ZJMX nameCN="证据明细"><MC nameCN="名称" value="罗某江证言"/><ZL nameCN="种类" value="证人证言"/><TJR nameCN="提交人" value="罗某江"/></ZJMX></ZJJL><ZJJL nameCN="证据记录" value="3、证人陶某相证言证实：2014年4月29日晚上，我开车和潘杰校长从又诗小学返回麻江县城，晚上十点半左右经过新田坳时，看见有群众在路上围观，我停车下来看见一辆二轮摩托车倒在路上，驾驶员躺在摩托车旁边，伤得很严重，还有一个伤员在左边的路坎下面，听旁群众说好象是面包车撞的，面包车已经朝良田街上跑了，于是我就报警了，我还拿得车上的三角警示牌摆在路上，一直等到警察来了我才离开的。我看见现场有很多碎片，摩托车上卡着一块逃逸小车的保险杠护板，是黑色的。"><ZJMX nameCN="证据明细"><MC nameCN="名称" value="陶某相证言"/><ZL nameCN="种类" value="证人证言"/><TJR nameCN="提交人" value="陶某相"/></ZJMX></ZJJL><ZJJL nameCN="证据记录" value="4、证人施某香证言证实：宋建波是我的儿子，2014年4月29日那天下午4点过钟，我、女儿宋某英乘坐宋建波驾驶的贵JP8385号面包车从甘粑哨去麻江县土桥河我姐夫王某平家吊唁姑妈。晚饭后，宋建波开车送宋某英回马场坪，我在亲戚家守夜。晚上宋建波打电话给我，说来接我回家，等了一晚上宋建波都没有来，打电话给宋建波一直占线联系不上。第二天上午大概10点过钟，我接到侄子宋建华的电话，说宋建波开车在麻江发生车祸，麻江交警队在马场坪找宋建波，我回家看见宋建波在家里躺着，我问宋建波，他说29号晚上在麻江境内驾驶的面包车和一辆二轮摩托车碰了。过了一会儿，马场坪交警、麻江交警和宋建华来到我家把宋建波带走了。"><ZJMX nameCN="证据明细"><MC nameCN="名称" value="施某香证言"/><ZL nameCN="种类" value="证人证言"/><TJR nameCN="提交人" value="施某香"/></ZJMX></ZJJL><ZJJL nameCN="证据记录" value="5、证人宋某金证言证实：2014年4月29日晚上十点过钟我在麻江汽车站对面找得羊昌坡桐子园姓张的摩托车回两路口，到新田坳路段时，从马场坪方向有一辆小车超车过来，占着我们的线路把我们的摩托车撞了，我就昏过去了。"><ZJMX nameCN="证据明细"><MC nameCN="名称" value="宋某金证言"/><ZL nameCN="种类" value="证人证言"/><TJR nameCN="提交人" value="宋某金"/></ZJMX></ZJJL><ZJJL nameCN="证据记录" value="6、《驾驶人信息查询结果单》及宋继波和张某学《驾驶证》复印件分别证实二人准驾车型为C1和D；《机动车信息查询结果单》及贵JP8385号五菱车小型普通客车和贵HC9332普通二轮摩托车《行驶证》复印件分别证实车主系宋继波和张某学；《道路交通事故车辆技术检验报告》及照片证实贵JP8385号五菱车小型普通客车和贵HC9332普通二轮摩托车均符合机动车运行安全技术条件要求。"><ZJMX nameCN="证据明细"><MC nameCN="名称" value="《驾驶人信息查询结果单》及宋继波和张某学《驾驶证》复印件"/><ZL nameCN="种类" value="书证"/></ZJMX></ZJJL><ZJJL nameCN="证据记录" value="7、贵州省麻江县公安司法鉴定中心出具的（麻）公（司）鉴（尸）字（2014）027号《法医学尸体检验报告》及照片证实医院对张某学抢救记录为：经常规抢救30多分钟，患者未恢复自主心率，双侧瞳孔散大，对光反射消失，颈动脉未扪及波动感，四肢冰冷，行心电图检查回示为直线，与患者家属交代病情，患者家属同意后于2014年4月30日7：05分放弃抢救，宣布死亡，死亡原因脑干功能衰竭；鉴定意见张某学系交通事故致颅脑、胸腹腔脏器复合损伤死亡。"><ZJMX nameCN="证据明细"><MC nameCN="名称" value="贵州省麻江县公安司法鉴定中心（麻）公（司）鉴（尸）字（2014）027号《法医学尸体检验报告》及照片"/><ZL nameCN="种类" value="鉴定结论"/><TJR nameCN="提交人" value="贵州省麻江县公安司法鉴定中心"/></ZJMX></ZJJL><ZJJL nameCN="证据记录" value="8、《道路交通事故逃逸嫌疑车辆痕迹勘验笔录》及照片证实勘验地点位于福泉市陆坪镇浪波河村长冲组26号李兵家院坝内；勘验对象系白色“贵JP8385号小型普通客车；勘验内容："><ZJMX nameCN="证据明细"><MC nameCN="名称" value="《道路交通事故逃逸嫌疑车辆痕迹勘验笔录》及照片"/><ZL nameCN="种类" value="勘验、检查笔录"/></ZJMX></ZJJL><ZJJL nameCN="证据记录" value="（1）、前号牌脱落置于该车内，车后悬挂有贵JB8385号小型汽车号牌；"><ZJMX nameCN="证据明细"><MC nameCN="名称" value="前号牌脱落置于该车内"/><ZL nameCN="种类" value="其他"/></ZJMX></ZJJL><ZJJL nameCN="证据记录" value="（2）、该车前挡风玻璃呈粉碎状破损，前挡风玻璃框左上端处凹陷变形，并附着有毛发；"><ZJMX nameCN="证据明细"><MC nameCN="名称" value="该车前挡风玻璃呈粉碎状破损"/><ZL nameCN="种类" value="其他"/></ZJMX></ZJJL><ZJJL nameCN="证据记录" value="（3）、该车左后视镜壳与底座断落，由导线连接，断口呈新印；"><ZJMX nameCN="证据明细"><MC nameCN="名称" value="该车左后视镜壳与底座断落"/><ZL nameCN="种类" value="其他"/></ZJMX></ZJJL><ZJJL nameCN="证据记录" value="（4）、引擎盖左侧面板凹陷变形，凹陷面板上有两条纵向红色漆印；"><ZJMX nameCN="证据明细"><MC nameCN="名称" value="引擎盖左侧面板凹陷变形"/><ZL nameCN="种类" value="其他"/></ZJMX></ZJJL><ZJJL nameCN="证据记录" value="（5）、该车左前大灯破损，破口呈新印，灯壳部分缺损；"><ZJMX nameCN="证据明细"><MC nameCN="名称" value="该车左前大灯破损"/><ZL nameCN="种类" value="其他"/></ZJMX></ZJJL><ZJJL nameCN="证据记录" value="（6）、该车前保险杠左端破损缺失；"><ZJMX nameCN="证据明细"><MC nameCN="名称" value="该车前保险杠左端破损缺失"/><ZL nameCN="种类" value="其他"/></ZJMX></ZJJL><ZJJL nameCN="证据记录" value="（7）、该车中网左端破损缺失，破口呈新印；"><ZJMX nameCN="证据明细"><MC nameCN="名称" value="该车中网左端破损缺失"/><ZL nameCN="种类" value="其他"/></ZJMX></ZJJL><ZJJL nameCN="证据记录" value="（8）、前保险杠下护板缺失；"><ZJMX nameCN="证据明细"><MC nameCN="名称" value="前保险杠下护板缺失"/><ZL nameCN="种类" value="其他"/></ZJMX></ZJJL><ZJJL nameCN="证据记录" value="（9）、该车左前轮叶子板和防撞护板夹缝处嵌有一块破损的黑色胶条，上印有“一帆风顺”字样，胶条由螺丝连接一块破损的红色塑料，破口呈新印，红色塑料上有“吉祥”、“快车”、“平”字样和鹰形图案；"><ZJMX nameCN="证据明细"><MC nameCN="名称" value="该车左前轮叶子板和防撞护板夹缝处嵌有一块破损的黑色胶条"/><ZL nameCN="种类" value="其他"/></ZJMX></ZJJL><ZJJL nameCN="证据记录" value="（10）、勘验人员提取并保存了"><ZJMX nameCN="证据明细"><MC nameCN="名称" value="勘验人员提取并保存了"/><ZL nameCN="种类" value="其他"/></ZJMX></ZJJL><ZJJL nameCN="证据记录" value="（9）中的黑色胶条和红色塑料。"><ZJMX nameCN="证据明细"><MC nameCN="名称" value="中的黑色胶条和红色塑料"/><ZL nameCN="种类" value="其他"/></ZJMX></ZJJL><ZJJL nameCN="证据记录" value="9、《道路交通事故肇事车辆痕迹勘验笔录》及照片证实经过将事故现场提取物与疑似肇事车的损坏现状进行对比，结论为："><ZJMX nameCN="证据明细"><MC nameCN="名称" value="《道路交通事故肇事车辆痕迹勘验笔录》及照片"/><ZL nameCN="种类" value="勘验、检查笔录"/></ZJMX></ZJJL><ZJJL nameCN="证据记录" value="（1）、白色保险杠碎片对比其位置、材质、颜色等对比吻合；"><ZJMX nameCN="证据明细"><MC nameCN="名称" value="白色保险杠碎片对比其位置、材质、颜色等对比吻合"/><ZL nameCN="种类" value="其他"/></ZJMX></ZJJL><ZJJL nameCN="证据记录" value="（2）、一块银色塑料条与该车中网缺失部分对比其位置、材质、颜色等对比吻合；"><ZJMX nameCN="证据明细"><MC nameCN="名称" value="一块银色塑料条与该车中网缺失部分对比其位置、材质、颜色等对比吻合"/><ZL nameCN="种类" value="其他"/></ZJMX></ZJJL><ZJJL nameCN="证据记录" value="（3）、两块黑色塑料板拼合后于车前保险杠下端，符合其特征；"><ZJMX nameCN="证据明细"><MC nameCN="名称" value="两块黑色塑料板拼合后于车前保险杠下端"/><ZL nameCN="种类" value="其他"/></ZJMX></ZJJL><ZJJL nameCN="证据记录" value="（4）、该车挡风玻璃清洗液罐缺失，并与事故现场提取的贮水罐吻合；"><ZJMX nameCN="证据明细"><MC nameCN="名称" value="该车挡风玻璃清洗液罐缺失"/><ZL nameCN="种类" value="其他"/></ZJMX></ZJJL><ZJJL nameCN="证据记录" value="（5）、从逃逸嫌疑车辆（贵JP8385号）上左前轮叶子板与防撞护板夹缝处提取的红色塑料和黑色胶条与摩托车右侧挡风板破损处作比对，提取的红色塑料与该车右侧挡风板处红色塑料破损边缘完全吻合。"><ZJMX nameCN="证据明细"><MC nameCN="名称" value="从逃逸嫌疑车辆（贵JP8385号）上左前轮叶子板与防撞护板夹缝处提取的红色塑料和黑色胶条与摩托车右侧挡风板破损处作比对"/><ZL nameCN="种类" value="物证"/></ZJMX></ZJJL><ZJJL nameCN="证据记录" value="10、麻江县公安局交通警察大队出具的麻公交认字（2014）第A00012号《道路交通事故认定书》认定被告人宋建波承担此事故的全部责任。"><ZJMX nameCN="证据明细"><MC nameCN="名称" value="麻公交认字（2014）第A00012号《道路交通事故认定书》认定被告人宋建波承担此事故的全部责任"/><ZL nameCN="种类" value="鉴定结论"/><TJR nameCN="提交人" value="麻江县公安局交通警察大队"/></ZJMX></ZJJL><ZJJL nameCN="证据记录" value="11、《丧葬协议书》及《收条》证实被告人宋建波案发后已支付被害人张某学经济损失五万元。"><ZJMX nameCN="证据明细"><MC nameCN="名称" value="《丧葬协议书》及《收条》"/><ZL nameCN="种类" value="书证"/></ZJMX></ZJJL><ZJJL nameCN="证据记录" value="12、麻江县公安局交通警察大队出具的《常住人口基本信息》证实被告人宋建波生于1991年12月11日。"><ZJMX nameCN="证据明细"><MC nameCN="名称" value="《常住人口基本信息》"/><ZL nameCN="种类" value="书证"/><TJR nameCN="提交人" value="麻江县公安局交通警察大队"/></ZJMX></ZJJL><ZJJL nameCN="证据记录" value="被告人宋建波对上述查明的事实予以供认。 "><ZJMX nameCN="证据明细"><MC nameCN="名称" value="宋建波对上述查明的事实予以供认"/><ZL nameCN="种类" value="被告人供述和辩解"/><TJR nameCN="提交人" value="宋建波"/></ZJMX></ZJJL></ZJFZ></ZJXX><ZRXX nameCN="证人信息"><ZR nameCN="证人" value="罗某江"/><ZR nameCN="证人" value="陶某相"/><ZR nameCN="证人" value="施某香"/><ZR nameCN="证人" value="宋某金"/></ZRXX></BSSLD></AJJBQK><CPFXGC nameCN="裁判分析过程" value="本院认为，被告人宋建波违反交通运输管理法规，造成一人死亡、一人受伤的重大交通事故，其行为已触犯我国刑律，构成交通肇事罪，应当追究刑事责任。被告人宋建波肇事后为逃避法律追究而驾车逃逸，对其应在三年以上七年以下有期徒刑量刑。公诉机关的指控，事实清楚，证据确实、充分，定性准确，本院予以确认。鉴于被告人宋建波当庭认罪，可酌情对其从轻处罚。据此，依照《中华人民共和国刑法》第一百三十三条之规定，判决如下："><LXQJ nameCN="量刑情节"><ZDLXQJ nameCN="酌定量刑情节"><XGR nameCN="相关人" value="宋建波"/><QJ nameCN="情节" value="认罪态度好"/><LXQJLB nameCN="量刑情节类别" value="酌定从轻情节"/></ZDLXQJ></LXQJ><BGRTYRZCX nameCN="被告人同意认罪程序" value="是"/><FLFTYY nameCN="法律法条引用"><FLFTFZ nameCN="法律法条分组"><MC nameCN="名称" value="《中华人民共和国刑法》"/><T nameCN="条" value="第一百三十三条"/></FLFTFZ></FLFTYY><CUS_FLFT_FZ_RY nameCN="法律法条分组冗余"><CUS_FLFT_RY nameCN="法律法条" value="《中华人民共和国刑法》第一百三十三条"/></CUS_FLFT_FZ_RY></CPFXGC><PJJG nameCN="判决结果" value=" 被告人宋建波犯交通肇事罪，判处有期徒刑三年零六个月。 （刑期从判决执行之日起计算。判决执行以前先行羁押的，羁押一日折抵刑期一日。即自2014年12月4日起至2018年6月3日止。） 如不服本判决，可在接到判决书的第二日起十日内，通过本院或者直接向贵州省黔东南苗族侗族自治州中级人民法院提出上诉。书面上诉的，应当提交上诉状正本一份，副本二份。"><GXQYY nameCN="提出管辖权异议" value="否"/><YSJAFS nameCN="一审结案方式" value="判决"/><YSXSBFCPJG nameCN="一审刑事部分裁判结果" value="判决"/><XSPJJGFZ nameCN="刑事判决结果分组"><SSCYR nameCN="诉讼参与人" value="宋建波"/><BSPJJG nameCN="本审判决结果"><DZPF nameCN="单罪判罚" value="犯交通肇事罪，判处有期徒刑三年零六个月。"><ZM nameCN="罪名" value="交通肇事罪"><ZMDM nameCN="罪名代码" value="51"/><WZZM nameCN="完整罪名" value="交通肇事罪"/></ZM><ZX nameCN="主刑"><ZXLB nameCN="主刑类别" value="有期徒刑"/><ZXXQ nameCN="主刑刑期" value="三年零六个月"/></ZX><PJJGLX nameCN="判决结果类型" value="给予刑事处罚"/></DZPF><ZXPF nameCN="执行判罚" value="犯交通肇事罪，判处有期徒刑三年零六个月。"><ZX nameCN="主刑"><ZXLB nameCN="主刑类别" value="有期徒刑"/><ZXXQ nameCN="主刑刑期" value="三年零六个月"/></ZX><PJJGLX nameCN="判决结果类型" value="给予刑事处罚"/></ZXPF><PJZZM nameCN="判决主罪名" value="交通肇事罪"><ZMDM nameCN="罪名代码" value="51"/><WZZM nameCN="完整罪名" value="交通肇事罪"/></PJZZM></BSPJJG><XQQZRQ nameCN="刑期起止日期"><XQQSRQ nameCN="刑期起始日期" value="2014年12月4日"/><XQJZRQ nameCN="刑期截止日期" value="2018年6月3日"/></XQQZRQ><XQZDBF nameCN="刑期折抵办法" value="羁押一日折抵刑期一日"/><MXHWZSF nameCN="免刑或无罪释放" value="否"/><SZBF nameCN="数罪并罚" value="否"/><HBLX nameCN="合并量刑" value="否"/></XSPJJGFZ><KSSZ nameCN="可上诉至" value="贵州省黔东南苗族侗族自治州中级人民法院"/><SSTJCL nameCN="上诉提交材料" value="上诉状正本一份，副本二份"/><SSQX nameCN="上诉期限" value="十日"/></PJJG><WW nameCN="文尾" value=" 审判长赵镛 审判员潘朝金 审判员唐树佳 二〇一四年十二月四日 书记员陆双勤 "><CPSJ nameCN="裁判时间" value="2014年12月4日"><JAND nameCN="结案年度" value="2014"/><CUS_JANYR nameCN="结案年月日" value="2014年12月4日"/><CUS_JANY nameCN="结案年月" value="2014-12"/><CUS_JAYF nameCN="结案月份" value="12"/></CPSJ><SPZZCY nameCN="审判组织成员"><SPRYXM nameCN="审判人员姓名" value="赵镛"/><SPRYJS nameCN="审判人员角色" value="审判长"/></SPZZCY><SPZZCY nameCN="审判组织成员"><SPRYXM nameCN="审判人员姓名" value="潘朝金"/><SPRYJS nameCN="审判人员角色" value="审判员"/></SPZZCY><SPZZCY nameCN="审判组织成员"><SPRYXM nameCN="审判人员姓名" value="唐树佳"/><SPRYJS nameCN="审判人员角色" value="审判员"/></SPZZCY><SPZZCY nameCN="审判组织成员"><SPRYXM nameCN="审判人员姓名" value="陆双勤"/><SPRYJS nameCN="审判人员角色" value="书记员"/></SPZZCY></WW><WSSFMH nameCN="文书是否模糊" value="否"/><CUS_SJ nameCN="时间"><CUS_YW nameCN="原文" value="麻江县人民检察院以麻检公诉刑诉（2014）73号起诉书指控被告人宋建波犯交通肇事罪，于2014年10月11日向本院提起公诉"/><CUS_SJYW nameCN="时间原文" value="麻江县人民检察院以麻检公诉刑诉（2014）73号起诉书指控被告人宋建波犯交通肇事罪，于2014年10月11日向本院提起公诉"/><CUS_JTSJ nameCN="具体时间" value="2014年10月11日"/></CUS_SJ><CUS_SJ nameCN="时间"><CUS_YW nameCN="原文" value="麻江县人民检察院指控：2014年4月29日，被告人宋建波驾驶贵JP8385号小型普通客车在210国道由福泉往都匀方向行驶，22时30分，当行驶至210国道2459Km＋350m处时，遇对向来车未减速靠右通行，占线与对向由被害人张某学驾驶的贵HC9332号普通二轮摩托车碰撞，后被告人宋建波驾车逃离现场，造成摩托车驾驶员张某学经抢救无效于次日07：05分死亡及摩托车乘客宋某金受伤的道路交通事故"/><CUS_SJYW nameCN="时间原文" value="麻江县人民检察院指控：2014年4月29日，被告人宋建波驾驶贵JP8385号小型普通客车在210国道由福泉往都匀方向行驶，22时30分，当行驶至210国道2459Km＋350m处时，遇对向来车未减速靠右通行，占线与对向由被害人张某学驾驶的贵HC9332号普通二轮摩托车碰撞，后被告人宋建波驾车逃离现场，造成摩托车驾驶员张某学经抢救无效于2014年4月30日07：05分死亡及摩托车乘客宋某金受伤的道路交通事故"/><CUS_JTSJ nameCN="具体时间" value="2014年4月29日"/></CUS_SJ><CUS_SJ nameCN="时间"><CUS_YW nameCN="原文" value="经审理查明，2014年4月29日，被告人宋建波驾驶贵JP8385号小型普通客车在210国道由福泉方向往都匀方向行驶，22时30分许，当行驶至210国道2459Km＋350m处时，遇对向来车未减速靠右通行，占线与对向由张某学驾驶的贵HC9332号普通二轮摩托车发生碰撞，造成张某学经抢救无效于次日07：05分死亡及乘客宋某金受伤的道路交通事故"/><CUS_SJYW nameCN="时间原文" value="经审理查明，2014年4月29日，被告人宋建波驾驶贵JP8385号小型普通客车在210国道由福泉方向往都匀方向行驶，22时30分许，当行驶至210国道2459Km＋350m处时，遇对向来车未减速靠右通行，占线与对向由张某学驾驶的贵HC9332号普通二轮摩托车发生碰撞，造成张某学经抢救无效于2014年4月30日07：05分死亡及乘客宋某金受伤的道路交通事故"/><CUS_JTSJ nameCN="具体时间" value="2014年4月29日"/></CUS_SJ><CUS_SJ nameCN="时间"><CUS_YW nameCN="原文" value="2、证人罗某江证言证实：2014年4月29日晚上十点过钟，我和妻子放水浇田，我脚痛就坐在公路旁的护栏石上休息，妻子一人去放水，她走得约一分钟左右，就有一辆从良田方向过来的二轮摩托车从我面前过，一两秒钟，我就听到“嘭”的一声，我朝声音的方向看，看见一辆小车从马场坪方向开过来，当时我知道撞车了，我看那小车没有停车，我用拐杖向小车摇晃，想让车停下来，但是小车加油朝良田街上跑了"/><CUS_SJYW nameCN="时间原文" value="2、证人罗某江证言证实：2014年4月29日晚上十点过钟，我和妻子放水浇田，我脚痛就坐在公路旁的护栏石上休息，妻子一人去放水，她走得约一分钟左右，就有一辆从良田方向过来的二轮摩托车从我面前过，一两秒钟，我就听到“嘭”的一声，我朝声音的方向看，看见一辆小车从马场坪方向开过来，当时我知道撞车了，我看那小车没有停车，我用拐杖向小车摇晃，想让车停下来，但是小车加油朝良田街上跑了"/><CUS_JTSJ nameCN="具体时间" value="2014年4月29日"/></CUS_SJ><CUS_SJ nameCN="时间"><CUS_YW nameCN="原文" value="3、证人陶某相证言证实：2014年4月29日晚上，我开车和潘杰校长从又诗小学返回麻江县城，晚上十点半左右经过新田坳时，看见有群众在路上围观，我停车下来看见一辆二轮摩托车倒在路上，驾驶员躺在摩托车旁边，伤得很严重，还有一个伤员在左边的路坎下面，听旁群众说好象是面包车撞的，面包车已经朝良田街上跑了，于是我就报警了，我还拿得车上的三角警示牌摆在路上，一直等到警察来了我才离开的"/><CUS_SJYW nameCN="时间原文" value="3、证人陶某相证言证实：2014年4月29日晚上，我开车和潘杰校长从又诗小学返回麻江县城，晚上十点半左右经过新田坳时，看见有群众在路上围观，我停车下来看见一辆二轮摩托车倒在路上，驾驶员躺在摩托车旁边，伤得很严重，还有一个伤员在左边的路坎下面，听旁群众说好象是面包车撞的，面包车已经朝良田街上跑了，于是我就报警了，我还拿得车上的三角警示牌摆在路上，一直等到警察来了我才离开的"/><CUS_JTSJ nameCN="具体时间" value="2014年4月29日"/></CUS_SJ><CUS_SJ nameCN="时间"><CUS_YW nameCN="原文" value="4、证人施某香证言证实：宋建波是我的儿子，2014年4月29日那天下午4点过钟，我、女儿宋某英乘坐宋建波驾驶的贵JP8385号面包车从甘粑哨去麻江县土桥河我姐夫王某平家吊唁姑妈"/><CUS_SJYW nameCN="时间原文" value="4、证人施某香证言证实：宋建波是我的儿子，2014年4月29日那天下午4点过钟，我、女儿宋某英乘坐宋建波驾驶的贵JP8385号面包车从甘粑哨去麻江县土桥河我姐夫王某平家吊唁姑妈"/><CUS_JTSJ nameCN="具体时间" value="2014年4月29日"/></CUS_SJ><CUS_SJ nameCN="时间"><CUS_YW nameCN="原文" value="5、证人宋某金证言证实：2014年4月29日晚上十点过钟我在麻江汽车站对面找得羊昌坡桐子园姓张的摩托车回两路口，到新田坳路段时，从马场坪方向有一辆小车超车过来，占着我们的线路把我们的摩托车撞了，我就昏过去了"/><CUS_SJYW nameCN="时间原文" value="5、证人宋某金证言证实：2014年4月29日晚上十点过钟我在麻江汽车站对面找得羊昌坡桐子园姓张的摩托车回两路口，到新田坳路段时，从马场坪方向有一辆小车超车过来，占着我们的线路把我们的摩托车撞了，我就昏过去了"/><CUS_JTSJ nameCN="具体时间" value="2014年4月29日"/></CUS_SJ><CUS_SJ nameCN="时间"><CUS_YW nameCN="原文" value="7、贵州省麻江县公安司法鉴定中心出具的（麻）公（司）鉴（尸）字（2014）027号《法医学尸体检验报告》及照片证实医院对张某学抢救记录为：经常规抢救30多分钟，患者未恢复自主心率，双侧瞳孔散大，对光反射消失，颈动脉未扪及波动感，四肢冰冷，行心电图检查回示为直线，与患者家属交代病情，患者家属同意后于2014年4月30日7：05分放弃抢救，宣布死亡，死亡原因脑干功能衰竭"/><CUS_SJYW nameCN="时间原文" value="7、贵州省麻江县公安司法鉴定中心出具的（麻）公（司）鉴（尸）字（2014）027号《法医学尸体检验报告》及照片证实医院对张某学抢救记录为：经常规抢救30多分钟，患者未恢复自主心率，双侧瞳孔散大，对光反射消失，颈动脉未扪及波动感，四肢冰冷，行心电图检查回示为直线，与患者家属交代病情，患者家属同意后于2014年4月30日7：05分放弃抢救，宣布死亡，死亡原因脑干功能衰竭"/><CUS_JTSJ nameCN="具体时间" value="2014年4月30日"/></CUS_SJ><CUS_SJ nameCN="时间"><CUS_YW nameCN="原文" value="12、麻江县公安局交通警察大队出具的《常住人口基本信息》证实被告人宋建波生于1991年12月11日"/><CUS_SJYW nameCN="时间原文" value="12、麻江县公安局交通警察大队出具的《常住人口基本信息》证实被告人宋建波生于1991年12月11日"/><CUS_JTSJ nameCN="具体时间" value="1991年12月11日"/></CUS_SJ><CUS_SJ nameCN="时间"><CUS_YW nameCN="原文" value="即自2014年12月4日起至2018年6月3日止"/><CUS_SJYW nameCN="时间原文" value="即自2014年12月4日起至2018年6月3日止"/><CUS_JTSJ nameCN="具体时间" value="2014年12月4日"/></CUS_SJ><title value="宋建波犯交通肇事罪"/><subTitle value="刑事一审判决书"/><slzq value="54"/></QW></writ>